Workbook

Sheet EXECUTIVE DASHBOARD
A1: MASTER SEO MATRIX 2026 — chatbot.thuexemaynguyentu.com
A2: Ngày dữ liệu: 2026-11-01 · Nguồn: repository + HTML build · Search Console: NOT CONNECTED · Mọi giá trị dưới đây là công thức tham chiếu các sheet.
A4: KPI | B4: Giá trị | C4: Công thức / nguồn | D4: Ghi chú
A5: Tổng URL kiểm kê | B5: =COUNTA('URL INVENTORY'!A:A)-1 | C5: URL INVENTORY: COUNTA('URL INVENTORY'!A:A)-1 | D5: Hợp nhất sitemap + build + link graph + manifest
A6: URL trong sitemap | B6: =COUNTIF('URL INVENTORY'!E:E,"Có") | C6: URL INVENTORY: COUNTIF('URL INVENTORY'!E:E,"Có")
A7: URL có file build | B7: =COUNTIF('URL INVENTORY'!F:F,"Có") | C7: URL INVENTORY: COUNTIF('URL INVENTORY'!F:F,"Có")
A8: URL có ≥ 1 trang liên kết vào | B8: =COUNTIF('URL INVENTORY'!G:G,">0") | C8: URL INVENTORY: COUNTIF('URL INVENTORY'!G:G,">0")
A9: URL đối soát OK (≥ 3 nguồn) | B9: =COUNTIF('URL INVENTORY'!K:K,"OK") | C9: URL INVENTORY: COUNTIF('URL INVENTORY'!K:K,"OK")
A10: URL đã kiểm tra HTTP live = 200 | B10: =COUNTIF('URL INVENTORY'!I:I,"200*") | C10: URL INVENTORY: COUNTIF('URL INVENTORY'!I:I,"200*") | D10: Mẫu 2026-10-28/29
A11: Bài viết | B11: =COUNTIF('URL INVENTORY'!C:C,"Bài viết") | C11: URL INVENTORY: COUNTIF('URL INVENTORY'!C:C,"Bài viết")
A12: Phân loại KEEP | B12: =COUNTIF('URL INVENTORY'!L:L,"KEEP") | C12: URL INVENTORY: COUNTIF('URL INVENTORY'!L:L,"KEEP")
A13: Phân loại IMPROVE | B13: =COUNTIF('URL INVENTORY'!L:L,"IMPROVE") | C13: URL INVENTORY: COUNTIF('URL INVENTORY'!L:L,"IMPROVE")
A14: Phân loại EXPAND | B14: =COUNTIF('URL INVENTORY'!L:L,"EXPAND") | C14: URL INVENTORY: COUNTIF('URL INVENTORY'!L:L,"EXPAND")
A15: Phân loại CONSOLIDATE-CANDIDATE | B15: =COUNTIF('URL INVENTORY'!L:L,"CONSOLIDATE-CANDIDATE") | C15: URL INVENTORY: COUNTIF('URL INVENTORY'!L:L,"CONSOLIDATE-CANDIDATE")
A16: Phân loại REDIRECT-CANDIDATE | B16: =COUNTIF('URL INVENTORY'!L:L,"REDIRECT-CANDIDATE") | C16: URL INVENTORY: COUNTIF('URL INVENTORY'!L:L,"REDIRECT-CANDIDATE")
A17: Phân loại NOINDEX-CANDIDATE | B17: =COUNTIF('URL INVENTORY'!L:L,"NOINDEX-CANDIDATE") | C17: URL INVENTORY: COUNTIF('URL INVENTORY'!L:L,"NOINDEX-CANDIDATE")
A18: Nhóm từ khóa NEW CONTENT (đề xuất) | B18: =COUNTIF('KEYWORD GAP'!N:N,"NEW CONTENT*") | C18: KEYWORD GAP: COUNTIF('KEYWORD GAP'!N:N,"NEW CONTENT*") | D18: Owner duyệt
A19: QA proxy trung bình (/100) | B19: =ROUND(AVERAGE('QA RESULTS'!K:K),1) | C19: QA RESULTS: ROUND(AVERAGE('QA RESULTS'!K:K),1) | D19: Proxy tự động
A20: Tỉ lệ URL đạt QA proxy ≥ 85 | B20: =ROUND(COUNTIF('QA RESULTS'!K:K,">=85")/COUNT('QA RESULTS'!K:K),3) | C20: QA RESULTS: ROUND(COUNTIF('QA RESULTS'!K:K,">=85")/COUNT('QA RESULTS'!K:K),3)
A21: QA nhà máy trung bình (bài) | B21: =ROUND(AVERAGE('QA RESULTS'!M:M),1) | C21: QA RESULTS: ROUND(AVERAGE('QA RESULTS'!M:M),1) | D21: tools/article-qa.mjs
A22: Từ khóa trong Keyword Master | B22: =COUNTA('KEYWORD MASTER'!A:A)-2 | C22: KEYWORD MASTER: COUNTA('KEYWORD MASTER'!A:A)-2 | D22: Trừ dòng ghi chú + tiêu đề
A23: Từ khóa có volume đo được | B23: =COUNT('KEYWORD MASTER'!E:E) | C23: KEYWORD MASTER: COUNT('KEYWORD MASTER'!E:E) | D23: Ô N/A không tính
A24: Truy vấn SERP đã chụp (có vị trí #1) | B24: =COUNTIF('COMPETITOR SERP'!C:C,1) | C24: COMPETITOR SERP: COUNTIF('COMPETITOR SERP'!C:C,1)
A25: Lượt website này xuất hiện trong SERP chụp | B25: =COUNTIF('COMPETITOR SERP'!G:G,"website này") | C25: COMPETITOR SERP: COUNTIF('COMPETITOR SERP'!G:G,"website này") | D25: Một thời điểm
A26: Kiểm tra kỹ thuật FAIL | B26: =COUNTIF('TECHNICAL SEO AUDIT'!H:H,"FAIL") | C26: TECHNICAL SEO AUDIT: COUNTIF('TECHNICAL SEO AUDIT'!H:H,"FAIL")
A27: Kiểm tra kỹ thuật WARN | B27: =COUNTIF('TECHNICAL SEO AUDIT'!H:H,"WARN") | C27: TECHNICAL SEO AUDIT: COUNTIF('TECHNICAL SEO AUDIT'!H:H,"WARN")
A28: LCP lab tệ nhất (ms) | B28: =_xlfn.MAXIFS('TECHNICAL SEO AUDIT'!F:F,'TECHNICAL SEO AUDIT'!B:B,"Core Web Vitals (LAB)",'TECHNICAL SEO AUDIT'!C:C,"LCP*") | C28: TECHNICAL SEO AUDIT: _xlfn.MAXIFS('TECHNICAL SEO AUDIT'!F:F,'TECHNICAL SEO AUDIT'!B:B,"Core Web Vitals (LAB)",'TECHNICAL SEO AUDIT'!C:C,"LCP*") | D28: LAB, ngưỡng 2.500
A29: Trang lỗi structured data | B29: =COUNTIF('STRUCTURED DATA'!H:H,"LỖI") | C29: STRUCTURED DATA: COUNTIF('STRUCTURED DATA'!H:H,"LỖI")
A30: Bài có ảnh đại diện LIVE | B30: =COUNTIF('IMAGE SEO'!C:C,"LIVE_VERIFIED") | C30: IMAGE SEO: COUNTIF('IMAGE SEO'!C:C,"LIVE_VERIFIED")
A31: Bài IMAGE PENDING | B31: =COUNTIF('IMAGE SEO'!C:C,"IMAGE PENDING") | C31: IMAGE SEO: COUNTIF('IMAGE SEO'!C:C,"IMAGE PENDING") | D31: Nhà máy ảnh tạm dừng
A32: Trang mồ côi nội dung | B32: =COUNTIF('INTERNAL LINK MATRIX'!M:M,"Có") | C32: INTERNAL LINK MATRIX: COUNTIF('INTERNAL LINK MATRIX'!M:M,"Có")
A33: Vào ngữ cảnh TB / bài | B33: =ROUND(AVERAGEIF('INTERNAL LINK MATRIX'!B:B,"Bài viết",'INTERNAL LINK MATRIX'!E:E),1) | C33: INTERNAL LINK MATRIX: ROUND(AVERAGEIF('INTERNAL LINK MATRIX'!B:B,"Bài viết",'INTERNAL LINK MATRIX'!E:E),1)
A34: Nhóm CONSOLIDATE-CANDIDATE (cannibalization) | B34: =COUNTIF('CANNIBALIZATION'!G:G,"CONSOLIDATE-CANDIDATE") | C34: CANNIBALIZATION: COUNTIF('CANNIBALIZATION'!G:G,"CONSOLIDATE-CANDIDATE")
A35: Backlog chương trình P0 | B35: =COUNTIFS('PRIORITY BACKLOG'!A:A,"Chương trình",'PRIORITY BACKLOG'!C:C,"P0") | C35: PRIORITY BACKLOG: COUNTIFS('PRIORITY BACKLOG'!A:A,"Chương trình",'PRIORITY BACKLOG'!C:C,"P0")
A36: Backlog chương trình P1 | B36: =COUNTIFS('PRIORITY BACKLOG'!A:A,"Chương trình",'PRIORITY BACKLOG'!C:C,"P1") | C36: PRIORITY BACKLOG: COUNTIFS('PRIORITY BACKLOG'!A:A,"Chương trình",'PRIORITY BACKLOG'!C:C,"P1")
A37: Backlog chương trình P2 | B37: =COUNTIFS('PRIORITY BACKLOG'!A:A,"Chương trình",'PRIORITY BACKLOG'!C:C,"P2") | C37: PRIORITY BACKLOG: COUNTIFS('PRIORITY BACKLOG'!A:A,"Chương trình",'PRIORITY BACKLOG'!C:C,"P2")
A38: Backlog chương trình P3 | B38: =COUNTIFS('PRIORITY BACKLOG'!A:A,"Chương trình",'PRIORITY BACKLOG'!C:C,"P3") | C38: PRIORITY BACKLOG: COUNTIFS('PRIORITY BACKLOG'!A:A,"Chương trình",'PRIORITY BACKLOG'!C:C,"P3")
A39: URL còn việc mở (OPEN) | B39: =COUNTIF('URL INVENTORY'!N:N,"OPEN") | C39: URL INVENTORY: COUNTIF('URL INVENTORY'!N:N,"OPEN") | D39: work-queue.csv
A40: URL đã sửa và kiểm tra live (DONE_LIVE) | B40: =COUNTIF('URL INVENTORY'!N:N,"DONE_LIVE") | C40: URL INVENTORY: COUNTIF('URL INVENTORY'!N:N,"DONE_LIVE") | D40: work-status.json
A41: URL đã rà soát, không cần đổi (REVIEWED_OK) | B41: =COUNTIF('URL INVENTORY'!N:N,"REVIEWED_OK") | C41: URL INVENTORY: COUNTIF('URL INVENTORY'!N:N,"REVIEWED_OK") | D41: work-status.json
A42: URL không có việc mở (OK) | B42: =COUNTIF('URL INVENTORY'!N:N,"OK") | C42: URL INVENTORY: COUNTIF('URL INVENTORY'!N:N,"OK")
A43: URL chờ chủ sở hữu (REVIEW_REQUIRED) | B43: =COUNTIF('URL INVENTORY'!N:N,"REVIEW_REQUIRED") | C43: URL INVENTORY: COUNTIF('URL INVENTORY'!N:N,"REVIEW_REQUIRED") | D43: review-required.csv
A44: Search Console | B44: ='GSC PERFORMANCE'!B2 | C44: GSC PERFORMANCE: 'GSC PERFORMANCE'!B2 | D44: Owner kết nối
A45: Hreflang | B45: ='HREFLANG MATRIX'!E2 | C45: HREFLANG MATRIX: 'HREFLANG MATRIX'!E2 | D45: Site đơn ngữ

Sheet URL INVENTORY
A1: URL | B1: Article ID | C1: Loại trang | D1: Danh mục | E1: Trong sitemap | F1: Có file build | G1: Số trang liên kết vào (mọi vị trí) | H1: Trong manifest bài | I1: HTTP live (ngày) | J1: Số nguồn xác nhận | K1: Đối soát | L1: Phân loại | M1: Lý do phân loại | N1: Trạng thái công việc | O1: Ưu tiên công việc | P1: Mã việc mở
A2: https://chatbot.thuexemaynguyentu.com/ | B2: N/A | C2: Trang chủ (website) | D2: N/A | E2: Có | F2: Có | G2: 2169 | H2: Không áp dụng | I2: 200 (2026-10-29) | J2: 4 | K2: OK | L2: KEEP | M2: QA proxy ≥ 85, không cờ mở, không cảnh báo nội dung | N2: DONE_LIVE | O2: — | P2: Không
A3: https://chatbot.thuexemaynguyentu.com/agent/ | B3: N/A | C3: Ứng dụng Agent (chat) | D3: N/A | E3: Có | F3: Có | G3: 2168 | H3: Không áp dụng | I3: 200 (2026-10-29) | J3: 3 | K3: OK | L3: KEEP | M3: QA proxy ≥ 85, không cờ mở, không cảnh báo nội dung | N3: REVIEWED_OK | O3: — | P3: Không
A4: https://chatbot.thuexemaynguyentu.com/blog/ | B4: N/A | C4: Blog home | D4: N/A | E4: Có | F4: Có | G4: 2169 | H4: Không áp dụng | I4: 200 (2026-10-28) | J4: 3 | K4: OK | L4: KEEP | M4: QA proxy ≥ 85, không cờ mở, không cảnh báo nội dung | N4: OPEN | O4: P1 | P4: HUB-CONTENT
A5: https://chatbot.thuexemaynguyentu.com/chinh-sach/ | B5: N/A | C5: Trang chính sách thuê xe | D5: N/A | E5: Có | F5: Có | G5: 2169 | H5: Không áp dụng | I5: 200 (2026-10-28) | J5: 4 | K5: OK | L5: KEEP | M5: QA proxy ≥ 85, không cờ mở, không cảnh báo nội dung | N5: OK | O5: — | P5: Không
A6: https://chatbot.thuexemaynguyentu.com/doi-tac/ | B6: N/A | C6: Trang đối tác (B2B) | D6: N/A | E6: Có | F6: Có | G6: 2169 | H6: Không áp dụng | I6: Chưa kiểm tra live trong lô này | J6: 4 | K6: OK | L6: KEEP | M6: QA proxy ≥ 85, không cờ mở, không cảnh báo nội dung | N6: OK | O6: — | P6: Không
A7: https://chatbot.thuexemaynguyentu.com/gia-thue/ | B7: N/A | C7: Trang chuyển đổi (giá) | D7: N/A | E7: Có | F7: Có | G7: 2169 | H7: Không áp dụng | I7: 200 (2026-10-28) | J7: 4 | K7: OK | L7: KEEP | M7: QA proxy ≥ 85, không cờ mở, không cảnh báo nội dung | N7: DONE_LIVE | O7: — | P7: Không
A8: https://chatbot.thuexemaynguyentu.com/gioi-thieu/ | B8: N/A | C8: Trang giới thiệu (E-E-A-T) | D8: N/A | E8: Có | F8: Có | G8: 2169 | H8: Không áp dụng | I8: 200 (2026-10-28) | J8: 4 | K8: OK | L8: KEEP | M8: QA proxy ≥ 85, không cờ mở, không cảnh báo nội dung | N8: OK | O8: — | P8: Không
A9: https://chatbot.thuexemaynguyentu.com/lien-he/ | B9: N/A | C9: Trang chuyển đổi (liên hệ) | D9: N/A | E9: Có | F9: Có | G9: 2169 | H9: Không áp dụng | I9: 200 (2026-10-28) | J9: 4 | K9: OK | L9: KEEP | M9: QA proxy ≥ 85, không cờ mở, không cảnh báo nội dung | N9: DONE_LIVE | O9: — | P9: Không
A10: https://chatbot.thuexemaynguyentu.com/privacy/ | B10: N/A | C10: Pháp lý | D10: N/A | E10: Có | F10: Có | G10: 2169 | H10: Không áp dụng | I10: Chưa kiểm tra live trong lô này | J10: 4 | K10: OK | L10: KEEP | M10: QA proxy ≥ 85, không cờ mở, không cảnh báo nội dung | N10: OK | O10: — | P10: Không
A11: https://chatbot.thuexemaynguyentu.com/terms/ | B11: N/A | C11: Pháp lý | D11: N/A | E11: Có | F11: Có | G11: 2169 | H11: Không áp dụng | I11: Chưa kiểm tra live trong lô này | J11: 4 | K11: OK | L11: KEEP | M11: QA proxy ≥ 85, không cờ mở, không cảnh báo nội dung | N11: OK | O11: — | P11: Không
A12: https://chatbot.thuexemaynguyentu.com/blog/an-toan/ | B12: N/A | C12: Hub danh mục | D12: N/A | E12: Có | F12: Có | G12: 2169 | H12: Không áp dụng | I12: Chưa kiểm tra live trong lô này | J12: 3 | K12: OK | L12: KEEP | M12: QA proxy ≥ 85, không cờ mở, không cảnh báo nội dung | N12: OPEN | O12: P1 | P12: HUB-CONTENT
A13: https://chatbot.thuexemaynguyentu.com/blog/app/ | B13: N/A | C13: Hub danh mục | D13: N/A | E13: Có | F13: Có | G13: 2169 | H13: Không áp dụng | I13: Chưa kiểm tra live trong lô này | J13: 3 | K13: OK | L13: KEEP | M13: QA proxy ≥ 85, không cờ mở, không cảnh báo nội dung | N13: OPEN | O13: P1 | P13: HUB-CONTENT
... A2170: https://chatbot.thuexemaynguyentu.com/blog/xe-dien/pin-xe/page/2/ | B2170: N/A | C2170: Hub chủ đề con (phân trang) | D2170: N/A | E2170: Có | F2170: Có | G2170: 1 | H2170: Không áp dụng | I2170: Chưa kiểm tra live trong lô này | J2170: 3 | K2170: OK | L2170: KEEP | M2170: QA proxy ≥ 85, không cờ mở, không cảnh báo nội dung | N2170: DONE_LIVE | O2170: — | P2170: Không

Sheet KEYWORD MASTER
A1: Nguồn: docs/seo/battle/02-keyword-master-matrix.csv — Volume A: OpenRush research_keywords (Vietnam, Vietnamese, 2026-10-14); Volume B/KD: OpenSEO get_keyword_metrics (DataForSEO, 2026-10-14/2026-10-15) — hai nguồn khác nhau, không gộp. Ô N/A = công cụ không trả số / chưa đo.
A2: Từ khóa | B2: Phạm vi | C2: Cụm | D2: Nhóm engine | E2: Volume A (keyword-demand) | F2: Nguồn A | G2: Volume B (DataForSEO) | H2: KD | I2: Ý định công cụ | J2: Ý định SERP | K2: Tính năng SERP | L2: Vị trí website | M2: Website chị em | N2: Đối thủ #1 | O2: URL tham chiếu | P2: Top 3 | Q2: Độ phủ | R2: Trang đích | S2: Hành động | T2: Điểm ưu tiên | U2: Hạng | V2: Độ tin cậy dữ liệu
A3: xe máy điện vinfast | B3: UNVERIFIED | C3: N/A | D3: N/A | E3: 135000 | F3: OpenRush research_keywords 2026-10-14 | G3: N/A | H3: N/A | I3: transactional | J3: N/A | K3: N/A | L3: N/A | M3: N/A | N3: N/A | O3: N/A | P3: N/A | Q3: N/A | R3: N/A | S3: N/A | T3: 0 | U3: N/A | V3: Đo được (1 công cụ)
A4: thuê xe máy | B4: IN-SCOPE | C4: K02 | D4: thue-xe-may | E4: 33100 | F4: OpenRush research_keywords 2026-10-14 | G4: 33100 | H4: 11 | I4: transactional | J4: Giao dịch – địa phương | K4: local pack | L4: N/A | M4: N/A | N4: alothuexemay.com | O4: https://alothuexemay.com/ | P4: #1 alothuexemay.com; #2 motogo.vn; #3 www.facebook.com | Q4: Đã có bài | R4: /blog/thue-xe/thue-xe-may-gia-re/ | S4: Giữ nguyên | T4: 0 | U4: N/A | V4: Đo được (2 công cụ)
A5: phạt nguội xe máy | B5: IN-SCOPE | C5: K09 | D5: phat-nguoi-xe-may | E5: 27100 | F5: OpenRush research_keywords 2026-10-14 | G5: 27100 | H5: 21 | I5: informational | J5: Hỗn hợp (thương mại + thông tin) | K5: AI Overview, PAA | L5: N/A | M5: N/A | N5: phatnguoi.com.vn | O5: https://phatnguoi.com.vn/ | P5: #1 phatnguoi.com.vn; #2 canhsatgiaothong.bocongan.gov.vn; #3 checkphatnguoi.com.vn | Q5: Đã có bài | R5: /blog/an-toan/den-do-va-camera-phat-nguoi/ | S5: Giữ nguyên | T5: 0 | U5: N/A | V5: Đo được (2 công cụ)
A6: giá xe máy điện vinfast | B6: OUT-INTENT | C6: N/A | D6: N/A | E6: 22200 | F6: OpenRush research_keywords 2026-10-14 | G6: N/A | H6: N/A | I6: commercial | J6: N/A | K6: N/A | L6: N/A | M6: N/A | N6: N/A | O6: N/A | P6: N/A | Q6: N/A | R6: N/A | S6: N/A | T6: 0 | U6: N/A | V6: Đo được (1 công cụ)
A7: phụ tùng xe máy | B7: OUT-INTENT | C7: N/A | D7: N/A | E7: 18100 | F7: OpenRush research_keywords 2026-10-14 | G7: N/A | H7: N/A | I7: transactional | J7: N/A | K7: N/A | L7: N/A | M7: N/A | N7: N/A | O7: N/A | P7: N/A | Q7: N/A | R7: N/A | S7: N/A | T7: 0 | U7: N/A | V7: Đo được (1 công cụ)
A8: sh mode giá | B8: OUT-INTENT | C8: N/A | D8: N/A | E8: 14800 | F8: OpenRush research_keywords 2026-10-14 | G8: N/A | H8: N/A | I8: commercial | J8: N/A | K8: N/A | L8: N/A | M8: N/A | N8: N/A | O8: N/A | P8: N/A | Q8: N/A | R8: N/A | S8: N/A | T8: 0 | U8: N/A | V8: Đo được (1 công cụ)
A9: thi bằng lái xe máy a1 | B9: OUT-INTENT | C9: N/A | D9: N/A | E9: 14800 | F9: OpenRush research_keywords 2026-10-14 | G9: N/A | H9: N/A | I9: informational | J9: N/A | K9: N/A | L9: N/A | M9: N/A | N9: N/A | O9: N/A | P9: N/A | Q9: N/A | R9: N/A | S9: N/A | T9: 0 | U9: N/A | V9: Đo được (1 công cụ)
A10: vinfast xe máy điện | B10: UNVERIFIED | C10: N/A | D10: N/A | E10: 14800 | F10: OpenRush research_keywords 2026-10-14 | G10: N/A | H10: N/A | I10: transactional | J10: N/A | K10: N/A | L10: N/A | M10: N/A | N10: N/A | O10: N/A | P10: N/A | Q10: N/A | R10: N/A | S10: N/A | T10: 0 | U10: N/A | V10: Đo được (1 công cụ)
A11: cửa hàng xe máy | B11: OUT-INTENT | C11: N/A | D11: N/A | E11: 12100 | F11: OpenRush research_keywords 2026-10-14 | G11: N/A | H11: N/A | I11: navigational | J11: N/A | K11: N/A | L11: N/A | M11: N/A | N11: N/A | O11: N/A | P11: N/A | Q11: N/A | R11: N/A | S11: N/A | T11: 0 | U11: N/A | V11: Đo được (1 công cụ)
A12: siêu xe | B12: OUT-INTENT | C12: N/A | D12: N/A | E12: 12100 | F12: OpenRush research_keywords 2026-10-14 | G12: N/A | H12: N/A | I12: informational | J12: N/A | K12: N/A | L12: N/A | M12: N/A | N12: N/A | O12: N/A | P12: N/A | Q12: N/A | R12: N/A | S12: N/A | T12: 0 | U12: N/A | V12: Đo được (1 công cụ)
A13: thi bằng lái xe máy | B13: OUT-INTENT | C13: N/A | D13: N/A | E13: 12100 | F13: OpenRush research_keywords 2026-10-14 | G13: N/A | H13: N/A | I13: informational | J13: N/A | K13: N/A | L13: N/A | M13: N/A | N13: N/A | O13: N/A | P13: N/A | Q13: N/A | R13: N/A | S13: N/A | T13: 0 | U13: N/A | V13: Đo được (1 công cụ)
A14: giá xe honda | B14: OUT-INTENT | C14: N/A | D14: N/A | E14: 9900 | F14: OpenRush research_keywords 2026-10-14 | G14: N/A | H14: N/A | I14: commercial | J14: N/A | K14: N/A | L14: N/A | M14: N/A | N14: N/A | O14: N/A | P14: N/A | Q14: N/A | R14: N/A | S14: N/A | T14: 0 | U14: N/A | V14: Đo được (1 công cụ)
A15: xe máy 50cc | B15: UNVERIFIED | C15: N/A | D15: N/A | E15: 9900 | F15: OpenRush research_keywords 2026-10-14 | G15: N/A | H15: N/A | I15: transactional | J15: N/A | K15: N/A | L15: N/A | M15: N/A | N15: N/A | O15: N/A | P15: N/A | Q15: N/A | R15: N/A | S15: N/A | T15: 0 | U15: N/A | V15: Đo được (1 công cụ)
A16: cho thuê xe máy | B16: IN-SCOPE | C16: K02 | D16: thue-xe-may | E16: 8100 | F16: OpenRush research_keywords 2026-10-14 | G16: 8100 | H16: 0 | I16: commercial | J16: N/A | K16: N/A | L16: N/A | M16: N/A | N16: N/A | O16: N/A | P16: N/A | Q16: Đã có bài | R16: /blog/thue-xe/thue-xe-may-gia-re/ | S16: Giữ nguyên | T16: 0 | U16: N/A | V16: Đo được (2 công cụ)
A17: thuê xe máy đà lạt | B17: OUT-MARKET | C17: N/A | D17: N/A | E17: 8100 | F17: OpenRush research_keywords 2026-10-14 | G17: N/A | H17: N/A | I17: commercial | J17: N/A | K17: N/A | L17: N/A | M17: N/A | N17: N/A | O17: N/A | P17: N/A | Q17: N/A | R17: N/A | S17: N/A | T17: 0 | U17: N/A | V17: Đo được (1 công cụ)
A18: thuê xe máy hà nội | B18: SISTER | C18: LANDSCAPE | D18: N/A | E18: 8100 | F18: OpenRush research_keywords 2026-10-14 | G18: N/A | H18: N/A | I18: commercial | J18: Giao dịch – địa phương | K18: AI Overview, local pack | L18: N/A | M18: N/A | N18: motogo.vn | O18: https://motogo.vn/ha-noi/ | P18: #1 motogo.vn; #2 www.facebook.com; #3 hanoibiker.com | Q18: N/A | R18: N/A | S18: N/A | T18: 0 | U18: N/A | V18: Đo được (1 công cụ)
A19: bằng lái xe máy | B19: IN-SCOPE | C19: K09 | D19: bang-lai-xe-may | E19: 6600 | F19: OpenRush research_keywords 2026-10-14 | G19: 6600 | H19: 0 | I19: informational | J19: Giao dịch – địa phương | K19: AI Overview, local pack | L19: N/A | M19: N/A | N19: hoclaixeotohcm.com | O19: https://hoclaixeotohcm.com/150-cau-hoi-thi-bang-lai-xe-may | P19: #1 hoclaixeotohcm.com; #2 www.thibanglaixemaysaigon.com; #3 tinhte.vn | Q19: Đã có bài | R19: /blog/thue-xe/bang-lai-a1-va-thue-xe-may/ | S19: Giữ nguyên | T19: 0 | U19: N/A | V19: Đo được (2 công cụ)
A20: bánh xe | B20: OUT-INTENT | C20: N/A | D20: N/A | E20: 6600 | F20: OpenRush research_keywords 2026-10-14 | G20: N/A | H20: N/A | I20: informational | J20: N/A | K20: N/A | L20: N/A | M20: N/A | N20: N/A | O20: N/A | P20: N/A | Q20: N/A | R20: N/A | S20: N/A | T20: 0 | U20: N/A | V20: Đo được (1 công cụ)
A21: dấu hiệu xe máy cần thay nhớt | B21: OUT-INTENT | C21: N/A | D21: N/A | E21: 6600 | F21: OpenRush research_keywords 2026-10-14 | G21: N/A | H21: N/A | I21: informational | J21: N/A | K21: N/A | L21: N/A | M21: N/A | N21: N/A | O21: N/A | P21: N/A | Q21: N/A | R21: N/A | S21: N/A | T21: 0 | U21: N/A | V21: Đo được (1 công cụ)
A22: định vị xe máy | B22: OUT-INTENT | C22: N/A | D22: N/A | E22: 6600 | F22: OpenRush research_keywords 2026-10-14 | G22: N/A | H22: N/A | I22: navigational | J22: N/A | K22: N/A | L22: N/A | M22: N/A | N22: N/A | O22: N/A | P22: N/A | Q22: N/A | R22: N/A | S22: N/A | T22: 0 | U22: N/A | V22: Đo được (1 công cụ)
A23: giá xe máy honda | B23: OUT-INTENT | C23: N/A | D23: N/A | E23: 6600 | F23: OpenRush research_keywords 2026-10-14 | G23: N/A | H23: N/A | I23: transactional | J23: N/A | K23: N/A | L23: N/A | M23: N/A | N23: N/A | O23: N/A | P23: N/A | Q23: N/A | R23: N/A | S23: N/A | T23: 0 | U23: N/A | V23: Đo được (1 công cụ)
A24: không bằng lái xe máy phạt bao nhiêu | B24: IN-SCOPE | C24: K09 | D24: khong-bang-lai-xe-may-phat-bao-nhieu | E24: 6600 | F24: OpenRush research_keywords 2026-10-14 | G24: 6600 | H24: 0 | I24: informational | J24: N/A | K24: N/A | L24: N/A | M24: N/A | N24: N/A | O24: N/A | P24: N/A | Q24: Đã có bài | R24: /blog/an-toan/di-xe-khong-giay-phep/ | S24: Giữ nguyên | T24: 0 | U24: N/A | V24: Đo được (2 công cụ)
A25: sửa chữa xe máy | B25: OUT-INTENT | C25: N/A | D25: N/A | E25: 6600 | F25: OpenRush research_keywords 2026-10-14 | G25: N/A | H25: N/A | I25: commercial | J25: N/A | K25: N/A | L25: N/A | M25: N/A | N25: N/A | O25: N/A | P25: N/A | Q25: N/A | R25: N/A | S25: N/A | T25: 0 | U25: N/A | V25: Đo được (1 công cụ)
A26: thuê xe máy đà nẵng | B26: OUT-MARKET | C26: N/A | D26: N/A | E26: 6600 | F26: OpenRush research_keywords 2026-10-14 | G26: N/A | H26: N/A | I26: commercial | J26: N/A | K26: N/A | L26: N/A | M26: N/A | N26: N/A | O26: N/A | P26: N/A | Q26: N/A | R26: N/A | S26: N/A | T26: 0 | U26: N/A | V26: Đo được (1 công cụ)
A27: thuê xe máy nha trang | B27: OUT-MARKET | C27: N/A | D27: N/A | E27: 6600 | F27: OpenRush research_keywords 2026-10-14 | G27: N/A | H27: N/A | I27: transactional | J27: N/A | K27: N/A | L27: N/A | M27: N/A | N27: N/A | O27: N/A | P27: N/A | Q27: N/A | R27: N/A | S27: N/A | T27: 0 | U27: N/A | V27: Đo được (1 công cụ)
A28: xe đạp martin | B28: OUT-INTENT | C28: N/A | D28: N/A | E28: 6600 | F28: OpenRush research_keywords 2026-10-14 | G28: N/A | H28: N/A | I28: transactional | J28: N/A | K28: N/A | L28: N/A | M28: N/A | N28: N/A | O28: N/A | P28: N/A | Q28: N/A | R28: N/A | S28: N/A | T28: 0 | U28: N/A | V28: Đo được (1 công cụ)
A29: xe máy yamaha | B29: OUT-INTENT | C29: N/A | D29: N/A | E29: 6600 | F29: OpenRush research_keywords 2026-10-14 | G29: N/A | H29: N/A | I29: transactional | J29: N/A | K29: N/A | L29: N/A | M29: N/A | N29: N/A | O29: N/A | P29: N/A | Q29: N/A | R29: N/A | S29: N/A | T29: 0 | U29: N/A | V29: Đo được (1 công cụ)
A30: bánh xe đẩy | B30: OUT-INTENT | C30: N/A | D30: N/A | E30: 5400 | F30: OpenRush research_keywords 2026-10-14 | G30: N/A | H30: N/A | I30: transactional | J30: N/A | K30: N/A | L30: N/A | M30: N/A | N30: N/A | O30: N/A | P30: N/A | Q30: N/A | R30: N/A | S30: N/A | T30: 0 | U30: N/A | V30: Đo được (1 công cụ)
A31: giá xe ab 125 | B31: OUT-INTENT | C31: N/A | D31: N/A | E31: 5400 | F31: OpenRush research_keywords 2026-10-14 | G31: N/A | H31: N/A | I31: transactional | J31: N/A | K31: N/A | L31: N/A | M31: N/A | N31: N/A | O31: N/A | P31: N/A | Q31: N/A | R31: N/A | S31: N/A | T31: 0 | U31: N/A | V31: Đo được (1 công cụ)
A32: k có bằng lái xe máy phạt bao nhiêu | B32: IN-SCOPE | C32: K09 | D32: khong-bang-lai-xe-may-phat-bao-nhieu | E32: 5400 | F32: OpenRush research_keywords 2026-10-14 | G32: 5400 | H32: 0 | I32: commercial | J32: N/A | K32: N/A | L32: N/A | M32: N/A | N32: N/A | O32: N/A | P32: N/A | Q32: Đã có bài | R32: /blog/an-toan/di-xe-khong-giay-phep/ | S32: Giữ nguyên | T32: 0 | U32: N/A | V32: Đo được (2 công cụ)
A33: không có bằng lái xe máy phạt bao nhiêu | B33: IN-SCOPE | C33: K09 | D33: khong-bang-lai-xe-may-phat-bao-nhieu | E33: 5400 | F33: OpenRush research_keywords 2026-10-14 | G33: 5400 | H33: 0 | I33: informational | J33: Thông tin | K33: AI Overview | L33: N/A | M33: N/A | N33: www.greensm.com | O33: https://www.greensm.com/vn-vi/news/khong-bang-lai-xe-may-phat-bao-nhieu-khi-cong-an-kiem-tra | P33: #1 www.greensm.com; #2 baomoi.com; #3 osakar.com.vn | Q33: Đã có bài | R33: /blog/an-toan/di-xe-khong-giay-phep/ | S33: Giữ nguyên | T33: 0 | U33: N/A | V33: Đo được (2 công cụ)
A34: mức phạt nồng độ cồn xe máy | B34: IN-SCOPE | C34: K09 | D34: muc-phat-nong-do-con-xe-may | E34: 5400 | F34: OpenRush research_keywords 2026-10-14 | G34: 5400 | H34: 0 | I34: informational | J34: Thông tin | K34: AI Overview | L34: N/A | M34: N/A | N34: teracolongbien.com | O34: https://teracolongbien.com/nong-do-con-phat-bao-nhieu | P34: #1 teracolongbien.com; #2 thuvienphapluat.vn; #3 thuvienphapluat.vn | Q34: Đã có bài | R34: /blog/an-toan/nong-do-con-khi-lai-xe/ | S34: Giữ nguyên | T34: 0 | U34: N/A | V34: Đo được (2 công cụ)
A35: thuê xe máy sài gòn | B35: OUT-MARKET | C35: N/A | D35: N/A | E35: 5400 | F35: OpenRush research_keywords 2026-10-14 | G35: N/A | H35: N/A | I35: commercial | J35: N/A | K35: N/A | L35: N/A | M35: N/A | N35: N/A | O35: N/A | P35: N/A | Q35: N/A | R35: N/A | S35: N/A | T35: 0 | U35: N/A | V35: Đo được (1 công cụ)
A36: vinfast xe máy | B36: UNVERIFIED | C36: N/A | D36: N/A | E36: 5400 | F36: OpenRush research_keywords 2026-10-14 | G36: N/A | H36: N/A | I36: transactional | J36: N/A | K36: N/A | L36: N/A | M36: N/A | N36: N/A | O36: N/A | P36: N/A | Q36: N/A | R36: N/A | S36: N/A | T36: 0 | U36: N/A | V36: Đo được (1 công cụ)
A37: xe điện 3 bánh | B37: OUT-INTENT | C37: N/A | D37: N/A | E37: 5400 | F37: OpenRush research_keywords 2026-10-14 | G37: N/A | H37: N/A | I37: transactional | J37: N/A | K37: N/A | L37: N/A | M37: N/A | N37: N/A | O37: N/A | P37: N/A | Q37: N/A | R37: N/A | S37: N/A | T37: 0 | U37: N/A | V37: Đo được (1 công cụ)
A38: xe điện xmen | B38: OUT-INTENT | C38: N/A | D38: N/A | E38: 5400 | F38: OpenRush research_keywords 2026-10-14 | G38: N/A | H38: N/A | I38: transactional | J38: N/A | K38: N/A | L38: N/A | M38: N/A | N38: N/A | O38: N/A | P38: N/A | Q38: N/A | R38: N/A | S38: N/A | T38: 0 | U38: N/A | V38: Đo được (1 công cụ)
A39: cách sử dụng máy tính thi bằng lái xe a1 | B39: OUT-INTENT | C39: N/A | D39: N/A | E39: 4400 | F39: OpenRush research_keywords 2026-10-14 | G39: N/A | H39: N/A | I39: informational | J39: N/A | K39: N/A | L39: N/A | M39: N/A | N39: N/A | O39: N/A | P39: N/A | Q39: N/A | R39: N/A | S39: N/A | T39: 0 | U39: N/A | V39: Đo được (1 công cụ)
A40: cho thuê xe máy 88 vũng tàu | B40: OUT-INTENT | C40: N/A | D40: N/A | E40: 4400 | F40: OpenRush research_keywords 2026-10-14 | G40: N/A | H40: N/A | I40: transactional | J40: N/A | K40: N/A | L40: N/A | M40: N/A | N40: N/A | O40: N/A | P40: N/A | Q40: N/A | R40: N/A | S40: N/A | T40: 0 | U40: N/A | V40: Đo được (1 công cụ)
A41: giá xe wave | B41: OUT-INTENT | C41: N/A | D41: N/A | E41: 4400 | F41: OpenRush research_keywords 2026-10-14 | G41: N/A | H41: N/A | I41: commercial | J41: N/A | K41: N/A | L41: N/A | M41: N/A | N41: N/A | O41: N/A | P41: N/A | Q41: N/A | R41: N/A | S41: N/A | T41: 0 | U41: N/A | V41: Đo được (1 công cụ)
A42: học bằng lái xe máy | B42: OUT-INTENT | C42: N/A | D42: N/A | E42: 4400 | F42: OpenRush research_keywords 2026-10-14 | G42: N/A | H42: N/A | I42: informational | J42: N/A | K42: N/A | L42: N/A | M42: N/A | N42: N/A | O42: N/A | P42: N/A | Q42: N/A | R42: N/A | S42: N/A | T42: 0 | U42: N/A | V42: Đo được (1 công cụ)
A43: lý thuyết thi bằng lái xe máy có đáp an | B43: OUT-INTENT | C43: N/A | D43: N/A | E43: 4400 | F43: OpenRush research_keywords 2026-10-14 | G43: N/A | H43: N/A | I43: informational | J43: N/A | K43: N/A | L43: N/A | M43: N/A | N43: N/A | O43: N/A | P43: N/A | Q43: N/A | R43: N/A | S43: N/A | T43: 0 | U43: N/A | V43: Đo được (1 công cụ)
A44: thuê xe máy gần đây | B44: LOCAL-PACK | C44: K15 | D44: N/A | E44: 4400 | F44: OpenRush research_keywords 2026-10-14 | G44: N/A | H44: N/A | I44: commercial | J44: Giao dịch – địa phương | K44: AI Overview, PAA | L44: N/A | M44: N/A | N44: motogo.vn | O44: https://motogo.vn/ha-noi/ | P44: #1 motogo.vn; #2 www.facebook.com; #3 chothuexemaytphcm.com | Q44: N/A | R44: N/A | S44: N/A | T44: 0 | U44: N/A | V44: Đo được (1 công cụ)
A45: thuê xe máy quy nhơn | B45: OUT-MARKET | C45: N/A | D45: N/A | E45: 4400 | F45: OpenRush research_keywords 2026-10-14 | G45: N/A | H45: N/A | I45: commercial | J45: N/A | K45: N/A | L45: N/A | M45: N/A | N45: N/A | O45: N/A | P45: N/A | Q45: N/A | R45: N/A | S45: N/A | T45: 0 | U45: N/A | V45: Đo được (1 công cụ)
A46: xe máy điện dat bike | B46: OUT-INTENT | C46: N/A | D46: N/A | E46: 4400 | F46: OpenRush research_keywords 2026-10-14 | G46: N/A | H46: N/A | I46: transactional | J46: N/A | K46: N/A | L46: N/A | M46: N/A | N46: N/A | O46: N/A | P46: N/A | Q46: N/A | R46: N/A | S46: N/A | T46: 0 | U46: N/A | V46: Đo được (1 công cụ)
... A54: giá xe máy | B54: OUT-INTENT | C54: N/A | D54: N/A | E54: 2900 | F54: OpenRush research_keywords 2026-10-14 | G54: N/A | H54: N/A | I54: transactional | J54: N/A | K54: N/A | L54: N/A | M54: N/A | N54: N/A | O54: N/A | P54: N/A | Q54: N/A | R54: N/A | S54: N/A | T54: 0 | U54: N/A | V54: Đo được (1 công cụ)
A55: lỗi không bằng lái xe máy | B55: IN-SCOPE | C55: K09 | D55: khong-bang-lai-xe-may-phat-bao-nhieu | E55: 2900 | F55: OpenRush research_keywords 2026-10-14 | G55: 2900 | H55: 0 | I55: informational | J55: N/A | K55: N/A | L55: N/A | M55: N/A | N55: N/A | O55: N/A | P55: N/A | Q55: Đã có bài | R55: /blog/an-toan/di-xe-khong-giay-phep/ | S55: Giữ nguyên | T55: 0 | U55: N/A | V55: Đo được (2 công cụ)
A56: thuê xe máy vũng tàu | B56: OUT-MARKET | C56: N/A | D56: N/A | E56: 2900 | F56: OpenRush research_keywords 2026-10-14 | G56: N/A | H56: N/A | I56: commercial | J56: N/A | K56: N/A | L56: N/A | M56: N/A | N56: N/A | O56: N/A | P56: N/A | Q56: N/A | R56: N/A | S56: N/A | T56: 0 | U56: N/A | V56: Đo được (1 công cụ)
A57: tìm tên chủ xe qua biển số xe máy online | B57: OUT-INTENT | C57: N/A | D57: N/A | E57: 2900 | F57: OpenRush research_keywords 2026-10-14 | G57: N/A | H57: N/A | I57: navigational | J57: N/A | K57: N/A | L57: N/A | M57: N/A | N57: N/A | O57: N/A | P57: N/A | Q57: N/A | R57: N/A | S57: N/A | T57: 0 | U57: N/A | V57: Đo được (1 công cụ)
A58: xe máy chuyên dùng | B58: OUT-INTENT | C58: N/A | D58: N/A | E58: 2900 | F58: OpenRush research_keywords 2026-10-14 | G58: N/A | H58: N/A | I58: transactional | J58: N/A | K58: N/A | L58: N/A | M58: N/A | N58: N/A | O58: N/A | P58: N/A | Q58: N/A | R58: N/A | S58: N/A | T58: 0 | U58: N/A | V58: Đo được (1 công cụ)
A59: xe máy điện honda mới nhất | B59: OUT-INTENT | C59: N/A | D59: N/A | E59: 2900 | F59: OpenRush research_keywords 2026-10-14 | G59: N/A | H59: N/A | I59: informational | J59: N/A | K59: N/A | L59: N/A | M59: N/A | N59: N/A | O59: N/A | P59: N/A | Q59: N/A | R59: N/A | S59: N/A | T59: 0 | U59: N/A | V59: Đo được (1 công cụ)
A60: cho thuê xe máy đà lạt | B60: OUT-MARKET | C60: N/A | D60: N/A | E60: 2400 | F60: OpenRush research_keywords 2026-10-14 | G60: N/A | H60: N/A | I60: commercial | J60: N/A | K60: N/A | L60: N/A | M60: N/A | N60: N/A | O60: N/A | P60: N/A | Q60: N/A | R60: N/A | S60: N/A | T60: 0 | U60: N/A | V60: Đo được (1 công cụ)
A61: đổi bằng lái xe máy | B61: OUT-INTENT | C61: N/A | D61: N/A | E61: 2400 | F61: OpenRush research_keywords 2026-10-14 | G61: N/A | H61: N/A | I61: transactional | J61: N/A | K61: N/A | L61: N/A | M61: N/A | N61: N/A | O61: N/A | P61: N/A | Q61: N/A | R61: N/A | S61: N/A | T61: 0 | U61: N/A | V61: Đo được (1 công cụ)
A62: giá xe yamaha | B62: OUT-INTENT | C62: N/A | D62: N/A | E62: 2400 | F62: OpenRush research_keywords 2026-10-14 | G62: N/A | H62: N/A | I62: commercial | J62: N/A | K62: N/A | L62: N/A | M62: N/A | N62: N/A | O62: N/A | P62: N/A | Q62: N/A | R62: N/A | S62: N/A | T62: 0 | U62: N/A | V62: Đo được (1 công cụ)
A63: lỗi không gương xe máy | B63: IN-SCOPE | C63: K10 | D63: loi-khong-guong-xe-may | E63: 2400 | F63: OpenRush research_keywords 2026-10-14 | G63: 2400 | H63: 0 | I63: informational | J63: Thông tin | K63: AI Overview | L63: N/A | M63: N/A | N63: www.momo.vn | O63: https://www.momo.vn/phat-nguoi/blog/loi-khong-guong-xe-may-4995 | P63: #1 www.momo.vn; #2 thuvienphapluat.vn; #3 laodong.vn | Q63: Có mục trong bài | R63: /blog/an-toan/loi-khong-guong-xe-may/ | S63: Giữ nguyên | T63: 0 | U63: N/A | V63: Đo được (2 công cụ)
A64: nhớt xe máy | B64: OUT-INTENT | C64: N/A | D64: N/A | E64: 2400 | F64: OpenRush research_keywords 2026-10-14 | G64: N/A | H64: N/A | I64: transactional | J64: N/A | K64: N/A | L64: N/A | M64: N/A | N64: N/A | O64: N/A | P64: N/A | Q64: N/A | R64: N/A | S64: N/A | T64: 0 | U64: N/A | V64: Đo được (1 công cụ)
A65: thuê xe máy đà nẵng bình minh | B65: OUT-INTENT | C65: N/A | D65: N/A | E65: 2400 | F65: OpenRush research_keywords 2026-10-14 | G65: N/A | H65: N/A | I65: commercial | J65: N/A | K65: N/A | L65: N/A | M65: N/A | N65: N/A | O65: N/A | P65: N/A | Q65: N/A | R65: N/A | S65: N/A | T65: 0 | U65: N/A | V65: Đo được (1 công cụ)
A66: thuê xe máy tphcm | B66: OUT-MARKET | C66: N/A | D66: N/A | E66: 2400 | F66: OpenRush research_keywords 2026-10-14 | G66: N/A | H66: N/A | I66: commercial | J66: N/A | K66: N/A | L66: N/A | M66: N/A | N66: N/A | O66: N/A | P66: N/A | Q66: N/A | R66: N/A | S66: N/A | T66: 0 | U66: N/A | V66: Đo được (1 công cụ)
A67: xe máy đặng hoà | B67: OUT-INTENT | C67: N/A | D67: N/A | E67: 2400 | F67: OpenRush research_keywords 2026-10-14 | G67: N/A | H67: N/A | I67: navigational | J67: N/A | K67: N/A | L67: N/A | M67: N/A | N67: N/A | O67: N/A | P67: N/A | Q67: N/A | R67: N/A | S67: N/A | T67: 0 | U67: N/A | V67: Đo được (1 công cụ)
A68: bình ắc quy xe máy | B68: OUT-INTENT | C68: N/A | D68: N/A | E68: 1900 | F68: OpenRush research_keywords 2026-10-14 | G68: N/A | H68: N/A | I68: transactional | J68: N/A | K68: N/A | L68: N/A | M68: N/A | N68: N/A | O68: N/A | P68: N/A | Q68: N/A | R68: N/A | S68: N/A | T68: 0 | U68: N/A | V68: Đo được (1 công cụ)
A69: cấp lại bằng lái xe máy | B69: OUT-INTENT | C69: N/A | D69: N/A | E69: 1900 | F69: OpenRush research_keywords 2026-10-14 | G69: N/A | H69: N/A | I69: transactional | J69: N/A | K69: N/A | L69: N/A | M69: N/A | N69: N/A | O69: N/A | P69: N/A | Q69: N/A | R69: N/A | S69: N/A | T69: 0 | U69: N/A | V69: Đo được (1 công cụ)
A70: cho thuê xe máy gần đây | B70: LOCAL-PACK | C70: N/A | D70: N/A | E70: 1900 | F70: OpenRush research_keywords 2026-10-14 | G70: N/A | H70: N/A | I70: commercial | J70: N/A | K70: N/A | L70: N/A | M70: N/A | N70: N/A | O70: N/A | P70: N/A | Q70: N/A | R70: N/A | S70: N/A | T70: 0 | U70: N/A | V70: Đo được (1 công cụ)
A71: thi bằng lái xe máy hà nội | B71: OUT-INTENT | C71: N/A | D71: N/A | E71: 1900 | F71: OpenRush research_keywords 2026-10-14 | G71: N/A | H71: N/A | I71: navigational | J71: N/A | K71: N/A | L71: N/A | M71: N/A | N71: N/A | O71: N/A | P71: N/A | Q71: N/A | R71: N/A | S71: N/A | T71: 0 | U71: N/A | V71: Đo được (1 công cụ)
A72: thi bằng lái xe máy tại hà nội | B72: OUT-INTENT | C72: N/A | D72: N/A | E72: 1900 | F72: OpenRush research_keywords 2026-10-14 | G72: N/A | H72: N/A | I72: navigational | J72: N/A | K72: N/A | L72: N/A | M72: N/A | N72: N/A | O72: N/A | P72: N/A | Q72: N/A | R72: N/A | S72: N/A | T72: 0 | U72: N/A | V72: Đo được (1 công cụ)
A73: thuê xe máy nha trang san hô việt | B73: OUT-INTENT | C73: N/A | D73: N/A | E73: 1900 | F73: OpenRush research_keywords 2026-10-14 | G73: N/A | H73: N/A | I73: transactional | J73: N/A | K73: N/A | L73: N/A | M73: N/A | N73: N/A | O73: N/A | P73: N/A | Q73: N/A | R73: N/A | S73: N/A | T73: 0 | U73: N/A | V73: Đo được (1 công cụ)
A74: xe máy điện có cần bằng lái không | B74: IN-SCOPE | C74: K09 | D74: xe-may-dien-co-can-bang-lai-khong | E74: 1900 | F74: OpenRush research_keywords 2026-10-14 | G74: 1900 | H74: 0 | I74: informational | J74: Thông tin | K74: AI Overview, PAA | L74: N/A | M74: N/A | N74: www.greensm.com | O74: https://www.greensm.com/vn-vi/news/di-xe-may-dien-co-can-bang-lai-khong | P74: #1 www.greensm.com; #2 vinfastauto.com; #3 thuvienphapluat.vn | Q74: Đã có bài | R74: /blog/an-toan/xe-may-dien-co-can-bang-lai-khong/ | S74: Giữ nguyên | T74: 0 | U74: N/A | V74: Đo được (2 công cụ)
A75: bao nhiêu tuổi được đi xe máy điện | B75: IN-SCOPE | C75: K09 | D75: bao-nhieu-tuoi-duoc-di-xe-may-dien | E75: 1600 | F75: OpenRush research_keywords 2026-10-14 | G75: 1600 | H75: 0 | I75: informational | J75: Thông tin | K75: AI Overview, PAA | L75: N/A | M75: N/A | N75: vamm.vn | O75: https://vamm.vn/hoc-sinh-cap-2-cap-3-co-duoc-di-xe-may-dien-khong/ | P75: #1 vamm.vn; #2 dibao.com.vn; #3 vinfastauto.com | Q75: Chưa có | R75: /blog/an-toan/xe-may-dien-co-can-bang-lai-khong/ | S75: Bổ sung mục/FAQ vào bài đích (review body) | T75: 2156 | U75: P0 | V75: Đo được (2 công cụ)
A76: cho thuê xe máy hà nội | B76: SISTER | C76: N/A | D76: N/A | E76: 1600 | F76: OpenRush research_keywords 2026-10-14 | G76: N/A | H76: N/A | I76: commercial | J76: N/A | K76: N/A | L76: N/A | M76: N/A | N76: N/A | O76: N/A | P76: N/A | Q76: N/A | R76: N/A | S76: N/A | T76: 0 | U76: N/A | V76: Đo được (1 công cụ)
A77: của hàng xe máy điện vinfast gần nhất | B77: OUT-INTENT | C77: N/A | D77: N/A | E77: 1600 | F77: OpenRush research_keywords 2026-10-14 | G77: N/A | H77: N/A | I77: navigational | J77: N/A | K77: N/A | L77: N/A | M77: N/A | N77: N/A | O77: N/A | P77: N/A | Q77: N/A | R77: N/A | S77: N/A | T77: 0 | U77: N/A | V77: Đo được (1 công cụ)
A78: giá xe hrv | B78: OUT-INTENT | C78: N/A | D78: N/A | E78: 1600 | F78: OpenRush research_keywords 2026-10-14 | G78: N/A | H78: N/A | I78: commercial | J78: N/A | K78: N/A | L78: N/A | M78: N/A | N78: N/A | O78: N/A | P78: N/A | Q78: N/A | R78: N/A | S78: N/A | T78: 0 | U78: N/A | V78: Đo được (1 công cụ)
A79: giá xe máy yamaha | B79: OUT-INTENT | C79: N/A | D79: N/A | E79: 1600 | F79: OpenRush research_keywords 2026-10-14 | G79: N/A | H79: N/A | I79: commercial | J79: N/A | K79: N/A | L79: N/A | M79: N/A | N79: N/A | O79: N/A | P79: N/A | Q79: N/A | R79: N/A | S79: N/A | T79: 0 | U79: N/A | V79: Đo được (1 công cụ)
A80: làm lại bằng lái xe máy | B80: OUT-INTENT | C80: N/A | D80: N/A | E80: 1600 | F80: OpenRush research_keywords 2026-10-14 | G80: N/A | H80: N/A | I80: transactional | J80: N/A | K80: N/A | L80: N/A | M80: N/A | N80: N/A | O80: N/A | P80: N/A | Q80: N/A | R80: N/A | S80: N/A | T80: 0 | U80: N/A | V80: Đo được (1 công cụ)
A81: lý thuyết thi bằng lái xe máy a1 | B81: OUT-INTENT | C81: N/A | D81: N/A | E81: 1600 | F81: OpenRush research_keywords 2026-10-14 | G81: N/A | H81: N/A | I81: informational | J81: N/A | K81: N/A | L81: N/A | M81: N/A | N81: N/A | O81: N/A | P81: N/A | Q81: N/A | R81: N/A | S81: N/A | T81: 0 | U81: N/A | V81: Đo được (1 công cụ)
A82: thi bằng lái xe máy a1 tại gò vấp | B82: OUT-INTENT | C82: N/A | D82: N/A | E82: 1600 | F82: OpenRush research_keywords 2026-10-14 | G82: N/A | H82: N/A | I82: transactional | J82: N/A | K82: N/A | L82: N/A | M82: N/A | N82: N/A | O82: N/A | P82: N/A | Q82: N/A | R82: N/A | S82: N/A | T82: 0 | U82: N/A | V82: Đo được (1 công cụ)
A83: thi bằng lái xe máy bao nhiêu tiền | B83: OUT-INTENT | C83: N/A | D83: N/A | E83: 1600 | F83: OpenRush research_keywords 2026-10-14 | G83: N/A | H83: N/A | I83: commercial | J83: N/A | K83: N/A | L83: N/A | M83: N/A | N83: N/A | O83: N/A | P83: N/A | Q83: N/A | R83: N/A | S83: N/A | T83: 0 | U83: N/A | V83: Đo được (1 công cụ)
A84: thuê xe máy bike saigon | B84: OUT-INTENT | C84: N/A | D84: N/A | E84: 1600 | F84: OpenRush research_keywords 2026-10-14 | G84: N/A | H84: N/A | I84: transactional | J84: N/A | K84: N/A | L84: N/A | M84: N/A | N84: N/A | O84: N/A | P84: N/A | Q84: N/A | R84: N/A | S84: N/A | T84: 0 | U84: N/A | V84: Đo được (1 công cụ)
A85: thuê xe máy huế | B85: OUT-MARKET | C85: N/A | D85: N/A | E85: 1600 | F85: OpenRush research_keywords 2026-10-14 | G85: N/A | H85: N/A | I85: commercial | J85: N/A | K85: N/A | L85: N/A | M85: N/A | N85: N/A | O85: N/A | P85: N/A | Q85: N/A | R85: N/A | S85: N/A | T85: 0 | U85: N/A | V85: Đo được (1 công cụ)
A86: thuê xe máy huế hidden land bikes | B86: OUT-INTENT | C86: N/A | D86: N/A | E86: 1600 | F86: OpenRush research_keywords 2026-10-14 | G86: N/A | H86: N/A | I86: transactional | J86: N/A | K86: N/A | L86: N/A | M86: N/A | N86: N/A | O86: N/A | P86: N/A | Q86: N/A | R86: N/A | S86: N/A | T86: 0 | U86: N/A | V86: Đo được (1 công cụ)
A87: xe máy điện honda 2025 | B87: OUT-INTENT | C87: N/A | D87: N/A | E87: 1600 | F87: OpenRush research_keywords 2026-10-14 | G87: N/A | H87: N/A | I87: informational | J87: N/A | K87: N/A | L87: N/A | M87: N/A | N87: N/A | O87: N/A | P87: N/A | Q87: N/A | R87: N/A | S87: N/A | T87: 0 | U87: N/A | V87: Đo được (1 công cụ)
... A100: xe máy thịnh phát xe lướt giá rẻ | B100: OUT-INTENT | C100: N/A | D100: N/A | E100: 1300 | F100: OpenRush research_keywords 2026-10-14 | G100: N/A | H100: N/A | I100: commercial | J100: N/A | K100: N/A | L100: N/A | M100: N/A | N100: N/A | O100: N/A | P100: N/A | Q100: N/A | R100: N/A | S100: N/A | T100: 0 | U100: N/A | V100: Đo được (1 công cụ)
A101: bằng lái xe máy a1 | B101: IN-SCOPE | C101: K09 | D101: bang-lai-xe-may-a1 | E101: 1000 | F101: OpenRush research_keywords 2026-10-14 | G101: 1000 | H101: 0 | I101: informational | J101: N/A | K101: N/A | L101: N/A | M101: N/A | N101: N/A | O101: N/A | P101: N/A | Q101: Đã có bài | R101: /blog/thue-xe/bang-lai-a1-va-thue-xe-may/ | S101: Giữ nguyên | T101: 0 | U101: N/A | V101: Đo được (2 công cụ)
A102: bơm xe máy | B102: OUT-INTENT | C102: N/A | D102: N/A | E102: 1000 | F102: OpenRush research_keywords 2026-10-14 | G102: N/A | H102: N/A | I102: transactional | J102: N/A | K102: N/A | L102: N/A | M102: N/A | N102: N/A | O102: N/A | P102: N/A | Q102: N/A | R102: N/A | S102: N/A | T102: 0 | U102: N/A | V102: Đo được (1 công cụ)
A103: các loại bằng lái xe máy | B103: IN-SCOPE | C103: K09 | D103: cac-loai-bang-lai-xe-may | E103: 1000 | F103: OpenRush research_keywords 2026-10-14 | G103: 1000 | H103: 0 | I103: informational | J103: Thông tin | K103: AI Overview | L103: N/A | M103: N/A | N103: thuvienphapluat.vn | O103: https://thuvienphapluat.vn/chinh-sach-phap-luat-moi/vn/ho-tro-phap-luat/tu-van-phap-luat/107524/cac-loai-bang-lai-xe-may-giay-phep-lai-xe-may-nam-2026-moi-nhat | P103: #1 thuvienphapluat.vn; #2 thuvienphapluat.vn; #3 dibao.com.vn | Q103: Đã có bài | R103: /blog/an-toan/cac-loai-bang-lai-xe-may/ | S103: Giữ nguyên | T103: 0 | U103: N/A | V103: Đo được (2 công cụ)
A104: cấm xe máy | B104: IN-SCOPE | C104: K20 | D104: cam-xe-may | E104: 1000 | F104: OpenRush research_keywords 2026-10-14 | G104: 1000 | H104: 0 | I104: informational | J104: Thông tin | K104: AI Overview | L104: N/A | M104: N/A | N104: laodong.vn | O104: https://laodong.vn/xa-hoi/de-xuat-cam-hoan-toan-xe-may-xang-chay-dich-vu-cong-nghe-tu-cuoi-2029-o-tphcm-1541694.ldo | P104: #1 laodong.vn; #2 laodong.vn; #3 www.24h.com.vn | Q104: Đã có bài | R104: /blog/an-toan/cam-xe-may-xang-vanh-dai-1/ | S104: Giữ nguyên | T104: 0 | U104: N/A | V104: Đo được (2 công cụ)
A105: cho thuê xe máy cần thơ | B105: OUT-MARKET | C105: N/A | D105: N/A | E105: 1000 | F105: OpenRush research_keywords 2026-10-14 | G105: N/A | H105: N/A | I105: transactional | J105: N/A | K105: N/A | L105: N/A | M105: N/A | N105: N/A | O105: N/A | P105: N/A | Q105: N/A | R105: N/A | S105: N/A | T105: 0 | U105: N/A | V105: Đo được (1 công cụ)
A106: cho thuê xe máy đà nẵng văn khoa | B106: OUT-INTENT | C106: N/A | D106: N/A | E106: 1000 | F106: OpenRush research_keywords 2026-10-14 | G106: N/A | H106: N/A | I106: transactional | J106: N/A | K106: N/A | L106: N/A | M106: N/A | N106: N/A | O106: N/A | P106: N/A | Q106: N/A | R106: N/A | S106: N/A | T106: 0 | U106: N/A | V106: Đo được (1 công cụ)
A107: cho thuê xe máy nha trang | B107: OUT-MARKET | C107: N/A | D107: N/A | E107: 1000 | F107: OpenRush research_keywords 2026-10-14 | G107: N/A | H107: N/A | I107: transactional | J107: N/A | K107: N/A | L107: N/A | M107: N/A | N107: N/A | O107: N/A | P107: N/A | Q107: N/A | R107: N/A | S107: N/A | T107: 0 | U107: N/A | V107: Đo được (1 công cụ)
A108: cho thuê xe máy ninh bình trà my | B108: OUT-INTENT | C108: N/A | D108: N/A | E108: 1000 | F108: OpenRush research_keywords 2026-10-14 | G108: N/A | H108: N/A | I108: transactional | J108: N/A | K108: N/A | L108: N/A | M108: N/A | N108: N/A | O108: N/A | P108: N/A | Q108: N/A | R108: N/A | S108: N/A | T108: 0 | U108: N/A | V108: Đo được (1 công cụ)
A109: cứu hộ xe máy hà nội 24 24 | B109: OUT-INTENT | C109: N/A | D109: N/A | E109: 1000 | F109: OpenRush research_keywords 2026-10-14 | G109: N/A | H109: N/A | I109: navigational | J109: N/A | K109: N/A | L109: N/A | M109: N/A | N109: N/A | O109: N/A | P109: N/A | Q109: N/A | R109: N/A | S109: N/A | T109: 0 | U109: N/A | V109: Đo được (1 công cụ)
A110: đăng ký bằng lái xe máy | B110: OUT-INTENT | C110: N/A | D110: N/A | E110: 1000 | F110: OpenRush research_keywords 2026-10-14 | G110: N/A | H110: N/A | I110: transactional | J110: N/A | K110: N/A | L110: N/A | M110: N/A | N110: N/A | O110: N/A | P110: N/A | Q110: N/A | R110: N/A | S110: N/A | T110: 0 | U110: N/A | V110: Đo được (1 công cụ)
A111: đăng ký thi bằng lái xe máy ở gò vấp | B111: OUT-INTENT | C111: N/A | D111: N/A | E111: 1000 | F111: OpenRush research_keywords 2026-10-14 | G111: N/A | H111: N/A | I111: transactional | J111: N/A | K111: N/A | L111: N/A | M111: N/A | N111: N/A | O111: N/A | P111: N/A | Q111: N/A | R111: N/A | S111: N/A | T111: 0 | U111: N/A | V111: Đo được (1 công cụ)
A112: định vị xe máy viettel | B112: OUT-INTENT | C112: N/A | D112: N/A | E112: 1000 | F112: OpenRush research_keywords 2026-10-14 | G112: N/A | H112: N/A | I112: navigational | J112: N/A | K112: N/A | L112: N/A | M112: N/A | N112: N/A | O112: N/A | P112: N/A | Q112: N/A | R112: N/A | S112: N/A | T112: 0 | U112: N/A | V112: Đo được (1 công cụ)
A113: đổi bằng lái xe máy ở đâu | B113: OUT-INTENT | C113: N/A | D113: N/A | E113: 1000 | F113: OpenRush research_keywords 2026-10-14 | G113: N/A | H113: N/A | I113: navigational | J113: N/A | K113: N/A | L113: N/A | M113: N/A | N113: N/A | O113: N/A | P113: N/A | Q113: N/A | R113: N/A | S113: N/A | T113: 0 | U113: N/A | V113: Đo được (1 công cụ)
A114: honda bình dương | B114: OUT-MARKET | C114: N/A | D114: N/A | E114: 1000 | F114: OpenRush research_keywords 2026-10-14 | G114: N/A | H114: N/A | I114: navigational | J114: N/A | K114: N/A | L114: N/A | M114: N/A | N114: N/A | O114: N/A | P114: N/A | Q114: N/A | R114: N/A | S114: N/A | T114: 0 | U114: N/A | V114: Đo được (1 công cụ)
A115: khóa xe máy | B115: OUT-INTENT | C115: N/A | D115: N/A | E115: 1000 | F115: OpenRush research_keywords 2026-10-14 | G115: N/A | H115: N/A | I115: transactional | J115: N/A | K115: N/A | L115: N/A | M115: N/A | N115: N/A | O115: N/A | P115: N/A | Q115: N/A | R115: N/A | S115: N/A | T115: 0 | U115: N/A | V115: Đo được (1 công cụ)
A116: không có bằng lái xe máy phạt bao nhiêu tiền | B116: IN-SCOPE | C116: K09 | D116: khong-bang-lai-xe-may-phat-bao-nhieu | E116: 1000 | F116: OpenRush research_keywords 2026-10-14 | G116: 1000 | H116: 0 | I116: informational | J116: N/A | K116: N/A | L116: N/A | M116: N/A | N116: N/A | O116: N/A | P116: N/A | Q116: Đã có bài | R116: /blog/an-toan/di-xe-khong-giay-phep/ | S116: Giữ nguyên | T116: 0 | U116: N/A | V116: Đo được (2 công cụ)
A117: luật thi bằng lái xe máy 2026 | B117: OUT-INTENT | C117: N/A | D117: N/A | E117: 1000 | F117: OpenRush research_keywords 2026-10-14 | G117: N/A | H117: N/A | I117: informational | J117: N/A | K117: N/A | L117: N/A | M117: N/A | N117: N/A | O117: N/A | P117: N/A | Q117: N/A | R117: N/A | S117: N/A | T117: 0 | U117: N/A | V117: Đo được (1 công cụ)
A118: mất bằng lái xe máy | B118: OUT-INTENT | C118: N/A | D118: N/A | E118: 1000 | F118: OpenRush research_keywords 2026-10-14 | G118: N/A | H118: N/A | I118: informational | J118: N/A | K118: N/A | L118: N/A | M118: N/A | N118: N/A | O118: N/A | P118: N/A | Q118: N/A | R118: N/A | S118: N/A | T118: 0 | U118: N/A | V118: Đo được (1 công cụ)
A119: thi bằng lái xe máy 2025 | B119: OUT-INTENT | C119: N/A | D119: N/A | E119: 1000 | F119: OpenRush research_keywords 2026-10-14 | G119: N/A | H119: N/A | I119: informational | J119: N/A | K119: N/A | L119: N/A | M119: N/A | N119: N/A | O119: N/A | P119: N/A | Q119: N/A | R119: N/A | S119: N/A | T119: 0 | U119: N/A | V119: Đo được (1 công cụ)
...

Sheet KEYWORD GAP
A1: Nguồn: docs/seo/battle/04-opportunity-matrix.csv (engine 06 + SERP 2026-10-14). NEW CONTENT chỉ là đề xuất: chủ sở hữu thêm ID vào content-matrix.csv.
A2: Từ khóa | B2: Nhóm | C2: Volume (đo được) | D2: Cụm | E2: Ý định | F2: Độ phủ | G2: Cạnh tranh SERP | H2: Đối thủ mạnh top 10 | I2: Điểm cơ hội | J2: Loại trang | K2: Hành động engine | L2: Trang đích | M2: Quyết định engine | N2: Phân loại M1
A3: bao nhiêu tuổi được đi xe máy điện | B3: bao-nhieu-tuoi-duoc-di-xe-may-dien | C3: 3080 | D3: K09 | E3: Thông tin | F3: Phủ một phần | G3: Trung bình | H3: vinfastauto.com thuvienphapluat.vn | I3: 4096 | J3: Mục/FAQ trong bài hiện có | K3: Bổ sung mục/FAQ vào bài đích (review body) | L3: /blog/an-toan/xe-may-dien-co-can-bang-lai-khong/ | M3: done | N3: EXPAND
A4: lỗi sử dụng điện thoại khi đi xe máy | B4: loi-su-dung-dien-thoai-khi-di-xe-may | C4: 480 | D4: K10 | E4: Thông tin | F4: Phủ một phần | G4: Trung bình | H4: laodong.vn thuvienphapluat.vn | I4: 491 | J4: Mục/FAQ trong bài hiện có | K4: Bổ sung mục/FAQ vào bài đích (review body) | L4: /blog/an-toan/dien-thoai-khi-lai-xe-tom-tat/ | M4: deferred | N4: EXPAND
A5: bằng lái xe máy là hạng gì | B5: bang-lai-xe-may-la-hang-gi | C5: 1270 | D5: K09 | E5: Hỗn hợp (thương mại + thông tin) | F5: Đã có bài | G5: Trung bình | H5: vinfastauto.com thuvienphapluat.vn | I5: 334 | J5: Title/meta của bài hiện có | K5: Đưa cụm từ chính vào title/meta (article-meta) | L5: /blog/an-toan/cac-loai-bang-lai-xe-may/ | M5: done | N5: COVERED
A6: phượt hà giang bằng xe máy | B6: phuot-ha-giang-bang-xe-may | C6: 70 | D6: K17 | E6: Thông tin (công cụ) | F6: Phủ một phần | G6: Chưa chụp SERP | H6: N/A | I6: 39 | J6: Mục/FAQ trong bài hiện có | K6: Bổ sung mục/FAQ vào bài đích (review body) | L6: /blog/dia-phuong/ha-giang-vong-cung/ | M6: rejected | N6: EXPAND
A7: phượt tam đảo bằng xe máy | B7: phuot-tam-dao-bang-xe-may | C7: 70 | D7: K17 | E7: Thông tin (công cụ) | F7: Phủ một phần | G7: Chưa chụp SERP | H7: N/A | I7: 39 | J7: Mục/FAQ trong bài hiện có | K7: Bổ sung mục/FAQ vào bài đích (review body) | L7: /blog/dia-phuong/tam-dao-bang-xe-may/ | M7: rejected | N7: EXPAND
A8: đường đi thái nguyên từ hà nội bằng xe máy | B8: duong-di-thai-nguyen-tu-ha-noi-bang-xe-may | C8: 30 | D8: K18 | E8: Thông tin (công cụ) | F8: Chưa có | G8: Chưa chụp SERP | H8: N/A | I8: 2 | J8: Giữ trang hiện có | K8: Theo dõi (nhu cầu thấp/chưa đo) | L8: N/A | M8: open | N8: NEW CONTENT
A9: xe máy đi phượt tốt nhất | B9: xe-may-di-phuot-tot-nhat | C9: 30 | D9: K04 | E9: Thương mại (công cụ) | F9: Phủ một phần | G9: Chưa chụp SERP | H9: N/A | I9: 2 | J9: Giữ trang hiện có | K9: Theo dõi (nhu cầu thấp/chưa đo) | L9: /blog/huong-dan/di-phuot-bang-xe-may/ | M9: open | N9: EXPAND
A10: đường đi hà nội hải phòng bằng xe máy | B10: duong-di-ha-noi-hai-phong-bang-xe-may | C10: 20 | D10: K18 | E10: Thông tin (công cụ) | F10: Chưa có | G10: Chưa chụp SERP | H10: N/A | I10: 2 | J10: Giữ trang hiện có | K10: Theo dõi (nhu cầu thấp/chưa đo) | L10: N/A | M10: open | N10: NEW CONTENT
A11: đường đi nam định hà nội bằng xe máy | B11: duong-di-nam-dinh-ha-noi-bang-xe-may | C11: 20 | D11: K18 | E11: Thông tin (công cụ) | F11: Phủ một phần | G11: Chưa chụp SERP | H11: N/A | I11: 2 | J11: Giữ trang hiện có | K11: Theo dõi (nhu cầu thấp/chưa đo) | L11: /blog/dia-phuong/sai-gon-duong-nam/ | M11: open | N11: EXPAND
A12: hội phượt xe máy | B12: hoi-phuot-xe-may | C12: 20 | D12: K04 | E12: Thông tin (công cụ) | F12: Chưa có | G12: Chưa chụp SERP | H12: N/A | I12: 2 | J12: Giữ trang hiện có | K12: Theo dõi (nhu cầu thấp/chưa đo) | L12: N/A | M12: open | N12: NEW CONTENT
A13: kinh nghiệm đi phượt bằng xe máy | B13: kinh-nghiem-di-phuot-bang-xe-may | C13: 20 | D13: K07 | E13: Thông tin (công cụ) | F13: Phủ một phần | G13: Chưa chụp SERP | H13: N/A | I13: 2 | J13: Giữ trang hiện có | K13: Theo dõi (nhu cầu thấp/chưa đo) | L13: /blog/thue-xe/thue-honda-air-blade/ | M13: open | N13: EXPAND
A14: kinh nghiệm phượt sapa bằng xe máy | B14: kinh-nghiem-phuot-sapa-bang-xe-may | C14: 20 | D14: K07 | E14: Thông tin (công cụ) | F14: Chưa có | G14: Chưa chụp SERP | H14: N/A | I14: 2 | J14: Giữ trang hiện có | K14: Theo dõi (nhu cầu thấp/chưa đo) | L14: N/A | M14: open | N14: NEW CONTENT
... A96: xe máy đi phượt cho nữ | B96: xe-may-di-phuot-cho-nu | C96: 10 | D96: K04 | E96: Giao dịch (công cụ) | F96: Phủ một phần | G96: Chưa chụp SERP | H96: N/A | I96: 0 | J96: Giữ trang hiện có | K96: Theo dõi (nhu cầu thấp/chưa đo) | L96: /blog/huong-dan/di-phuot-bang-xe-may/ | M96: open | N96: EXPAND
A97: bằng lái a1 a2 khác gì | B97: bang-lai-a1-a2-khac-gi | C97: N/A | D97: K09 | E97: Thông tin | F97: Đã có bài | G97: Thấp | H97: thuvienphapluat.vn | I97: 0 | J97: Giữ trang hiện có | K97: Giữ nguyên | L97: /blog/an-toan/bang-lai-a1-a2-khac-gi/ | M97: open | N97: COVERED
A98: bảo hiểm xe máy thuê | B98: bao-hiem-xe-may-thue | C98: N/A | D98: K11 | E98: Thông tin | F98: Đã có bài | G98: Thấp | H98: N/A | I98: 0 | J98: Giữ trang hiện có | K98: Giữ nguyên | L98: /blog/an-toan/bao-hiem-khi-thue-xe-may/ | M98: open | N98: COVERED
A99: cấm xe máy xăng vành đai 1 | B99: cam-xe-may-xang-vanh-dai-1 | C99: N/A | D99: K20 | E99: Thông tin | F99: Đã có bài | G99: Cao | H99: thuvienphapluat.vn | I99: 0 | J99: Giữ trang hiện có | K99: Giữ nguyên | L99: /blog/an-toan/cam-xe-may-xang-vanh-dai-1/ | M99: done | N99: COVERED
A100: đặt cọc thuê xe máy | B100: dat-coc-thue-xe-may | C100: N/A | D100: K04 | E100: Thông tin | F100: Đã có bài | G100: Cao | H100: motogo.vn vinwonders.com thuvienphapluat.vn www.otosaigon.com | I100: 0 | J100: Giữ trang hiện có | K100: Giữ nguyên | L100: /blog/huong-dan/dat-coc-the-nao/ | M100: open | N100: COVERED
A101: đặt thuê xe máy online | B101: dat-thue-xe-may-online | C101: N/A | D101: K01 | E101: Giao dịch – địa phương | F101: Phủ một phần | G101: Thấp | H101: motogo.vn | I101: 0 | J101: Trang bán hàng / Google Business Profile | K101: Ý định giao dịch – địa phương: trang bán hàng/Google Business Profile, không viết blog | L101: (trang bán hàng / Google Business Profile) | M101: open | N101: EXPAND
A102: đi hồ tây bằng xe máy | B102: di-ho-tay-bang-xe-may | C102: N/A | D102: K14 | E102: Thông tin | F102: Phủ một phần | G102: Trung bình | H102: motogo.vn vinwonders.com | I102: 0 | J102: Giữ trang hiện có | K102: Theo dõi (nhu cầu thấp/chưa đo) | L102: /blog/dia-phuong/hoang-hon-ho-tay/ | M102: open | N102: EXPAND
A103: đi phố cổ hà nội bằng xe máy | B103: di-pho-co-ha-noi-bang-xe-may | C103: N/A | D103: K12 | E103: Hỗn hợp (thương mại + thông tin) | F103: Phủ một phần | G103: Thấp | H103: justfly.vn | I103: 0 | J103: Giữ trang hiện có | K103: Theo dõi (nhu cầu thấp/chưa đo) | L103: /blog/dia-phuong/ca-phe-pho-co/ | M103: open | N103: EXPAND
A104: đi xe máy xuyên việt | B104: di-xe-may-xuyen-viet | C104: N/A | D104: K18 | E104: Thông tin | F104: Đã có bài | G104: Thấp | H104: N/A | I104: 0 | J104: Giữ trang hiện có | K104: Giữ nguyên | L104: /blog/dia-phuong/hue-xuyen-viet/ | M104: open | N104: COVERED
A105: du lịch biển gần hà nội bằng xe máy | B105: du-lich-bien-gan-ha-noi-bang-xe-may | C105: 0 | D105: K12 | E105: Thông tin (công cụ) | F105: Chưa có | G105: Chưa chụp SERP | H105: N/A | I105: 0 | J105: Giữ trang hiện có | K105: Theo dõi (nhu cầu thấp/chưa đo) | L105: N/A | M105: open | N105: NEW CONTENT
A106: đường đi hà nội thái nguyên bằng xe máy | B106: duong-di-ha-noi-thai-nguyen-bang-xe-may | C106: 0 | D106: K17 | E106: Thông tin (công cụ) | F106: Chưa có | G106: Chưa chụp SERP | H106: N/A | I106: 0 | J106: Giữ trang hiện có | K106: Theo dõi (nhu cầu thấp/chưa đo) | L106: N/A | M106: open | N106: NEW CONTENT
A107: kiểm tra xe máy khi thuê | B107: kiem-tra-xe-may-khi-thue | C107: N/A | D107: K05 | E107: Giao dịch – địa phương | F107: Đã có bài | G107: Thấp | H107: N/A | I107: 0 | J107: Giữ trang hiện có | K107: Giữ nguyên | L107: /blog/huong-dan/kiem-tra-xe-khi-nhan/ | M107: open | N107: COVERED
A108: kinh nghiệm lái xe máy ở hà nội | B108: kinh-nghiem-lai-xe-may-o-ha-noi | C108: N/A | D108: K01 | E108: Hỗn hợp (thương mại + thông tin) | F108: Phủ một phần | G108: Thấp | H108: vinfastauto.com | I108: 0 | J108: Giữ trang hiện có | K108: Theo dõi (nhu cầu thấp/chưa đo) | L108: /blog/app/cong-cu-chon-xe-theo-kinh-nghiem-lai/ | M108: open | N108: EXPAND
A109: tai nạn khi đi xe thuê ai chịu trách nhiệm | B109: tai-nan-khi-di-xe-thue-ai-chiu-trach-nhiem | C109: N/A | D109: K11 | E109: Hỗn hợp (thương mại + thông tin) | F109: Đã có bài | G109: Trung bình | H109: thuvienphapluat.vn | I109: 0 | J109: Giữ trang hiện có | K109: Giữ nguyên | L109: /blog/an-toan/trach-nhiem-khi-tai-nan-voi-xe-thue-cho-nguoi-moi/ | M109: open | N109: COVERED
A110: thuê xe máy ba đình | B110: thue-xe-may-ba-dinh | C110: N/A | D110: K13 | E110: Giao dịch – địa phương | F110: Đã có bài | G110: Trung bình | H110: motogo.vn www.otosaigon.com | I110: 0 | J110: Giữ trang hiện có | K110: Giữ nguyên | L110: /blog/dia-phuong/ba-dinh-xe-may-phuong/ | M110: open | N110: COVERED
A111: thuê xe máy cho người nước ngoài | B111: thue-xe-may-cho-nguoi-nuoc-ngoai | C111: N/A | D111: K01 | E111: Hỗn hợp (thương mại + thông tin) | F111: Đã có bài | G111: Trung bình | H111: vexere.com motogo.vn | I111: 0 | J111: Giữ trang hiện có | K111: Giữ nguyên | L111: /blog/app/app-thue-xe-cho-nguoi-nuoc-ngoai/ | M111: open | N111: COVERED
A112: thuê xe máy đi hà giang | B112: thue-xe-may-di-ha-giang | C112: N/A | D112: K17 | E112: Giao dịch – địa phương | F112: Phủ một phần | G112: Thấp | H112: N/A | I112: 0 | J112: Trang bán hàng / Google Business Profile | K112: Ý định giao dịch – địa phương: trang bán hàng/Google Business Profile, không viết blog | L112: (trang bán hàng / Google Business Profile) | M112: open | N112: EXPAND
A113: thuê xe máy đi ninh bình | B113: thue-xe-may-di-ninh-binh | C113: N/A | D113: K17 | E113: Giao dịch – địa phương | F113: Phủ một phần | G113: Thấp | H113: N/A | I113: 0 | J113: Trang bán hàng / Google Business Profile | K113: Ý định giao dịch – địa phương: trang bán hàng/Google Business Profile, không viết blog | L113: (trang bán hàng / Google Business Profile) | M113: open | N113: EXPAND
A114: thuê xe máy long biên | B114: thue-xe-may-long-bien | C114: N/A | D114: K11 | E114: Giao dịch – địa phương | F114: Phủ một phần | G114: Thấp | H114: N/A | I114: 0 | J114: Trang bán hàng / Google Business Profile | K114: Ý định giao dịch – địa phương: trang bán hàng/Google Business Profile, không viết blog | L114: (trang bán hàng / Google Business Profile) | M114: open | N114: EXPAND
A115: thuê xe máy ở ga hà nội | B115: thue-xe-may-o-ga-ha-noi | C115: N/A | D115: K07 | E115: — | F115: Phủ một phần | G115: Chưa chụp SERP | H115: N/A | I115: 0 | J115: Giữ trang hiện có | K115: Theo dõi (nhu cầu thấp/chưa đo) | L115: /blog/thue-xe/thue-xe-ga/ | M115: open | N115: EXPAND
A116: xe điện bờ hồ | B116: xe-dien-bo-ho | C116: N/A | D116: K12 | E116: — | F116: Có mục trong bài | G116: Chưa chụp SERP | H116: N/A | I116: 0 | J116: Giữ trang hiện có | K116: Giữ nguyên | L116: /blog/dia-phuong/du-lich-hoan-kiem-bang-xe-may/ | M116: open | N116: IMPROVE
A117: xe điện đi phố cổ | B117: xe-dien-di-pho-co | C117: N/A | D117: K08 | E117: — | F117: Đã có bài | G117: Chưa chụp SERP | H117: N/A | I117: 0 | J117: Giữ trang hiện có | K117: Giữ nguyên | L117: /blog/xe-dien/xe-dien-trong-pho-cho-khach-du-lich/ | M117: open | N117: COVERED
A118: xe máy bị thủng lốp giữa đường | B118: xe-may-bi-thung-lop-giua-duong | C118: N/A | D118: K08 | E118: Thông tin | F118: Có mục trong bài | G118: Thấp | H118: N/A | I118: 0 | J118: Giữ trang hiện có | K118: Giữ nguyên | L118: /blog/xe-dien/lop-xe-dien/ | M118: open | N118: IMPROVE
A119: xe thuê bị hỏng phải làm sao | B119: xe-thue-bi-hong-phai-lam-sao | C119: N/A | D119: K20 | E119: Hỗn hợp (thương mại + thông tin) | F119: Đã có bài | G119: Thấp | H119: www.otosaigon.com | I119: 0 | J119: Giữ trang hiện có | K119: Giữ nguyên | L119: /blog/huong-dan/sua-xe-nho-khi-dang-thue-cho-nguoi-moi/ | M119: open | N119: COVERED

Sheet COMPETITOR SERP
A1: Nguồn: data/seo/serp-snapshots/2026-10-14.json (Vietnam, Vietnamese, chụp 2026-10-14). Vị trí là ảnh chụp một thời điểm, không phải thứ hạng cố định.
A2: Truy vấn | B2: Cụm | C2: Vị trí | D2: Miền | E2: URL | F2: Title | G2: Quan hệ | H2: Tính năng SERP | I2: AI Overview | J2: Miền được AI Overview trích | K2: Công cụ | L2: Thời điểm lấy
A3: app thuê xe máy | B3: K01 | C3: 1 | D3: play.google.com | E3: https://play.google.com/store/apps/details?id=com.skoot.now&hl=vi | F3: Skoot | The Scooter Rental App - Ứng dụng trên Google Play | G3: đối thủ | H3: ai_overview, organic, people_also_ask | I3: Có | J3: Không | K3: openrush | L3: 2026-10-14T14:27:51.537382Z
A4: app thuê xe máy | B4: K01 | C4: 2 | D4: erent.vn | E4: https://erent.vn/app-thue-tai-xe/ | F4: App thuê tài xế E-rent | G4: đối thủ | H4: ai_overview, organic, people_also_ask | I4: Có | J4: Có | K4: openrush | L4: 2026-10-14T14:27:51.537382Z
A5: app thuê xe máy | B5: K01 | C5: 3 | D5: apps.apple.com | E5: https://apps.apple.com/vn/app/%E1%BB%A9ng-d%E1%BB%A5ng-cho-thu%C3%AA-%C3%B4-t%C3%B4-%C4%91%E1%BA%B7t-xe/id1590139268?l=vi | F5: Ứng dụng cho thuê ô tô・đặt xe - App Store - Apple | G5: đối thủ | H5: ai_overview, organic, people_also_ask | I5: Có | J5: Không | K5: openrush | L5: 2026-10-14T14:27:51.537382Z
A6: app thuê xe máy | B6: K01 | C6: 4 | D6: moma.vn | E6: https://moma.vn/tin-tuc/top-7-app-thue-xe-tu-lai-tiet-kiem-den-60-chi-phi-so-voi-thue-xe-truyen-thong-1ZWM2bMb | F6: Top 7 App Thuê Xe Tự Lái: Tiết Kiệm Đến 60% Chi Phí So ... | G6: đối thủ | H6: ai_overview, organic, people_also_ask | I6: Có | J6: Không | K6: openrush | L6: 2026-10-14T14:27:51.537382Z
A7: app thuê xe máy | B7: K01 | C7: 5 | D7: play.google.com | E7: https://play.google.com/store/apps/details?id=com.rentalcars.online&hl=vi | F7: Ứng dụng cho thuê xe・đặt xe | G7: đối thủ | H7: ai_overview, organic, people_also_ask | I7: Có | J7: Không | K7: openrush | L7: 2026-10-14T14:27:51.537382Z
A8: app thuê xe máy | B8: K01 | C8: 6 | D8: giaiphapgiaothong.com | E8: https://giaiphapgiaothong.com/blogs/blogs/top-9-ung-dung-cho-thue-xe-tu-lai-tren-ios-android | F8: Top 9 Ứng Dụng Cho Thuê Xe Tự Lái Trên iOS, Android | G8: đối thủ | H8: ai_overview, organic, people_also_ask | I8: Có | J8: Có | K8: openrush | L8: 2026-10-14T14:27:51.537382Z
A9: app thuê xe máy | B9: K01 | C9: 7 | D9: chatbot.thuexemaynguyentu.com | E9: https://chatbot.thuexemaynguyentu.com/blog/app/app-thue-xe-khong-can-tai-khoan/ | F9: App Thuê xe Không Cần Tài Khoản - MotoAI | G9: website này | H9: ai_overview, organic, people_also_ask | I9: Có | J9: Không | K9: openrush | L9: 2026-10-14T14:27:51.537382Z
A10: app thuê xe máy | B10: K01 | C10: 8 | D10: www.facebook.com | E10: https://www.facebook.com/groups/247616304947433/posts/967020739673649/ | F10: Cõ chỗ nào cho thuê xe để chạy k ạ e có app rồi | G10: đối thủ | H10: ai_overview, organic, people_also_ask | I10: Có | J10: Không | K10: openrush | L10: 2026-10-14T14:27:51.537382Z
A11: app thuê xe máy | B11: K01 | C11: 9 | D11: chatbot.thuexemaynguyentu.com | E11: https://chatbot.thuexemaynguyentu.com/blog/app/cach-dung-ung-dung-thue-xe-may/ | F11: Cách dùng ứng dụng thuê xe máy: 5 bước từ hỏi giá đến ... | G11: website này | H11: ai_overview, organic, people_also_ask | I11: Có | J11: Không | K11: openrush | L11: 2026-10-14T14:27:51.537382Z
A12: app thuê xe máy hà nội | B12: K01 | C12: 1 | D12: play.google.com | E12: https://play.google.com/store/apps/details?id=casuvang.com.motorbikerental | F12: TRAVEL LOOK: THUÊ XE MÁY - Apps on Google Play | G12: đối thủ | H12: ai_overview, organic, related_searches | I12: Có | J12: Không | K12: openseo | L12: 2026-10-14T14:35:56Z
A13: app thuê xe máy hà nội | B13: K01 | C13: 2 | D13: giaiphapgiaothong.com | E13: https://giaiphapgiaothong.com/blogs/blogs/top-4-app-thue-xe-o-to-xe-may-tu-lai-tot-nhat-tren-android-ios | F13: TOP 4 app thuê xe ô tô, xe máy tự lái tốt nhất trên Android, iOS | G13: đối thủ | H13: ai_overview, organic, related_searches | I13: Có | J13: Không | K13: openseo | L13: 2026-10-14T14:35:56Z
A14: app thuê xe máy hà nội | B14: K01 | C14: 3 | D14: www.facebook.com | E14: https://www.facebook.com/groups/855684482804801/posts/1704327764607131/ | F14: Tìm thuê xe và tài khoản app chạy XanhSM tại Hà Nội? | G14: đối thủ | H14: ai_overview, organic, related_searches | I14: Có | J14: Không | K14: openseo | L14: 2026-10-14T14:35:56Z
... A1135: thuê xe máy hà nội | B1135: LANDSCAPE | C1135: 15 | D1135: luhanhvietnam.com.vn | E1135: https://luhanhvietnam.com.vn/du-lich/dia-chi-thue-xe-may-ha-noi-gia-re.html | F1135: Tư vấn địa chỉ thuê xe máy Hà Nội giá rẻ và lưu ý quan trọng | G1135: đối thủ | H1135: ai_overview, local_pack, organic, related_searches | I1135: Có | J1135: Không | K1135: openseo | L1135: 2026-10-14T14:35:21Z

Sheet URL–KEYWORD MAPPING
A1: URL | B1: Article ID | C1: Loại trang | D1: Từ khóa chính | E1: Từ khóa phụ | F1: Ý định | G1: Cụm | H1: Volume/tháng | I1: Nguồn volume | J1: Vị trí quan sát (SERP chụp) | K1: Quan hệ pillar
A2: https://chatbot.thuexemaynguyentu.com/ | B2: N/A | C2: Trang chủ (website) | D2: cho thuê xe máy ở Hà Nội | E2: cho thuê xe máy Hà Nội; thuê xe máy Hà Nội; thuê xe máy ở Hà Nội; trợ lý thuê xe máy | F2: Thương mại / dịch vụ cho thuê | G2: K02 Giá thuê xe máy | H2: N/A | I2: N/A — chưa đo volume | J2: N/A — truy vấn chưa chụp SERP | K2: Không (trang điều hướng/chuyển đổi duy nhất)
A3: https://chatbot.thuexemaynguyentu.com/agent/ | B3: N/A | C3: Ứng dụng Agent (chat) | D3: ứng dụng thuê xe máy | E3: app thuê xe máy; app thuê xe điện; ứng dụng thuê xe máy điện; công cụ tính giá thuê xe máy | F3: Thông tin sản phẩm / công cụ | G3: K01 Ứng dụng & Agent thuê xe máy | H3: 30 | I3: Đo được (keyword-demand / DataForSEO) | J3: không thấy trong top kết quả (2026-10-14) | K3: Không (trang điều hướng/chuyển đổi duy nhất)
A4: https://chatbot.thuexemaynguyentu.com/blog/ | B4: N/A | C4: Blog home | D4: cẩm nang thuê xe máy | E4: kinh nghiệm thuê xe máy; thủ tục thuê xe máy; giá thuê xe máy | F4: Thông tin / điều hướng | G4: Tất cả cụm | H4: N/A | I4: N/A — chưa đo volume | J4: N/A — truy vấn chưa chụp SERP | K4: Không (trang điều hướng/chuyển đổi duy nhất)
A5: https://chatbot.thuexemaynguyentu.com/chinh-sach/ | B5: N/A | C5: Trang chính sách thuê xe | D5: chính sách thuê xe máy | E5: đặt cọc thuê xe máy; giao xe tận nơi; giấy tờ thuê xe | F5: Thông tin - chuyển đổi | G5: K04 Thủ tục, giấy tờ, hợp đồng và đặt cọc | H5: N/A | I5: N/A — chưa đo volume | J5: N/A — truy vấn chưa chụp SERP | K5: Không (trang điều hướng/chuyển đổi duy nhất)
A6: https://chatbot.thuexemaynguyentu.com/doi-tac/ | B6: N/A | C6: Trang đối tác (B2B) | D6: thuê xe máy theo đoàn | E6: thuê xe máy cho công ty du lịch; thuê xe máy cho khách sạn; thuê xe máy cho hướng dẫn viên | F6: Thương mại / đối tác | G6: K19 Kinh nghiệm thuê xe cho khách du lịch | H6: N/A | I6: N/A — chưa đo volume | J6: N/A — truy vấn chưa chụp SERP | K6: Không (trang điều hướng/chuyển đổi duy nhất)
A7: https://chatbot.thuexemaynguyentu.com/gia-thue/ | B7: N/A | C7: Trang chuyển đổi (giá) | D7: giá thuê xe máy Hà Nội | E7: bảng giá thuê xe máy; giá thuê xe máy theo ngày; giá thuê xe máy theo tháng; giá thuê xe tay ga | F7: Thương mại / chuyển đổi | G7: K02 Giá thuê xe máy | H7: N/A | I7: N/A — chưa đo volume | J7: không thấy trong top kết quả (2026-10-14) | K7: Không (trang điều hướng/chuyển đổi duy nhất)
A8: https://chatbot.thuexemaynguyentu.com/gioi-thieu/ | B8: N/A | C8: Trang giới thiệu (E-E-A-T) | D8: giới thiệu thuê xe máy Nguyễn Tú | E8: MotoAI; trợ lý thuê xe máy | F8: Điều hướng / thương hiệu | G8: K01 Ứng dụng & Agent thuê xe máy | H8: N/A | I8: N/A — chưa đo volume | J8: N/A — truy vấn chưa chụp SERP | K8: Không (trang điều hướng/chuyển đổi duy nhất)
A9: https://chatbot.thuexemaynguyentu.com/lien-he/ | B9: N/A | C9: Trang chuyển đổi (liên hệ) | D9: địa chỉ thuê xe máy Nguyễn Tú | E9: liên hệ thuê xe máy Nguyễn Tú; số điện thoại thuê xe máy; địa chỉ thuê xe máy Long Biên | F9: Điều hướng / chuyển đổi | G9: K15 Long Biên – Gia Lâm – Bát Tràng (khu vực cửa hàng) | H9: N/A | I9: N/A — chưa đo volume | J9: N/A — truy vấn chưa chụp SERP | K9: Không (trang điều hướng/chuyển đổi duy nhất)
A10: https://chatbot.thuexemaynguyentu.com/privacy/ | B10: N/A | C10: Pháp lý | D10: chính sách bảo mật MotoAI | E10: N/A | F10: Điều hướng | G10: Tất cả cụm | H10: N/A | I10: N/A — chưa đo volume | J10: N/A — truy vấn chưa chụp SERP | K10: Không (trang điều hướng/chuyển đổi duy nhất)
A11: https://chatbot.thuexemaynguyentu.com/terms/ | B11: N/A | C11: Pháp lý | D11: điều khoản sử dụng MotoAI | E11: N/A | F11: Điều hướng | G11: Tất cả cụm | H11: N/A | I11: N/A — chưa đo volume | J11: N/A — truy vấn chưa chụp SERP | K11: Không (trang điều hướng/chuyển đổi duy nhất)
A12: https://chatbot.thuexemaynguyentu.com/blog/an-toan/ | B12: N/A | C12: Hub danh mục | D12: luật giao thông và an toàn khi thuê xe máy | E12: an toàn / pháp lý | F12: Điều hướng / danh sách | G12: K10 An toàn khi lái xe máy | H12: N/A | I12: N/A — chưa đo volume | J12: N/A — truy vấn chưa chụp SERP | K12: Không (trang điều hướng/chuyển đổi duy nhất)
A13: https://chatbot.thuexemaynguyentu.com/blog/app/ | B13: N/A | C13: Hub danh mục | D13: hướng dẫn dùng ứng dụng thuê xe máy | E13: ứng dụng thuê xe máy | F13: Điều hướng / danh sách | G13: K01 Ứng dụng & Agent thuê xe máy | H13: N/A | I13: N/A — chưa đo volume | J13: N/A — truy vấn chưa chụp SERP | K13: Không (trang điều hướng/chuyển đổi duy nhất)
A14: https://chatbot.thuexemaynguyentu.com/blog/cong-cu-huong-dan/ | B14: N/A | C14: Hub cụm chủ đề | D14: công cụ và hướng dẫn thuê xe máy | E14: N/A | F14: Điều hướng / pillar cụm | G14: Nhiều cụm | H14: N/A | I14: N/A — chưa đo volume | J14: N/A — truy vấn chưa chụp SERP | K14: Không (trang điều hướng/chuyển đổi duy nhất)
A15: https://chatbot.thuexemaynguyentu.com/blog/dia-phuong/ | B15: N/A | C15: Hub danh mục | D15: đi xe máy ở hà nội | E15: địa phương / du lịch | F15: Điều hướng / danh sách | G15: K17 Hành trình ngoại thành và tỉnh lân cận | H15: N/A | I15: N/A — chưa đo volume | J15: N/A — truy vấn chưa chụp SERP | K15: Không (trang điều hướng/chuyển đổi duy nhất)
... A19: https://chatbot.thuexemaynguyentu.com/blog/thue-xe/ | B19: N/A | C19: Hub danh mục | D19: kinh nghiệm thuê xe máy | E19: thuê xe máy | F19: Điều hướng / danh sách | G19: K19 Kinh nghiệm thuê xe cho khách du lịch | H19: N/A | I19: N/A — chưa đo volume | J19: N/A — truy vấn chưa chụp SERP | K19: Không (trang điều hướng/chuyển đổi duy nhất)
A20: https://chatbot.thuexemaynguyentu.com/blog/xe-dien/ | B20: N/A | C20: Hub danh mục | D20: thuê xe máy điện hà nội | E20: xe điện / xe máy điện | F20: Điều hướng / danh sách | G20: K08 Xe máy điện và xe đạp điện | H20: 260 | I20: Đo được (keyword-demand / DataForSEO) | J20: không thấy trong top kết quả (2026-10-14) | K20: Không (trang điều hướng/chuyển đổi duy nhất)
A21: https://chatbot.thuexemaynguyentu.com/blog/an-toan/ai-chiu-phat-khi-di-xe-thue-cho-du-khach/ | B21: BA-0497 | C21: Bài viết | D21: ai chịu phạt khi đi xe thuê cho du khách | E21: ai chịu phạt khi đi xe thuê; bằng lái khi thuê xe máy; pháp luật | F21: Thông tin pháp lý | G21: K09 Bằng lái và luật giao thông | H21: N/A | I21: N/A — chưa đo volume | J21: N/A — truy vấn chưa chụp SERP | K21: Hỗ trợ pillar BA-0215 ("ai chịu phạt khi đi xe thuê")
A22: https://chatbot.thuexemaynguyentu.com/blog/an-toan/ai-chiu-phat-khi-di-xe-thue-cho-nguoi-moi/ | B22: BA-0779 | C22: Bài viết | D22: ai chịu phạt khi đi xe thuê cho người mới | E22: ai chịu phạt khi đi xe thuê; bằng lái khi thuê xe máy; pháp luật | F22: Thông tin pháp lý | G22: K09 Bằng lái và luật giao thông | H22: N/A | I22: N/A — chưa đo volume | J22: N/A — truy vấn chưa chụp SERP | K22: Hỗ trợ pillar BA-0215 ("ai chịu phạt khi đi xe thuê")
A23: https://chatbot.thuexemaynguyentu.com/blog/an-toan/ai-chiu-phat-khi-di-xe-thue-tom-tat/ | B23: BA-1061 | C23: Bài viết | D23: tóm tắt ai chịu phạt khi đi xe thuê | E23: ai chịu phạt khi đi xe thuê; bằng lái khi thuê xe máy; pháp luật | F23: Thông tin pháp lý | G23: K09 Bằng lái và luật giao thông | H23: N/A | I23: N/A — chưa đo volume | J23: N/A — truy vấn chưa chụp SERP | K23: Hỗ trợ pillar BA-0215 ("ai chịu phạt khi đi xe thuê")
A24: https://chatbot.thuexemaynguyentu.com/blog/an-toan/ai-chiu-phat-khi-di-xe-thue-vi-du-thuc-te/ | B24: BA-1343 | C24: Bài viết | D24: ví dụ ai chịu phạt khi đi xe thuê | E24: ai chịu phạt khi đi xe thuê; bằng lái khi thuê xe máy; pháp luật | F24: Thông tin pháp lý | G24: K09 Bằng lái và luật giao thông | H24: N/A | I24: N/A — chưa đo volume | J24: N/A — truy vấn chưa chụp SERP | K24: Hỗ trợ pillar BA-0215 ("ai chịu phạt khi đi xe thuê")
A25: https://chatbot.thuexemaynguyentu.com/blog/an-toan/ai-chiu-phat-khi-di-xe-thue/ | B25: BA-0215 | C25: Bài viết | D25: ai chịu phạt khi đi xe thuê | E25: bằng lái khi thuê xe máy; pháp luật | F25: Thông tin pháp lý | G25: K09 Bằng lái và luật giao thông | H25: N/A | I25: N/A — chưa đo volume | J25: N/A — truy vấn chưa chụp SERP | K25: Pillar cụm "ai chịu phạt khi đi xe thuê" (5 bài)
A26: https://chatbot.thuexemaynguyentu.com/blog/an-toan/an-toan-khi-thanh-toan-coc-cho-du-khach/ | B26: BA-0563 | C26: Bài viết | D26: thanh toán cọc thuê xe an toàn cho du khách | E26: thanh toán cọc thuê xe an toàn; thủ tục thuê xe máy | F26: Thông tin pháp lý | G26: K04 Thủ tục, giấy tờ, hợp đồng và đặt cọc | H26: N/A | I26: N/A — chưa đo volume | J26: N/A — truy vấn chưa chụp SERP | K26: Hỗ trợ pillar BA-0281 ("thanh toán cọc thuê xe an toàn")
A27: https://chatbot.thuexemaynguyentu.com/blog/an-toan/an-toan-khi-thanh-toan-coc-cho-nguoi-moi/ | B27: BA-0845 | C27: Bài viết | D27: thanh toán cọc thuê xe an toàn cho người mới | E27: thanh toán cọc thuê xe an toàn; thủ tục thuê xe máy | F27: Thông tin pháp lý | G27: K04 Thủ tục, giấy tờ, hợp đồng và đặt cọc | H27: N/A | I27: N/A — chưa đo volume | J27: N/A — truy vấn chưa chụp SERP | K27: Hỗ trợ pillar BA-0281 ("thanh toán cọc thuê xe an toàn")
A28: https://chatbot.thuexemaynguyentu.com/blog/an-toan/an-toan-khi-thanh-toan-coc-tom-tat/ | B28: BA-1127 | C28: Bài viết | D28: tóm tắt thanh toán cọc thuê xe an toàn | E28: thanh toán cọc thuê xe an toàn; thủ tục thuê xe máy | F28: Thông tin pháp lý | G28: K04 Thủ tục, giấy tờ, hợp đồng và đặt cọc | H28: N/A | I28: N/A — chưa đo volume | J28: N/A — truy vấn chưa chụp SERP | K28: Hỗ trợ pillar BA-0281 ("thanh toán cọc thuê xe an toàn")
A29: https://chatbot.thuexemaynguyentu.com/blog/an-toan/an-toan-khi-thanh-toan-coc-vi-du-thuc-te/ | B29: BA-1409 | C29: Bài viết | D29: ví dụ thanh toán cọc thuê xe an toàn | E29: thanh toán cọc thuê xe an toàn; thủ tục thuê xe máy | F29: Thông tin pháp lý | G29: K04 Thủ tục, giấy tờ, hợp đồng và đặt cọc | H29: N/A | I29: N/A — chưa đo volume | J29: N/A — truy vấn chưa chụp SERP | K29: Hỗ trợ pillar BA-0281 ("thanh toán cọc thuê xe an toàn")
A30: https://chatbot.thuexemaynguyentu.com/blog/an-toan/an-toan-khi-thanh-toan-coc/ | B30: BA-0281 | C30: Bài viết | D30: thanh toán cọc thuê xe an toàn | E30: thủ tục thuê xe máy | F30: Thông tin pháp lý | G30: K04 Thủ tục, giấy tờ, hợp đồng và đặt cọc | H30: N/A | I30: N/A — chưa đo volume | J30: N/A — truy vấn chưa chụp SERP | K30: Pillar cụm "thanh toán cọc thuê xe an toàn" (5 bài)
A31: https://chatbot.thuexemaynguyentu.com/blog/an-toan/bang-lai-a1-a2-khac-gi-cau-hoi-thuong-gap/ | B31: BA-1445 | C31: Bài viết | D31: câu hỏi thường gặp bằng lái a1 a2 | E31: bằng lái a1 a2 khác gì; bằng lái khi thuê xe máy; bằng lái | F31: Thông tin pháp lý | G31: K09 Bằng lái và luật giao thông | H31: N/A | I31: N/A — chưa đo volume | J31: N/A — truy vấn chưa chụp SERP | K31: Hỗ trợ pillar BA-0035 ("bằng lái a1 a2 khác gì")
A32: https://chatbot.thuexemaynguyentu.com/blog/an-toan/bang-lai-a1-a2-khac-gi-cho-du-khach/ | B32: BA-0317 | C32: Bài viết | D32: bằng lái a1 a2 khác gì cho du khách | E32: bằng lái a1 a2 khác gì; bằng lái khi thuê xe máy; bằng lái | F32: Thông tin pháp lý + so sánh | G32: K09 Bằng lái và luật giao thông | H32: N/A | I32: N/A — chưa đo volume | J32: N/A — truy vấn chưa chụp SERP | K32: Hỗ trợ pillar BA-0035 ("bằng lái a1 a2 khác gì")
... A53: https://chatbot.thuexemaynguyentu.com/blog/an-toan/bao-ve-du-lieu-ca-nhan-khi-thue-xe/ | B53: BA-0275 | C53: Bài viết | D53: bảo vệ dữ liệu cá nhân khi thuê xe | E53: bảo hiểm khi thuê xe máy | F53: Thông tin pháp lý | G53: K11 Bảo hiểm, tai nạn, quyền lợi người thuê | H53: N/A | I53: N/A — chưa đo volume | J53: N/A — truy vấn chưa chụp SERP | K53: Pillar cụm "bảo vệ dữ liệu cá nhân khi thuê xe" (5 bài)
A54: https://chatbot.thuexemaynguyentu.com/blog/an-toan/cac-loai-bang-lai-xe-may/ | B54: BA-2002 | C54: Bài viết | D54: các loại bằng lái xe máy | E54: bằng lái khi thuê xe máy; lái xe | F54: Thông tin pháp lý | G54: K09 Bằng lái và luật giao thông | H54: 1000 | I54: Đo được (keyword-demand / DataForSEO) | J54: không thấy trong top kết quả (2026-10-14) | K54: Pillar cụm "các loại bằng lái xe máy" (1 bài)
A55: https://chatbot.thuexemaynguyentu.com/blog/an-toan/cam-do-xe-may-dung-luat-cho-du-khach/ | B55: BA-0503 | C55: Bài viết | D55: cầm đồ xe máy đúng luật cho du khách | E55: cầm đồ xe máy đúng luật; bằng lái khi thuê xe máy; pháp luật | F55: Thông tin pháp lý | G55: K09 Bằng lái và luật giao thông | H55: N/A | I55: N/A — chưa đo volume | J55: N/A — truy vấn chưa chụp SERP | K55: Hỗ trợ pillar BA-0221 ("cầm đồ xe máy đúng luật")
A56: https://chatbot.thuexemaynguyentu.com/blog/an-toan/cam-do-xe-may-dung-luat-cho-nguoi-moi/ | B56: BA-0785 | C56: Bài viết | D56: cầm đồ xe máy đúng luật cho người mới | E56: cầm đồ xe máy đúng luật; bằng lái khi thuê xe máy; pháp luật | F56: Thông tin pháp lý | G56: K09 Bằng lái và luật giao thông | H56: N/A | I56: N/A — chưa đo volume | J56: N/A — truy vấn chưa chụp SERP | K56: Hỗ trợ pillar BA-0221 ("cầm đồ xe máy đúng luật")
A57: https://chatbot.thuexemaynguyentu.com/blog/an-toan/cam-do-xe-may-dung-luat-tom-tat/ | B57: BA-1067 | C57: Bài viết | D57: tóm tắt cầm đồ xe máy đúng luật | E57: cầm đồ xe máy đúng luật; bằng lái khi thuê xe máy; pháp luật | F57: Thông tin pháp lý | G57: K09 Bằng lái và luật giao thông | H57: N/A | I57: N/A — chưa đo volume | J57: N/A — truy vấn chưa chụp SERP | K57: Hỗ trợ pillar BA-0221 ("cầm đồ xe máy đúng luật")
A58: https://chatbot.thuexemaynguyentu.com/blog/an-toan/cam-do-xe-may-dung-luat-vi-du-thuc-te/ | B58: BA-1349 | C58: Bài viết | D58: ví dụ cầm đồ xe máy đúng luật | E58: cầm đồ xe máy đúng luật; bằng lái khi thuê xe máy; pháp luật | F58: Thông tin pháp lý | G58: K09 Bằng lái và luật giao thông | H58: N/A | I58: N/A — chưa đo volume | J58: N/A — truy vấn chưa chụp SERP | K58: Hỗ trợ pillar BA-0221 ("cầm đồ xe máy đúng luật")
A59: https://chatbot.thuexemaynguyentu.com/blog/an-toan/cam-do-xe-may-dung-luat/ | B59: BA-0221 | C59: Bài viết | D59: cầm đồ xe máy đúng luật | E59: bằng lái khi thuê xe máy; pháp luật | F59: Thông tin pháp lý | G59: K09 Bằng lái và luật giao thông | H59: N/A | I59: N/A — chưa đo volume | J59: N/A — truy vấn chưa chụp SERP | K59: Pillar cụm "cầm đồ xe máy đúng luật" (5 bài)
A60: https://chatbot.thuexemaynguyentu.com/blog/an-toan/cam-xe-may-xang-vanh-dai-1/ | B60: BA-2004 | C60: Bài viết | D60: cấm xe máy xăng vành đai 1 | E60: xe thuê bị hỏng phải làm sao; pháp luật | F60: Thông tin pháp lý | G60: K20 Bảo dưỡng, sự cố và xử lý khi đi đường | H60: N/A | I60: N/A — chưa đo volume | J60: không thấy trong top kết quả (2026-10-14) | K60: Pillar cụm "cấm xe máy xăng vành đai 1" (1 bài)
A61: https://chatbot.thuexemaynguyentu.com/blog/an-toan/camera-phat-nguoi-khi-thue-xe-cho-du-khach/ | B61: BA-0485 | C61: Bài viết | D61: camera phạt nguội khi thuê xe cho du khách | E61: camera phạt nguội khi thuê xe; bằng lái khi thuê xe máy; pháp luật | F61: Thông tin pháp lý | G61: K09 Bằng lái và luật giao thông | H61: N/A | I61: N/A — chưa đo volume | J61: N/A — truy vấn chưa chụp SERP | K61: Hỗ trợ pillar BA-0203 ("camera phạt nguội khi thuê xe")
A62: https://chatbot.thuexemaynguyentu.com/blog/an-toan/camera-phat-nguoi-khi-thue-xe-cho-nguoi-moi/ | B62: BA-0767 | C62: Bài viết | D62: camera phạt nguội khi thuê xe cho người mới | E62: camera phạt nguội khi thuê xe; bằng lái khi thuê xe máy; pháp luật | F62: Thông tin pháp lý | G62: K09 Bằng lái và luật giao thông | H62: N/A | I62: N/A — chưa đo volume | J62: N/A — truy vấn chưa chụp SERP | K62: Hỗ trợ pillar BA-0203 ("camera phạt nguội khi thuê xe")
A63: https://chatbot.thuexemaynguyentu.com/blog/an-toan/camera-phat-nguoi-khi-thue-xe-tom-tat/ | B63: BA-1049 | C63: Bài viết | D63: tóm tắt camera phạt nguội khi thuê xe | E63: camera phạt nguội khi thuê xe; bằng lái khi thuê xe máy; pháp luật | F63: Thông tin pháp lý | G63: K09 Bằng lái và luật giao thông | H63: N/A | I63: N/A — chưa đo volume | J63: N/A — truy vấn chưa chụp SERP | K63: Hỗ trợ pillar BA-0203 ("camera phạt nguội khi thuê xe")
A64: https://chatbot.thuexemaynguyentu.com/blog/an-toan/camera-phat-nguoi-khi-thue-xe-vi-du-thuc-te/ | B64: BA-1331 | C64: Bài viết | D64: ví dụ camera phạt nguội khi thuê xe | E64: camera phạt nguội khi thuê xe; bằng lái khi thuê xe máy; pháp luật | F64: Thông tin pháp lý | G64: K09 Bằng lái và luật giao thông | H64: N/A | I64: N/A — chưa đo volume | J64: N/A — truy vấn chưa chụp SERP | K64: Hỗ trợ pillar BA-0203 ("camera phạt nguội khi thuê xe")
A65: https://chatbot.thuexemaynguyentu.com/blog/an-toan/camera-phat-nguoi-khi-thue-xe/ | B65: BA-0203 | C65: Bài viết | D65: camera phạt nguội khi thuê xe | E65: bằng lái khi thuê xe máy; pháp luật | F65: Thông tin pháp lý | G65: K09 Bằng lái và luật giao thông | H65: N/A | I65: N/A — chưa đo volume | J65: N/A — truy vấn chưa chụp SERP | K65: Pillar cụm "camera phạt nguội khi thuê xe" (5 bài)
A66: https://chatbot.thuexemaynguyentu.com/blog/an-toan/cho-tre-em-tren-xe-may-cho-du-khach/ | B66: BA-0431 | C66: Bài viết | D66: chở trẻ em trên xe máy cho du khách | E66: chở trẻ em trên xe máy; kinh nghiệm lái xe máy an toàn ở Hà Nội | F66: Thông tin pháp lý | G66: K10 An toàn khi lái xe máy | H66: N/A | I66: N/A — chưa đo volume | J66: N/A — truy vấn chưa chụp SERP | K66: Hỗ trợ pillar BA-0149 ("chở trẻ em trên xe máy")
... A101: https://chatbot.thuexemaynguyentu.com/blog/an-toan/di-xe-khong-giay-phep-vi-du-thuc-te/ | B101: BA-1157 | C101: Bài viết | D101: ví dụ đi xe không giấy phép | E101: không có bằng lái xe máy phạt bao nhiêu; bằng lái khi thuê xe máy; pháp luật | F101: Thông tin pháp lý | G101: K09 Bằng lái và luật giao thông | H101: N/A | I101: N/A — chưa đo volume | J101: N/A — truy vấn chưa chụp SERP | K101: Hỗ trợ pillar BA-0029 ("không có bằng lái xe máy phạt bao nhiêu")
A102: https://chatbot.thuexemaynguyentu.com/blog/an-toan/di-xe-khong-giay-phep/ | B102: BA-0029 | C102: Bài viết | D102: không có bằng lái xe máy phạt bao nhiêu | E102: bằng lái khi thuê xe máy; pháp luật | F102: Thông tin pháp lý | G102: K09 Bằng lái và luật giao thông | H102: 5400 | I102: Đo được (keyword-demand / DataForSEO) | J102: không thấy trong top kết quả (2026-10-14) | K102: Pillar cụm "không có bằng lái xe máy phạt bao nhiêu" (6 bài)
A103: https://chatbot.thuexemaynguyentu.com/blog/an-toan/dien-thoai-khi-lai-xe-cho-du-khach/ | B103: BA-0425 | C103: Bài viết | D103: dùng điện thoại khi lái xe máy cho du khách | E103: dùng điện thoại khi lái xe máy; kinh nghiệm lái xe máy an toàn ở Hà Nội; lái xe | F103: Thông tin pháp lý | G103: K10 An toàn khi lái xe máy | H103: N/A | I103: N/A — chưa đo volume | J103: N/A — truy vấn chưa chụp SERP | K103: Hỗ trợ pillar BA-0143 ("dùng điện thoại khi lái xe máy")
A104: https://chatbot.thuexemaynguyentu.com/blog/an-toan/dien-thoai-khi-lai-xe-cho-nguoi-moi/ | B104: BA-0707 | C104: Bài viết | D104: dùng điện thoại khi lái xe máy cho người mới | E104: dùng điện thoại khi lái xe máy; kinh nghiệm lái xe máy an toàn ở Hà Nội; lái xe | F104: Thông tin pháp lý | G104: K10 An toàn khi lái xe máy | H104: N/A | I104: N/A — chưa đo volume | J104: N/A — truy vấn chưa chụp SERP | K104: Hỗ trợ pillar BA-0143 ("dùng điện thoại khi lái xe máy")
A105: https://chatbot.thuexemaynguyentu.com/blog/an-toan/dien-thoai-khi-lai-xe-tom-tat/ | B105: BA-0989 | C105: Bài viết | D105: tóm tắt dùng điện thoại khi lái xe máy | E105: dùng điện thoại khi lái xe máy; kinh nghiệm lái xe máy an toàn ở Hà Nội; lái xe | F105: Thông tin pháp lý | G105: K10 An toàn khi lái xe máy | H105: N/A | I105: N/A — chưa đo volume | J105: N/A — truy vấn chưa chụp SERP | K105: Hỗ trợ pillar BA-0143 ("dùng điện thoại khi lái xe máy")
A106: https://chatbot.thuexemaynguyentu.com/blog/an-toan/dien-thoai-khi-lai-xe-vi-du-thuc-te/ | B106: BA-1271 | C106: Bài viết | D106: ví dụ dùng điện thoại khi lái xe máy | E106: dùng điện thoại khi lái xe máy; kinh nghiệm lái xe máy an toàn ở Hà Nội; lái xe | F106: Thông tin pháp lý | G106: K10 An toàn khi lái xe máy | H106: N/A | I106: N/A — chưa đo volume | J106: N/A — truy vấn chưa chụp SERP | K106: Hỗ trợ pillar BA-0143 ("dùng điện thoại khi lái xe máy")
A107: https://chatbot.thuexemaynguyentu.com/blog/an-toan/dien-thoai-khi-lai-xe/ | B107: BA-0143 | C107: Bài viết | D107: dùng điện thoại khi lái xe máy | E107: kinh nghiệm lái xe máy an toàn ở Hà Nội; lái xe | F107: Thông tin pháp lý | G107: K10 An toàn khi lái xe máy | H107: N/A | I107: N/A — chưa đo volume | J107: N/A — truy vấn chưa chụp SERP | K107: Pillar cụm "dùng điện thoại khi lái xe máy" (5 bài)
A108: https://chatbot.thuexemaynguyentu.com/blog/an-toan/du-lich/ | B108: N/A | C108: Hub chủ đề con | D108: luật giao thông và an toàn khi thuê xe máy | E108: an toàn / pháp lý | F108: Điều hướng / danh sách | G108: K10 An toàn khi lái xe máy | H108: N/A | I108: N/A — chưa đo volume | J108: N/A — truy vấn chưa chụp SERP | K108: Không (trang điều hướng/chuyển đổi duy nhất)
A109: https://chatbot.thuexemaynguyentu.com/blog/an-toan/goi-canh-sat-khi-tai-nan-cau-hoi-thuong-gap/ | B109: BA-1481 | C109: Bài viết | D109: câu hỏi thường gặp gọi cảnh sát khi tai nạn | E109: gọi cảnh sát khi tai nạn; bảo hiểm khi thuê xe máy; sự cố | F109: Thông tin pháp lý | G109: K11 Bảo hiểm, tai nạn, quyền lợi người thuê | H109: N/A | I109: N/A — chưa đo volume | J109: N/A — truy vấn chưa chụp SERP | K109: Hỗ trợ pillar BA-0071 ("gọi cảnh sát khi tai nạn")
A110: https://chatbot.thuexemaynguyentu.com/blog/an-toan/goi-canh-sat-khi-tai-nan-cho-du-khach/ | B110: BA-0353 | C110: Bài viết | D110: gọi cảnh sát khi tai nạn cho du khách | E110: gọi cảnh sát khi tai nạn; bảo hiểm khi thuê xe máy; sự cố | F110: Thông tin pháp lý | G110: K11 Bảo hiểm, tai nạn, quyền lợi người thuê | H110: N/A | I110: N/A — chưa đo volume | J110: N/A — truy vấn chưa chụp SERP | K110: Hỗ trợ pillar BA-0071 ("gọi cảnh sát khi tai nạn")
A111: https://chatbot.thuexemaynguyentu.com/blog/an-toan/goi-canh-sat-khi-tai-nan-cho-nguoi-moi/ | B111: BA-0635 | C111: Bài viết | D111: gọi cảnh sát khi tai nạn cho người mới | E111: gọi cảnh sát khi tai nạn; bảo hiểm khi thuê xe máy; sự cố | F111: Thông tin pháp lý | G111: K11 Bảo hiểm, tai nạn, quyền lợi người thuê | H111: N/A | I111: N/A — chưa đo volume | J111: N/A — truy vấn chưa chụp SERP | K111: Hỗ trợ pillar BA-0071 ("gọi cảnh sát khi tai nạn")
A112: https://chatbot.thuexemaynguyentu.com/blog/an-toan/goi-canh-sat-khi-tai-nan-tom-tat/ | B112: BA-0917 | C112: Bài viết | D112: tóm tắt gọi cảnh sát khi tai nạn | E112: gọi cảnh sát khi tai nạn; bảo hiểm khi thuê xe máy; sự cố | F112: Thông tin pháp lý | G112: K11 Bảo hiểm, tai nạn, quyền lợi người thuê | H112: N/A | I112: N/A — chưa đo volume | J112: N/A — truy vấn chưa chụp SERP | K112: Hỗ trợ pillar BA-0071 ("gọi cảnh sát khi tai nạn")
A113: https://chatbot.thuexemaynguyentu.com/blog/an-toan/goi-canh-sat-khi-tai-nan-vi-du-thuc-te/ | B113: BA-1199 | C113: Bài viết | D113: ví dụ gọi cảnh sát khi tai nạn | E113: gọi cảnh sát khi tai nạn; bảo hiểm khi thuê xe máy; sự cố | F113: Thông tin pháp lý | G113: K11 Bảo hiểm, tai nạn, quyền lợi người thuê | H113: N/A | I113: N/A — chưa đo volume | J113: N/A — truy vấn chưa chụp SERP | K113: Hỗ trợ pillar BA-0071 ("gọi cảnh sát khi tai nạn")
A114: https://chatbot.thuexemaynguyentu.com/blog/an-toan/goi-canh-sat-khi-tai-nan/ | B114: BA-0071 | C114: Bài viết | D114: gọi cảnh sát khi tai nạn | E114: bảo hiểm khi thuê xe máy; sự cố | F114: Thông tin pháp lý | G114: K11 Bảo hiểm, tai nạn, quyền lợi người thuê | H114: N/A | I114: N/A — chưa đo volume | J114: N/A — truy vấn chưa chụp SERP | K114: Pillar cụm "gọi cảnh sát khi tai nạn" (6 bài)
... A153: https://chatbot.thuexemaynguyentu.com/blog/an-toan/lan-duong-va-quy-tac-nhuong/ | B153: BA-0125 | C153: Bài viết | D153: quy tắc làn đường và nhường đường | E153: bằng lái khi thuê xe máy; pháp luật | F153: Thông tin pháp lý | G153: K09 Bằng lái và luật giao thông | H153: N/A | I153: N/A — chưa đo volume | J153: N/A — truy vấn chưa chụp SERP | K153: Pillar cụm "quy tắc làn đường và nhường đường" (5 bài)
A154: https://chatbot.thuexemaynguyentu.com/blog/an-toan/loi-khong-guong-xe-may/ | B154: BA-2003 | C154: Bài viết | D154: lỗi không gương xe máy | E154: kinh nghiệm lái xe máy an toàn ở Hà Nội; pháp luật | F154: Thông tin pháp lý | G154: K10 An toàn khi lái xe máy | H154: 2400 | I154: Đo được (keyword-demand / DataForSEO) | J154: không thấy trong top kết quả (2026-10-14) | K154: Pillar cụm "lỗi không gương xe máy" (1 bài)
A155: https://chatbot.thuexemaynguyentu.com/blog/an-toan/luat-giao-thong-duong-bo-co-ban-cau-hoi-thuong-gap/ | B155: BA-1415 | C155: Bài viết | D155: câu hỏi về luật giao thông khi thuê xe máy | E155: luật giao thông đường bộ cơ bản; bằng lái khi thuê xe máy; pháp luật | F155: Thông tin pháp lý | G155: K09 Bằng lái và luật giao thông | H155: N/A | I155: N/A — chưa đo volume | J155: N/A — truy vấn chưa chụp SERP | K155: Hỗ trợ pillar BA-0005 ("luật giao thông đường bộ cơ bản")
A156: https://chatbot.thuexemaynguyentu.com/blog/an-toan/luat-giao-thong-duong-bo-co-ban-cho-du-khach/ | B156: BA-0287 | C156: Bài viết | D156: luật giao thông đường bộ cơ bản cho du khách | E156: luật giao thông đường bộ cơ bản; bằng lái khi thuê xe máy; pháp luật | F156: Thông tin pháp lý | G156: K09 Bằng lái và luật giao thông | H156: N/A | I156: N/A — chưa đo volume | J156: N/A — truy vấn chưa chụp SERP | K156: Hỗ trợ pillar BA-0005 ("luật giao thông đường bộ cơ bản")
A157: https://chatbot.thuexemaynguyentu.com/blog/an-toan/luat-giao-thong-duong-bo-co-ban-cho-nguoi-moi/ | B157: BA-0569 | C157: Bài viết | D157: luật giao thông đường bộ cơ bản cho người mới | E157: luật giao thông đường bộ cơ bản; bằng lái khi thuê xe máy; pháp luật | F157: Thông tin pháp lý | G157: K09 Bằng lái và luật giao thông | H157: N/A | I157: N/A — chưa đo volume | J157: N/A — truy vấn chưa chụp SERP | K157: Hỗ trợ pillar BA-0005 ("luật giao thông đường bộ cơ bản")
A158: https://chatbot.thuexemaynguyentu.com/blog/an-toan/luat-giao-thong-duong-bo-co-ban-tom-tat/ | B158: BA-0851 | C158: Bài viết | D158: tóm tắt luật giao thông đường bộ cơ bản | E158: luật giao thông đường bộ cơ bản; bằng lái khi thuê xe máy; pháp luật | F158: Thông tin pháp lý | G158: K09 Bằng lái và luật giao thông | H158: N/A | I158: N/A — chưa đo volume | J158: N/A — truy vấn chưa chụp SERP | K158: Hỗ trợ pillar BA-0005 ("luật giao thông đường bộ cơ bản")
A159: https://chatbot.thuexemaynguyentu.com/blog/an-toan/luat-giao-thong-duong-bo-co-ban-vi-du-thuc-te/ | B159: BA-1133 | C159: Bài viết | D159: ví dụ luật giao thông đường bộ cơ bản | E159: luật giao thông đường bộ cơ bản; bằng lái khi thuê xe máy; pháp luật | F159: Thông tin pháp lý | G159: K09 Bằng lái và luật giao thông | H159: N/A | I159: N/A — chưa đo volume | J159: N/A — truy vấn chưa chụp SERP | K159: Hỗ trợ pillar BA-0005 ("luật giao thông đường bộ cơ bản")
A160: https://chatbot.thuexemaynguyentu.com/blog/an-toan/luat-giao-thong-duong-bo-co-ban/ | B160: BA-0005 | C160: Bài viết | D160: luật giao thông đường bộ cơ bản | E160: bằng lái khi thuê xe máy; pháp luật | F160: Thông tin pháp lý | G160: K09 Bằng lái và luật giao thông | H160: N/A | I160: N/A — chưa đo volume | J160: N/A — truy vấn chưa chụp SERP | K160: Pillar cụm "luật giao thông đường bộ cơ bản" (6 bài)
A161: https://chatbot.thuexemaynguyentu.com/blog/an-toan/met-moi-khi-lai-duong-dai-cho-du-khach/ | B161: BA-0455 | C161: Bài viết | D161: mệt mỏi khi lái xe đường dài cho du khách | E161: mệt mỏi khi lái xe đường dài; kinh nghiệm lái xe máy an toàn ở Hà Nội; du lịch | F161: Thông tin pháp lý | G161: K10 An toàn khi lái xe máy | H161: N/A | I161: N/A — chưa đo volume | J161: N/A — truy vấn chưa chụp SERP | K161: Hỗ trợ pillar BA-0173 ("mệt mỏi khi lái xe đường dài")
A162: https://chatbot.thuexemaynguyentu.com/blog/an-toan/met-moi-khi-lai-duong-dai-cho-nguoi-moi/ | B162: BA-0737 | C162: Bài viết | D162: người mới lái xe đường dài bị mệt | E162: mệt mỏi khi lái xe đường dài; kinh nghiệm lái xe máy an toàn ở Hà Nội; du lịch | F162: Thông tin pháp lý | G162: K10 An toàn khi lái xe máy | H162: N/A | I162: N/A — chưa đo volume | J162: N/A — truy vấn chưa chụp SERP | K162: Hỗ trợ pillar BA-0173 ("mệt mỏi khi lái xe đường dài")
A163: https://chatbot.thuexemaynguyentu.com/blog/an-toan/met-moi-khi-lai-duong-dai-tom-tat/ | B163: BA-1019 | C163: Bài viết | D163: tóm tắt mệt mỏi khi lái xe đường dài | E163: mệt mỏi khi lái xe đường dài; kinh nghiệm lái xe máy an toàn ở Hà Nội; du lịch | F163: Thông tin pháp lý | G163: K10 An toàn khi lái xe máy | H163: N/A | I163: N/A — chưa đo volume | J163: N/A — truy vấn chưa chụp SERP | K163: Hỗ trợ pillar BA-0173 ("mệt mỏi khi lái xe đường dài")
A164: https://chatbot.thuexemaynguyentu.com/blog/an-toan/met-moi-khi-lai-duong-dai-vi-du-thuc-te/ | B164: BA-1301 | C164: Bài viết | D164: ví dụ mệt mỏi khi lái xe đường dài | E164: mệt mỏi khi lái xe đường dài; kinh nghiệm lái xe máy an toàn ở Hà Nội; du lịch | F164: Thông tin pháp lý | G164: K10 An toàn khi lái xe máy | H164: N/A | I164: N/A — chưa đo volume | J164: N/A — truy vấn chưa chụp SERP | K164: Hỗ trợ pillar BA-0173 ("mệt mỏi khi lái xe đường dài")
A165: https://chatbot.thuexemaynguyentu.com/blog/an-toan/met-moi-khi-lai-duong-dai/ | B165: BA-0173 | C165: Bài viết | D165: mệt mỏi khi lái xe đường dài | E165: kinh nghiệm lái xe máy an toàn ở Hà Nội; du lịch | F165: Thông tin pháp lý | G165: K10 An toàn khi lái xe máy | H165: N/A | I165: N/A — chưa đo volume | J165: N/A — truy vấn chưa chụp SERP | K165: Pillar cụm "mệt mỏi khi lái xe đường dài" (5 bài)
A166: https://chatbot.thuexemaynguyentu.com/blog/an-toan/mu-bao-hiem-chuan-cau-hoi-thuong-gap/ | B166: BA-1427 | C166: Bài viết | D166: câu hỏi về mũ bảo hiểm chuẩn | E166: mũ bảo hiểm đạt chuẩn; kinh nghiệm lái xe máy an toàn ở Hà Nội; mũ bảo hiểm | F166: Thông tin pháp lý | G166: K10 An toàn khi lái xe máy | H166: N/A | I166: N/A — chưa đo volume | J166: N/A — truy vấn chưa chụp SERP | K166: Hỗ trợ pillar BA-0017 ("mũ bảo hiểm đạt chuẩn")
... A170: https://chatbot.thuexemaynguyentu.com/blog/an-toan/mu-bao-hiem-chuan-vi-du-thuc-te/ | B170: BA-1145 | C170: Bài viết | D170: ví dụ mũ bảo hiểm chuẩn | E170: mũ bảo hiểm đạt chuẩn; kinh nghiệm lái xe máy an toàn ở Hà Nội; mũ bảo hiểm | F170: Thông tin pháp lý | G170: K10 An toàn khi lái xe máy | H170: N/A | I170: N/A — chưa đo volume | J170: N/A — truy vấn chưa chụp SERP | K170: Hỗ trợ pillar BA-0017 ("mũ bảo hiểm đạt chuẩn")
A171: https://chatbot.thuexemaynguyentu.com/blog/an-toan/mu-bao-hiem-chuan/ | B171: BA-0017 | C171: Bài viết | D171: mũ bảo hiểm đạt chuẩn | E171: kinh nghiệm lái xe máy an toàn ở Hà Nội; mũ bảo hiểm | F171: Thông tin pháp lý | G171: K10 An toàn khi lái xe máy | H171: 590 | I171: Đo được (keyword-demand / DataForSEO) | J171: không thấy trong top kết quả (2026-10-14) | K171: Pillar cụm "mũ bảo hiểm đạt chuẩn" (6 bài)
A172: https://chatbot.thuexemaynguyentu.com/blog/an-toan/mu-bao-hiem/ | B172: N/A | C172: Hub chủ đề con | D172: luật giao thông và an toàn khi thuê xe máy | E172: an toàn / pháp lý | F172: Điều hướng / danh sách | G172: K10 An toàn khi lái xe máy | H172: N/A | I172: N/A — chưa đo volume | J172: N/A — truy vấn chưa chụp SERP | K172: Không (trang điều hướng/chuyển đổi duy nhất)
A173: https://chatbot.thuexemaynguyentu.com/blog/an-toan/mua-ban-xe-may-giay-to-cho-du-khach/ | B173: BA-0509 | C173: Bài viết | D173: du khách mua xe máy cần giấy tờ gì | E173: mua bán xe máy giấy tờ; thủ tục thuê xe máy | F173: Thông tin pháp lý | G173: K04 Thủ tục, giấy tờ, hợp đồng và đặt cọc | H173: N/A | I173: N/A — chưa đo volume | J173: N/A — truy vấn chưa chụp SERP | K173: Hỗ trợ pillar BA-0227 ("mua bán xe máy giấy tờ")
A174: https://chatbot.thuexemaynguyentu.com/blog/an-toan/mua-ban-xe-may-giay-to-cho-nguoi-moi/ | B174: BA-0791 | C174: Bài viết | D174: mua xe máy cũ lần đầu cần giấy tờ gì | E174: mua bán xe máy giấy tờ; thủ tục thuê xe máy | F174: Thông tin pháp lý | G174: K04 Thủ tục, giấy tờ, hợp đồng và đặt cọc | H174: N/A | I174: N/A — chưa đo volume | J174: N/A — truy vấn chưa chụp SERP | K174: Hỗ trợ pillar BA-0227 ("mua bán xe máy giấy tờ")
A175: https://chatbot.thuexemaynguyentu.com/blog/an-toan/mua-ban-xe-may-giay-to-tom-tat/ | B175: BA-1073 | C175: Bài viết | D175: tóm tắt giấy tờ mua bán xe máy | E175: mua bán xe máy giấy tờ; thủ tục thuê xe máy | F175: Thông tin pháp lý | G175: K04 Thủ tục, giấy tờ, hợp đồng và đặt cọc | H175: N/A | I175: N/A — chưa đo volume | J175: N/A — truy vấn chưa chụp SERP | K175: Hỗ trợ pillar BA-0227 ("mua bán xe máy giấy tờ")
A176: https://chatbot.thuexemaynguyentu.com/blog/an-toan/mua-ban-xe-may-giay-to-vi-du-thuc-te/ | B176: BA-1355 | C176: Bài viết | D176: ví dụ giấy tờ mua bán xe máy | E176: mua bán xe máy giấy tờ; thủ tục thuê xe máy | F176: Thông tin pháp lý | G176: K04 Thủ tục, giấy tờ, hợp đồng và đặt cọc | H176: N/A | I176: N/A — chưa đo volume | J176: N/A — truy vấn chưa chụp SERP | K176: Hỗ trợ pillar BA-0227 ("mua bán xe máy giấy tờ")
A177: https://chatbot.thuexemaynguyentu.com/blog/an-toan/mua-ban-xe-may-giay-to/ | B177: BA-0227 | C177: Bài viết | D177: mua bán xe máy giấy tờ | E177: thủ tục thuê xe máy | F177: Thông tin pháp lý | G177: K04 Thủ tục, giấy tờ, hợp đồng và đặt cọc | H177: N/A | I177: N/A — chưa đo volume | J177: N/A — truy vấn chưa chụp SERP | K177: Pillar cụm "mua bán xe máy giấy tờ" (5 bài)
A178: https://chatbot.thuexemaynguyentu.com/blog/an-toan/mua-lon-va-lai-xe-cho-du-khach/ | B178: BA-0383 | C178: Bài viết | D178: du khách đi xe máy gặp mưa lớn | E178: lái xe máy khi mưa lớn; kinh nghiệm lái xe máy an toàn ở Hà Nội; lái xe | F178: Thông tin pháp lý | G178: K10 An toàn khi lái xe máy | H178: N/A | I178: N/A — chưa đo volume | J178: N/A — truy vấn chưa chụp SERP | K178: Hỗ trợ pillar BA-0101 ("lái xe máy khi mưa lớn")
A179: https://chatbot.thuexemaynguyentu.com/blog/an-toan/mua-lon-va-lai-xe-cho-nguoi-moi/ | B179: BA-0665 | C179: Bài viết | D179: người mới lái xe máy khi mưa lớn | E179: lái xe máy khi mưa lớn; kinh nghiệm lái xe máy an toàn ở Hà Nội; lái xe | F179: Thông tin pháp lý | G179: K10 An toàn khi lái xe máy | H179: N/A | I179: N/A — chưa đo volume | J179: N/A — truy vấn chưa chụp SERP | K179: Hỗ trợ pillar BA-0101 ("lái xe máy khi mưa lớn")
A180: https://chatbot.thuexemaynguyentu.com/blog/an-toan/mua-lon-va-lai-xe-tom-tat/ | B180: BA-0947 | C180: Bài viết | D180: tóm tắt lái xe máy khi mưa lớn | E180: lái xe máy khi mưa lớn; kinh nghiệm lái xe máy an toàn ở Hà Nội; lái xe | F180: Thông tin pháp lý | G180: K10 An toàn khi lái xe máy | H180: N/A | I180: N/A — chưa đo volume | J180: N/A — truy vấn chưa chụp SERP | K180: Hỗ trợ pillar BA-0101 ("lái xe máy khi mưa lớn")
A181: https://chatbot.thuexemaynguyentu.com/blog/an-toan/mua-lon-va-lai-xe-vi-du-thuc-te/ | B181: BA-1229 | C181: Bài viết | D181: ví dụ lái xe máy khi mưa lớn | E181: lái xe máy khi mưa lớn; kinh nghiệm lái xe máy an toàn ở Hà Nội; lái xe | F181: Thông tin pháp lý | G181: K10 An toàn khi lái xe máy | H181: N/A | I181: N/A — chưa đo volume | J181: N/A — truy vấn chưa chụp SERP | K181: Hỗ trợ pillar BA-0101 ("lái xe máy khi mưa lớn")
A182: https://chatbot.thuexemaynguyentu.com/blog/an-toan/mua-lon-va-lai-xe/ | B182: BA-0101 | C182: Bài viết | D182: lái xe máy khi mưa lớn | E182: kinh nghiệm lái xe máy an toàn ở Hà Nội; lái xe | F182: Thông tin pháp lý | G182: K10 An toàn khi lái xe máy | H182: N/A | I182: N/A — chưa đo volume | J182: N/A — truy vấn chưa chụp SERP | K182: Pillar cụm "lái xe máy khi mưa lớn" (5 bài)
A183: https://chatbot.thuexemaynguyentu.com/blog/an-toan/ngap-nuoc-va-xe-may-cho-du-khach/ | B183: BA-0473 | C183: Bài viết | D183: du khách đi xe máy gặp đường ngập | E183: đi xe máy qua đường ngập nước; kinh nghiệm lái xe máy an toàn ở Hà Nội | F183: Thông tin pháp lý | G183: K10 An toàn khi lái xe máy | H183: N/A | I183: N/A — chưa đo volume | J183: N/A — truy vấn chưa chụp SERP | K183: Hỗ trợ pillar BA-0191 ("đi xe máy qua đường ngập nước")
... A208: https://chatbot.thuexemaynguyentu.com/blog/an-toan/nong-do-con-khi-lai-xe-vi-du-thuc-te/ | B208: BA-1139 | C208: Bài viết | D208: ví dụ nồng độ cồn khi lái xe máy | E208: mức phạt nồng độ cồn xe máy; bằng lái khi thuê xe máy; pháp luật | F208: Thông tin pháp lý | G208: K09 Bằng lái và luật giao thông | H208: N/A | I208: N/A — chưa đo volume | J208: N/A — truy vấn chưa chụp SERP | K208: Hỗ trợ pillar BA-0011 ("mức phạt nồng độ cồn xe máy")
A209: https://chatbot.thuexemaynguyentu.com/blog/an-toan/nong-do-con-khi-lai-xe/ | B209: BA-0011 | C209: Bài viết | D209: mức phạt nồng độ cồn xe máy | E209: bằng lái khi thuê xe máy; pháp luật | F209: Thông tin pháp lý | G209: K09 Bằng lái và luật giao thông | H209: 5400 | I209: Đo được (keyword-demand / DataForSEO) | J209: không thấy trong top kết quả (2026-10-14) | K209: Pillar cụm "mức phạt nồng độ cồn xe máy" (6 bài)
A210: https://chatbot.thuexemaynguyentu.com/blog/an-toan/phap-luat/ | B210: N/A | C210: Hub chủ đề con | D210: luật giao thông và an toàn khi thuê xe máy | E210: an toàn / pháp lý | F210: Điều hướng / danh sách | G210: K10 An toàn khi lái xe máy | H210: N/A | I210: N/A — chưa đo volume | J210: N/A — truy vấn chưa chụp SERP | K210: Không (trang điều hướng/chuyển đổi duy nhất)
A211: https://chatbot.thuexemaynguyentu.com/blog/an-toan/phat-nguoi-va-xe-thue-cho-du-khach/ | B211: BA-0491 | C211: Bài viết | D211: phạt nguội xe thuê cho du khách | E211: phạt nguội xe thuê; bằng lái khi thuê xe máy; pháp luật | F211: Thông tin pháp lý | G211: K09 Bằng lái và luật giao thông | H211: N/A | I211: N/A — chưa đo volume | J211: N/A — truy vấn chưa chụp SERP | K211: Hỗ trợ pillar BA-0209 ("phạt nguội xe thuê")
A212: https://chatbot.thuexemaynguyentu.com/blog/an-toan/phat-nguoi-va-xe-thue-cho-nguoi-moi/ | B212: BA-0773 | C212: Bài viết | D212: phạt nguội xe thuê cho người mới | E212: phạt nguội xe thuê; bằng lái khi thuê xe máy; pháp luật | F212: Thông tin pháp lý | G212: K09 Bằng lái và luật giao thông | H212: N/A | I212: N/A — chưa đo volume | J212: N/A — truy vấn chưa chụp SERP | K212: Hỗ trợ pillar BA-0209 ("phạt nguội xe thuê")
A213: https://chatbot.thuexemaynguyentu.com/blog/an-toan/phat-nguoi-va-xe-thue-tom-tat/ | B213: BA-1055 | C213: Bài viết | D213: tóm tắt phạt nguội xe thuê | E213: phạt nguội xe thuê; bằng lái khi thuê xe máy; pháp luật | F213: Thông tin pháp lý | G213: K09 Bằng lái và luật giao thông | H213: N/A | I213: N/A — chưa đo volume | J213: N/A — truy vấn chưa chụp SERP | K213: Hỗ trợ pillar BA-0209 ("phạt nguội xe thuê")
A214: https://chatbot.thuexemaynguyentu.com/blog/an-toan/phat-nguoi-va-xe-thue-vi-du-thuc-te/ | B214: BA-1337 | C214: Bài viết | D214: ví dụ phạt nguội xe thuê | E214: phạt nguội xe thuê; bằng lái khi thuê xe máy; pháp luật | F214: Thông tin pháp lý | G214: K09 Bằng lái và luật giao thông | H214: N/A | I214: N/A — chưa đo volume | J214: N/A — truy vấn chưa chụp SERP | K214: Hỗ trợ pillar BA-0209 ("phạt nguội xe thuê")
A215: https://chatbot.thuexemaynguyentu.com/blog/an-toan/phat-nguoi-va-xe-thue/ | B215: BA-0209 | C215: Bài viết | D215: phạt nguội xe thuê | E215: bằng lái khi thuê xe máy; pháp luật | F215: Thông tin pháp lý | G215: K09 Bằng lái và luật giao thông | H215: N/A | I215: N/A — chưa đo volume | J215: N/A — truy vấn chưa chụp SERP | K215: Pillar cụm "phạt nguội xe thuê" (5 bài)
A216: https://chatbot.thuexemaynguyentu.com/blog/an-toan/quy-dinh-mu-bao-hiem-tre-em-cho-du-khach/ | B216: BA-0437 | C216: Bài viết | D216: quy định mũ bảo hiểm trẻ em cho du khách | E216: quy định mũ bảo hiểm trẻ em; kinh nghiệm lái xe máy an toàn ở Hà Nội; mũ bảo hiểm | F216: Thông tin pháp lý | G216: K10 An toàn khi lái xe máy | H216: N/A | I216: N/A — chưa đo volume | J216: N/A — truy vấn chưa chụp SERP | K216: Hỗ trợ pillar BA-0155 ("quy định mũ bảo hiểm trẻ em")
A217: https://chatbot.thuexemaynguyentu.com/blog/an-toan/quy-dinh-mu-bao-hiem-tre-em-cho-nguoi-moi/ | B217: BA-0719 | C217: Bài viết | D217: mũ bảo hiểm trẻ em cho người mới chở con | E217: quy định mũ bảo hiểm trẻ em; kinh nghiệm lái xe máy an toàn ở Hà Nội; mũ bảo hiểm | F217: Thông tin pháp lý | G217: K10 An toàn khi lái xe máy | H217: N/A | I217: N/A — chưa đo volume | J217: N/A — truy vấn chưa chụp SERP | K217: Hỗ trợ pillar BA-0155 ("quy định mũ bảo hiểm trẻ em")
A218: https://chatbot.thuexemaynguyentu.com/blog/an-toan/quy-dinh-mu-bao-hiem-tre-em-tom-tat/ | B218: BA-1001 | C218: Bài viết | D218: tóm tắt quy định mũ bảo hiểm trẻ em | E218: quy định mũ bảo hiểm trẻ em; kinh nghiệm lái xe máy an toàn ở Hà Nội; mũ bảo hiểm | F218: Thông tin pháp lý | G218: K10 An toàn khi lái xe máy | H218: N/A | I218: N/A — chưa đo volume | J218: N/A — truy vấn chưa chụp SERP | K218: Hỗ trợ pillar BA-0155 ("quy định mũ bảo hiểm trẻ em")
A219: https://chatbot.thuexemaynguyentu.com/blog/an-toan/quy-dinh-mu-bao-hiem-tre-em-vi-du-thuc-te/ | B219: BA-1283 | C219: Bài viết | D219: ví dụ quy định mũ bảo hiểm trẻ em | E219: quy định mũ bảo hiểm trẻ em; kinh nghiệm lái xe máy an toàn ở Hà Nội; mũ bảo hiểm | F219: Thông tin pháp lý | G219: K10 An toàn khi lái xe máy | H219: N/A | I219: N/A — chưa đo volume | J219: N/A — truy vấn chưa chụp SERP | K219: Hỗ trợ pillar BA-0155 ("quy định mũ bảo hiểm trẻ em")
A220: https://chatbot.thuexemaynguyentu.com/blog/an-toan/quy-dinh-mu-bao-hiem-tre-em/ | B220: BA-0155 | C220: Bài viết | D220: quy định mũ bảo hiểm trẻ em | E220: kinh nghiệm lái xe máy an toàn ở Hà Nội; mũ bảo hiểm | F220: Thông tin pháp lý | G220: K10 An toàn khi lái xe máy | H220: N/A | I220: N/A — chưa đo volume | J220: N/A — truy vấn chưa chụp SERP | K220: Pillar cụm "quy định mũ bảo hiểm trẻ em" (5 bài)
A221: https://chatbot.thuexemaynguyentu.com/blog/an-toan/quyen-cua-nguoi-thue-xe-cho-du-khach/ | B221: BA-0539 | C221: Bài viết | D221: quyền của du khách khi thuê xe máy | E221: quyền của người thuê xe máy; bảo hiểm khi thuê xe máy | F221: Thông tin pháp lý | G221: K11 Bảo hiểm, tai nạn, quyền lợi người thuê | H221: N/A | I221: N/A — chưa đo volume | J221: N/A — truy vấn chưa chụp SERP | K221: Hỗ trợ pillar BA-0257 ("quyền của người thuê xe máy")
... A280: https://chatbot.thuexemaynguyentu.com/blog/an-toan/xe-co-phia-truoc-va-khoang-cach-an-toan/ | B280: BA-0119 | C280: Bài viết | D280: khoảng cách an toàn với xe phía trước | E280: kinh nghiệm lái xe máy an toàn ở Hà Nội; lái xe | F280: Thông tin pháp lý | G280: K10 An toàn khi lái xe máy | H280: N/A | I280: N/A — chưa đo volume | J280: N/A — truy vấn chưa chụp SERP | K280: Pillar cụm "khoảng cách an toàn với xe phía trước" (5 bài)
...

Sheet CANNIBALIZATION
A1: Quy tắc: không gộp chỉ vì từ khóa giống nhau. Gộp/redirect cần (1) trùng ý định + (2) trùng nội dung (Jaccard ≥ 0,5) hoặc (3) GSC cho thấy URL hoán đổi — N/A — thiếu nguồn: Google Search Console chưa kết nối (OpenSEO 0 tài khoản Google; data/seo/performance/ trống). Bổ ngữ slug nhận diện: cho-khach-nuoc-ngoai, cau-hoi-thuong-gap, cho-khach-du-lich, hai-ngay-mot-dem, cho-nguoi-moi, cho-sinh-vien, vi-du-thuc-te, cho-du-khach, cho-gia-dinh, gia-tot-nhat, ky-nghi-le, tai-ha-noi, trong-ngay, cuoi-tuan, nhanh-gon, buoi-sang, checklist, nam-2026, buoi-toi, chay-pho, gia-tot, tom-tat, mua-thu, tan-noi, dai-han, mua-mua, mua-he.
A2: Loại kiểm tra | B2: Từ khóa / chủ đề | C2: Số URL | D2: URL | E2: Jaccard cao nhất | F2: Tỉ lệ nội dung riêng thấp nhất | G2: Kết luận | H2: Bằng chứng
A3: Hub kế thừa từ khóa danh mục (báo cáo seo-master-audit) | B3: hướng dẫn dùng ứng dụng thuê xe máy | C3: 8 | D3: https://chatbot.thuexemaynguyentu.com/blog/app/ | https://chatbot.thuexemaynguyentu.com/blog/app/dat-xe/ | https://chatbot.thuexemaynguyentu.com/blog/app/huong-dan/ | https://chatbot.thuexemaynguyentu.com/blog/app/so-sanh/ | https://chatbot.thuexemaynguyentu.com/blog/app/tim-xe/ | https://chatbot.thuexemaynguyentu.com/blog/app/tinh-gia/ | https://chatbot.thuexemaynguyentu.com/blog/app/tro-ly/ | https://chatbot.thuexemaynguyentu.com/blog/app/web-app/ | E3: N/A | F3: N/A | G3: WATCH | H3: 8 hub (title/H1 khác nhau) + 16 trang phân trang dùng chung từ khóa danh mục trong báo cáo; trang phân trang tự canonical là chuỗi hợp lệ. Việc: gán từ khóa riêng cho hub chủ đề con trong seo-master-audit (P3), không gộp/redirect
A4: Hub kế thừa từ khóa danh mục (báo cáo seo-master-audit) | B4: hướng dẫn thuê xe máy từng bước | C4: 8 | D4: https://chatbot.thuexemaynguyentu.com/blog/huong-dan/ | https://chatbot.thuexemaynguyentu.com/blog/huong-dan/ban-do/ | https://chatbot.thuexemaynguyentu.com/blog/huong-dan/chuan-bi/ | https://chatbot.thuexemaynguyentu.com/blog/huong-dan/dat-xe/ | https://chatbot.thuexemaynguyentu.com/blog/huong-dan/giay-to/ | https://chatbot.thuexemaynguyentu.com/blog/huong-dan/nhan-xe/ | https://chatbot.thuexemaynguyentu.com/blog/huong-dan/thu-tuc/ | https://chatbot.thuexemaynguyentu.com/blog/huong-dan/tra-xe/ | E4: N/A | F4: N/A | G4: WATCH | H4: 8 hub (title/H1 khác nhau) + 14 trang phân trang dùng chung từ khóa danh mục trong báo cáo; trang phân trang tự canonical là chuỗi hợp lệ. Việc: gán từ khóa riêng cho hub chủ đề con trong seo-master-audit (P3), không gộp/redirect
A5: Hub kế thừa từ khóa danh mục (báo cáo seo-master-audit) | B5: kinh nghiệm thuê xe máy | C5: 10 | D5: https://chatbot.thuexemaynguyentu.com/blog/thue-xe/ | https://chatbot.thuexemaynguyentu.com/blog/thue-xe/chon-xe/ | https://chatbot.thuexemaynguyentu.com/blog/thue-xe/dat-coc/ | https://chatbot.thuexemaynguyentu.com/blog/thue-xe/du-khach/ | https://chatbot.thuexemaynguyentu.com/blog/thue-xe/gia-thue/ | https://chatbot.thuexemaynguyentu.com/blog/thue-xe/nhan-xe/ | https://chatbot.thuexemaynguyentu.com/blog/thue-xe/thu-tuc/ | https://chatbot.thuexemaynguyentu.com/blog/thue-xe/thue-thang/ | https://chatbot.thuexemaynguyentu.com/blog/thue-xe/thue-tuan/ | https://chatbot.thuexemaynguyentu.com/blog/thue-xe/tra-xe/ | E5: N/A | F5: N/A | G5: WATCH | H5: 10 hub (title/H1 khác nhau) + 22 trang phân trang dùng chung từ khóa danh mục trong báo cáo; trang phân trang tự canonical là chuỗi hợp lệ. Việc: gán từ khóa riêng cho hub chủ đề con trong seo-master-audit (P3), không gộp/redirect
A6: Hub kế thừa từ khóa danh mục (báo cáo seo-master-audit) | B6: luật giao thông và an toàn khi thuê xe máy | C6: 8 | D6: https://chatbot.thuexemaynguyentu.com/blog/an-toan/ | https://chatbot.thuexemaynguyentu.com/blog/an-toan/bang-lai/ | https://chatbot.thuexemaynguyentu.com/blog/an-toan/du-lich/ | https://chatbot.thuexemaynguyentu.com/blog/an-toan/lai-xe/ | https://chatbot.thuexemaynguyentu.com/blog/an-toan/mu-bao-hiem/ | https://chatbot.thuexemaynguyentu.com/blog/an-toan/phap-luat/ | https://chatbot.thuexemaynguyentu.com/blog/an-toan/su-co/ | https://chatbot.thuexemaynguyentu.com/blog/an-toan/thoi-tiet/ | E6: N/A | F6: N/A | G6: WATCH | H6: 8 hub (title/H1 khác nhau) + 14 trang phân trang dùng chung từ khóa danh mục trong báo cáo; trang phân trang tự canonical là chuỗi hợp lệ. Việc: gán từ khóa riêng cho hub chủ đề con trong seo-master-audit (P3), không gộp/redirect
A7: Hub kế thừa từ khóa danh mục (báo cáo seo-master-audit) | B7: thuê xe máy điện hà nội | C7: 10 | D7: https://chatbot.thuexemaynguyentu.com/blog/xe-dien/ | https://chatbot.thuexemaynguyentu.com/blog/xe-dien/an-toan/ | https://chatbot.thuexemaynguyentu.com/blog/xe-dien/chi-phi/ | https://chatbot.thuexemaynguyentu.com/blog/xe-dien/chon-xe/ | https://chatbot.thuexemaynguyentu.com/blog/xe-dien/pin-xe/ | https://chatbot.thuexemaynguyentu.com/blog/xe-dien/quang-duong/ | https://chatbot.thuexemaynguyentu.com/blog/xe-dien/sac-pin/ | https://chatbot.thuexemaynguyentu.com/blog/xe-dien/so-sanh/ | https://chatbot.thuexemaynguyentu.com/blog/xe-dien/thue-ngay/ | https://chatbot.thuexemaynguyentu.com/blog/xe-dien/thue-thang/ | E7: N/A | F7: N/A | G7: WATCH | H7: 10 hub (title/H1 khác nhau) + 14 trang phân trang dùng chung từ khóa danh mục trong báo cáo; trang phân trang tự canonical là chuỗi hợp lệ. Việc: gán từ khóa riêng cho hub chủ đề con trong seo-master-audit (P3), không gộp/redirect
A8: Hub kế thừa từ khóa danh mục (báo cáo seo-master-audit) | B8: đi xe máy ở hà nội | C8: 4 | D8: https://chatbot.thuexemaynguyentu.com/blog/dia-phuong/ | https://chatbot.thuexemaynguyentu.com/blog/dia-phuong/diem-tham-quan/ | https://chatbot.thuexemaynguyentu.com/blog/dia-phuong/ha-noi/ | https://chatbot.thuexemaynguyentu.com/blog/dia-phuong/phuong-xa/ | E8: N/A | F8: N/A | G8: WATCH | H8: 4 hub (title/H1 khác nhau) + 22 trang phân trang dùng chung từ khóa danh mục trong báo cáo; trang phân trang tự canonical là chuỗi hợp lệ. Việc: gán từ khóa riêng cho hub chủ đề con trong seo-master-audit (P3), không gộp/redirect
A9: Hai URL của site cùng xuất hiện trên một SERP | B9: app thuê xe máy | C9: 2 | D9: https://chatbot.thuexemaynguyentu.com/blog/app/app-thue-xe-khong-can-tai-khoan/ | https://chatbot.thuexemaynguyentu.com/blog/app/cach-dung-ung-dung-thue-xe-may/ | E9: N/A | F9: N/A | G9: WATCH | H9: Cùng xếp hạng (không hoán đổi) trong ảnh chụp — theo dõi trong GSC khi có dữ liệu
A10: Hai URL của site cùng xuất hiện trên một SERP | B10: xe thuê bị hỏng phải làm sao | C10: 2 | D10: https://chatbot.thuexemaynguyentu.com/blog/thue-xe/ho-tro-khi-xe-thue-gap-su-co-gia-tot-nhat/ | https://chatbot.thuexemaynguyentu.com/blog/thue-xe/hong-xe-giua-duong-khi-thue/index.html | E10: N/A | F10: N/A | G10: WATCH | H10: Cùng xếp hạng (không hoán đổi) trong ảnh chụp — theo dõi trong GSC khi có dữ liệu
A11: Họ biến thể slug (cùng chủ đề + bổ ngữ) | B11: agent-chon-xe-giup-ban | C11: 6 | D11: https://chatbot.thuexemaynguyentu.com/blog/app/agent-chon-xe-giup-ban/ (+5 biến thể) | E11: 0.01 | F11: 0.946 | G11: OK | H11: Jaccard 5-gram cao nhất 0.010 (với agent-chon-xe-giup-ban-nam-2026); trung vị 0.004; tỉ lệ nội dung riêng thấp nhất 95%. Ngưỡng gộp ≥ 0,5; theo dõi ≥ 0,3.
A12: Họ biến thể slug (cùng chủ đề + bổ ngữ) | B12: ai-chiu-phat-khi-di-xe-thue | C12: 5 | D12: https://chatbot.thuexemaynguyentu.com/blog/an-toan/ai-chiu-phat-khi-di-xe-thue/ (+4 biến thể) | E12: 0.039 | F12: 0.815 | G12: OK | H12: Jaccard 5-gram cao nhất 0.039 (với ai-chiu-phat-khi-di-xe-thue-cho-du-khach); trung vị 0.020; tỉ lệ nội dung riêng thấp nhất 81%. Ngưỡng gộp ≥ 0,5; theo dõi ≥ 0,3.
A13: Họ biến thể slug (cùng chủ đề + bổ ngữ) | B13: ai-tra-loi-trong-ung-dung-thue-xe | C13: 6 | D13: https://chatbot.thuexemaynguyentu.com/blog/app/ai-tra-loi-trong-ung-dung-thue-xe/ (+5 biến thể) | E13: 0.038 | F13: 0.898 | G13: OK | H13: Jaccard 5-gram cao nhất 0.038 (với ai-tra-loi-trong-ung-dung-thue-xe-nam-2026); trung vị 0.008; tỉ lệ nội dung riêng thấp nhất 90%. Ngưỡng gộp ≥ 0,5; theo dõi ≥ 0,3.
A14: Họ biến thể slug (cùng chủ đề + bổ ngữ) | B14: an-toan-khi-thanh-toan-coc | C14: 5 | D14: https://chatbot.thuexemaynguyentu.com/blog/an-toan/an-toan-khi-thanh-toan-coc/ (+4 biến thể) | E14: 0.083 | F14: 0.808 | G14: OK | H14: Jaccard 5-gram cao nhất 0.083 (với an-toan-khi-thanh-toan-coc-cho-du-khach); trung vị 0.024; tỉ lệ nội dung riêng thấp nhất 81%. Ngưỡng gộp ≥ 0,5; theo dõi ≥ 0,3.
A15: Họ biến thể slug (cùng chủ đề + bổ ngữ) | B15: an-uong-va-lai-xe-an-toan | C15: 6 | D15: https://chatbot.thuexemaynguyentu.com/blog/huong-dan/an-uong-va-lai-xe-an-toan/ (+5 biến thể) | E15: 0.011 | F15: 0.936 | G15: OK | H15: Jaccard 5-gram cao nhất 0.011 (với an-uong-va-lai-xe-an-toan-nhanh-gon); trung vị 0.004; tỉ lệ nội dung riêng thấp nhất 94%. Ngưỡng gộp ≥ 0,5; theo dõi ≥ 0,3.
A16: Họ biến thể slug (cùng chủ đề + bổ ngữ) | B16: ao-mua-khi-thue-xe-may | C16: 6 | D16: https://chatbot.thuexemaynguyentu.com/blog/thue-xe/ao-mua-khi-thue-xe-may/ (+5 biến thể) | E16: 0.011 | F16: 0.949 | G16: OK | H16: Jaccard 5-gram cao nhất 0.011 (với ao-mua-khi-thue-xe-may-ky-nghi-le); trung vị 0.003; tỉ lệ nội dung riêng thấp nhất 95%. Ngưỡng gộp ≥ 0,5; theo dõi ≥ 0,3.
A17: Họ biến thể slug (cùng chủ đề + bổ ngữ) | B17: app-ho-tro-thu-tuc-thue-xe | C17: 6 | D17: https://chatbot.thuexemaynguyentu.com/blog/app/app-ho-tro-thu-tuc-thue-xe/ (+5 biến thể) | E17: 0.01 | F17: 0.876 | G17: OK | H17: Jaccard 5-gram cao nhất 0.010 (với app-ho-tro-thu-tuc-thue-xe-cho-khach-nuoc-ngoai); trung vị 0.010; tỉ lệ nội dung riêng thấp nhất 88%. Ngưỡng gộp ≥ 0,5; theo dõi ≥ 0,3.
A18: Họ biến thể slug (cùng chủ đề + bổ ngữ) | B18: app-mo-khoa-xe-dien | C18: 5 | D18: https://chatbot.thuexemaynguyentu.com/blog/xe-dien/app-mo-khoa-xe-dien/ (+4 biến thể) | E18: 0.018 | F18: 0.939 | G18: OK | H18: Jaccard 5-gram cao nhất 0.018 (với app-mo-khoa-xe-dien-cho-khach-du-lich); trung vị 0.004; tỉ lệ nội dung riêng thấp nhất 94%. Ngưỡng gộp ≥ 0,5; theo dõi ≥ 0,3.
A19: Họ biến thể slug (cùng chủ đề + bổ ngữ) | B19: app-theo-doi-pin-xe-dien | C19: 6 | D19: https://chatbot.thuexemaynguyentu.com/blog/xe-dien/app-theo-doi-pin-xe-dien/ (+5 biến thể) | E19: 0.005 | F19: 0.881 | G19: OK | H19: Jaccard 5-gram cao nhất 0.005 (với app-theo-doi-pin-xe-dien-dai-han); trung vị 0.004; tỉ lệ nội dung riêng thấp nhất 88%. Ngưỡng gộp ≥ 0,5; theo dõi ≥ 0,3.
A20: Họ biến thể slug (cùng chủ đề + bổ ngữ) | B20: app-thue-xe-cho-khach-du-lich | C20: 6 | D20: https://chatbot.thuexemaynguyentu.com/blog/app/app-thue-xe-cho-khach-du-lich/ (+5 biến thể) | E20: 0.008 | F20: 0.896 | G20: OK | H20: Jaccard 5-gram cao nhất 0.008 (với app-thue-xe-cho-khach-du-lich-tai-ha-noi); trung vị 0.007; tỉ lệ nội dung riêng thấp nhất 90%. Ngưỡng gộp ≥ 0,5; theo dõi ≥ 0,3.
A21: Họ biến thể slug (cùng chủ đề + bổ ngữ) | B21: app-thue-xe-cho-nguoi-nuoc-ngoai | C21: 6 | D21: https://chatbot.thuexemaynguyentu.com/blog/app/app-thue-xe-cho-nguoi-nuoc-ngoai/ (+5 biến thể) | E21: 0.056 | F21: 0.868 | G21: OK | H21: Jaccard 5-gram cao nhất 0.056 (với app-thue-xe-cho-nguoi-nuoc-ngoai-nam-2026); trung vị 0.006; tỉ lệ nội dung riêng thấp nhất 87%. Ngưỡng gộp ≥ 0,5; theo dõi ≥ 0,3.
A22: Họ biến thể slug (cùng chủ đề + bổ ngữ) | B22: app-thue-xe-dien | C22: 6 | D22: https://chatbot.thuexemaynguyentu.com/blog/xe-dien/app-thue-xe-dien/ (+5 biến thể) | E22: 0.009 | F22: 0.941 | G22: OK | H22: Jaccard 5-gram cao nhất 0.009 (với app-thue-xe-dien-mua-mua); trung vị 0.004; tỉ lệ nội dung riêng thấp nhất 94%. Ngưỡng gộp ≥ 0,5; theo dõi ≥ 0,3.
... A341: Họ biến thể slug (cùng chủ đề + bổ ngữ) | B341: xu-ly-du-lieu-ca-nhan-khi-thue-xe-online | C341: 6 | D341: https://chatbot.thuexemaynguyentu.com/blog/app/xu-ly-du-lieu-ca-nhan-khi-thue-xe-online/ (+5 biến thể) | E341: 0.027 | F341: 0.888 | G341: OK | H341: Jaccard 5-gram cao nhất 0.027 (với xu-ly-du-lieu-ca-nhan-khi-thue-xe-online-nam-2026); trung vị 0.014; tỉ lệ nội dung riêng thấp nhất 89%. Ngưỡng gộp ≥ 0,5; theo dõi ≥ 0,3.

Sheet HOMEPAGE & PILLAR
A1: URL | B1: Loại trang | C1: Vai trò pillar (cụm) | D1: Từ khóa chính | E1: Title | F1: Title (ký tự) | G1: Meta (ký tự) | H1: H1 | I1: Từ nội dung chính | J1: H2 | K1: Schema | L1: CTA | M1: Liên kết vào từ nội dung (trang) | N1: QA proxy | O1: Vấn đề | P1: Phân loại | Q1: Lý do
A2: https://chatbot.thuexemaynguyentu.com/ | B2: Trang chủ (website) | C2: CORE: cho thuê xe máy ở Hà Nội (P0) | K01: Ứng dụng & Agent thuê xe máy (volume nhóm 2710) | D2: cho thuê xe máy ở Hà Nội | E2: Cho thuê xe máy ở Hà Nội: xe số, xe ga, xe điện | MotoAI | F2: 56 | G2: 158 | H2: Cho thuê xe máy ở Hà Nội | I2: 1451 | J2: 6 | K2: ImageObject, Organization, WebPage, WebSite | L2: agent, giá, liên hệ | M2: 2168 | N2: 97 | O2: Không | P2: KEEP | Q2: QA proxy ≥ 85, không cờ mở, không cảnh báo nội dung
A3: https://chatbot.thuexemaynguyentu.com/gia-thue/ | B3: Trang chuyển đổi (giá) | C3: PRICE: giá thuê xe máy Hà Nội (P0) | K02: Giá thuê xe máy (volume nhóm 42160) | D3: giá thuê xe máy Hà Nội | E3: Giá thuê xe máy Hà Nội theo ngày, tuần, tháng | Bảng giá | F3: 56 | G3: 150 | H3: Bảng giá thuê xe máy Hà Nội | I3: 877 | J3: 4 | K3: Offer, OfferCatalog, Service, UnitPriceSpecification, WebPage, WebSite | L3: agent, liên hệ | M3: 1424 | N3: 97 | O3: Không | P3: KEEP | Q3: QA proxy ≥ 85, không cờ mở, không cảnh báo nội dung
A4: https://chatbot.thuexemaynguyentu.com/lien-he/ | B4: Trang chuyển đổi (liên hệ) | C4: CONTACT: thuê xe máy gần đây (P0) | DELIVERY: giao xe máy thuê tại Hà Nội (P1) | K15: Long Biên – Gia Lâm – Bát Tràng (khu vực cửa hàng) (volume nhóm 10) | D4: địa chỉ thuê xe máy Nguyễn Tú | E4: Địa chỉ thuê xe máy Nguyễn Tú, Long Biên — điện thoại, bản đồ | F4: 61 | G4: 136 | H4: Liên hệ | I4: 339 | J4: 8 | K4: AutoRental, OpeningHoursSpecification, PostalAddress, WebPage, WebSite | L4: agent, giá, liên hệ | M4: 2169 | N4: 93 | O4: Không | P4: KEEP | Q4: QA proxy ≥ 85, không cờ mở, không cảnh báo nội dung
A5: https://chatbot.thuexemaynguyentu.com/agent/ | B5: Ứng dụng Agent (chat) | C5: AGENT: trợ lý thuê xe máy Hà Nội (P1) | D5: ứng dụng thuê xe máy | E5: Hỏi Agent MotoAI — Ứng dụng thuê xe máy & xe điện: hỏi giá | F5: 58 | G5: 162 | H5: Hỗ trợ Agent | I5: 330 | J5: 0 | K5: Answer, FAQPage, Offer, Organization, PostalAddress, Question, WebApplication | L5: giá, liên hệ | M5: 2168 | N5: 87 | O5: Không | P5: KEEP | Q5: QA proxy ≥ 85, không cờ mở, không cảnh báo nội dung
A6: https://chatbot.thuexemaynguyentu.com/blog/ | B6: Blog home | C6: Trang chính | D6: cẩm nang thuê xe máy | E6: Cẩm nang thuê xe máy — ứng dụng, giá, xe điện, thủ tục | F6: 54 | G6: 141 | H6: Thuê xe máy & xe điện | I6: 2345 | J6: 41 | K6: BreadcrumbList, CollectionPage, ItemList, ListItem, WebSite | L6: agent, liên hệ | M6: 2161 | N6: 98 | O6: Không | P6: KEEP | Q6: QA proxy ≥ 85, không cờ mở, không cảnh báo nội dung
A7: https://chatbot.thuexemaynguyentu.com/gioi-thieu/ | B7: Trang giới thiệu (E-E-A-T) | C7: Trang chính | D7: giới thiệu thuê xe máy Nguyễn Tú | E7: Giới thiệu MotoAI — trợ lý thuê xe máy của Nguyễn Tú | F7: 52 | G7: 138 | H7: Giới thiệu | I7: 647 | J7: 6 | K7: WebPage, WebSite | L7: agent, giá, liên hệ | M7: 2007 | N7: 92 | O7: Không | P7: KEEP | Q7: QA proxy ≥ 85, không cờ mở, không cảnh báo nội dung
A8: https://chatbot.thuexemaynguyentu.com/chinh-sach/ | B8: Trang chính sách thuê xe | C8: K06: Giao xe tận nơi, tận khách sạn (volume nhóm 10) | D8: chính sách thuê xe máy | E8: Chính sách thuê xe máy: đặt cọc, giấy tờ, giao nhận xe | F8: 54 | G8: 160 | H8: Chính sách dịch vụ & thuê xe | I8: 243 | J8: 5 | K8: WebPage, WebSite | L8: agent, liên hệ | M8: 606 | N8: 91 | O8: Không | P8: KEEP | Q8: QA proxy ≥ 85, không cờ mở, không cảnh báo nội dung
A9: https://chatbot.thuexemaynguyentu.com/doi-tac/ | B9: Trang đối tác (B2B) | C9: Trang chính | D9: thuê xe máy theo đoàn | E9: Thuê xe máy theo đoàn cho công ty du lịch, khách sạn — Nguyễn Tú | F9: 64 | G9: 164 | H9: Đối tác | I9: 538 | J9: 5 | K9: WebPage, WebSite | L9: agent, giá, liên hệ | M9: 3 | N9: 93 | O9: Không | P9: KEEP | Q9: QA proxy ≥ 85, không cờ mở, không cảnh báo nội dung
A10: https://chatbot.thuexemaynguyentu.com/blog/thue-xe/ | B10: Hub danh mục | C10: MONTH: thuê xe máy tháng Hà Nội (P0) | DAY: thuê xe máy theo ngày Hà Nội (P1) | WEEK: thuê xe máy theo tuần Hà Nội (P1) | VISION: thuê xe Honda Vision Hà Nội (P1) | WAVE: thuê xe Honda Wave Hà Nội (P1) | AIRBLADE: thuê Honda Air Blade Hà Nội (P1) | 50CC: thuê xe máy 50cc Hà Nội (P1) | K03: Thuê theo ngày, tuần, tháng, dài hạn (volume nhóm 80) | K07: Chọn loại xe: xe số, xe ga, 50cc (volume nhóm 60) | K19: Kinh nghiệm thuê xe cho khách du lịch (volume nhóm 30) | D10: kinh nghiệm thuê xe máy | E10: Kinh nghiệm thuê xe máy: giá theo ngày, tuần, tháng và thủ tục | F10: 62 | G10: 136 | H10: Thuê xe máy | I10: 2275 | J10: 25 | K10: BreadcrumbList, CollectionPage, ItemList, ListItem, WebSite | L10: agent, giá, liên hệ | M10: 805 | N10: 98 | O10: Không | P10: KEEP | Q10: QA proxy ≥ 85, không cờ mở, không cảnh báo nội dung
A11: https://chatbot.thuexemaynguyentu.com/blog/xe-dien/ | B11: Hub danh mục | C11: EV: thuê xe máy điện Hà Nội (P0) | EBIKE: thuê xe đạp điện Hà Nội (P1) | K08: Xe máy điện và xe đạp điện (volume nhóm 590) | D11: thuê xe máy điện hà nội | E11: Thuê xe máy điện Hà Nội: pin, sạc, chi phí và cách chọn xe | F11: 58 | G11: 144 | H11: Xe điện / xe máy điện | I11: 2130 | J11: 25 | K11: BreadcrumbList, CollectionPage, ItemList, ListItem, WebSite | L11: agent, giá, liên hệ | M11: 803 | N11: 94 | O11: Không | P11: KEEP | Q11: QA proxy ≥ 85, không cờ mở, không cảnh báo nội dung
A12: https://chatbot.thuexemaynguyentu.com/blog/dia-phuong/ | B12: Hub danh mục | C12: LONGBIEN: thuê xe máy Long Biên (P0) | HOANKIEM: thuê xe máy Hoàn Kiếm (P1) | TAYHO: thuê xe máy Tây Hồ (P1) | BADINH: thuê xe máy Ba Đình (P1) | GIALAM: thuê xe máy Gia Lâm (P1) | K13: Ba Đình – Lăng Bác – Hoàng thành (volume nhóm 10) | K16: Cầu Giấy – Đống Đa – Thanh Xuân – Hai Bà Trưng (volume nhóm 110) | K18: Hành trình xa, xuyên Việt (volume nhóm 150) | D12: đi xe máy ở hà nội | E12: Đi xe máy ở Hà Nội: Phố Cổ, Hồ Tây, Ba Đình và ngoại thành | F12: 58 | G12: 137 | H12: Địa phương / du lịch | I12: 2257 | J12: 25 | K12: BreadcrumbList, CollectionPage, ItemList, ListItem, WebSite | L12: agent, liên hệ | M12: 754 | N12: 96 | O12: Không | P12: KEEP | Q12: QA proxy ≥ 85, không cờ mở, không cảnh báo nội dung
A13: https://chatbot.thuexemaynguyentu.com/blog/huong-dan/ | B13: Hub danh mục | C13: DEPOSIT: đặt cọc thuê xe máy Hà Nội (P1) | DOCUMENT: thủ tục thuê xe máy Hà Nội (P1) | FOREIGN: thuê xe máy cho người nước ngoài Hà Nội (P2) | K20: Bảo dưỡng, sự cố và xử lý khi đi đường (volume nhóm 1020) | D13: hướng dẫn thuê xe máy từng bước | E13: Hướng dẫn thuê xe máy từng bước: giấy tờ, cọc, nhận và trả xe | F13: 61 | G13: 136 | H13: Hướng dẫn / thủ tục | I13: 2176 | J13: 25 | K13: BreadcrumbList, CollectionPage, ItemList, ListItem, WebSite | L13: agent, liên hệ | M13: 751 | N13: 96 | O13: Không | P13: KEEP | Q13: QA proxy ≥ 85, không cờ mở, không cảnh báo nội dung
... A19: https://chatbot.thuexemaynguyentu.com/blog/kham-pha-an-toan/ | B19: Hub cụm chủ đề | C19: K17: Hành trình ngoại thành và tỉnh lân cận (volume nhóm 210) | D19: khám phá hà nội bằng xe máy thuê | E19: Khám phá Hà Nội bằng xe máy thuê: an toàn, luật, cung đường | F19: 59 | G19: 142 | H19: Khám phá & An toàn | I19: 810 | J19: 13 | K19: BreadcrumbList, CollectionPage, ItemList, ListItem, WebSite | L19: agent, liên hệ | M19: 706 | N19: 93 | O19: Không | P19: KEEP | Q19: QA proxy ≥ 85, không cờ mở, không cảnh báo nội dung

Sheet SEO HUB MATRIX
A1: Kiến trúc: Trang chủ → Pillar → Hub → Silo → Bài hỗ trợ. Số bài khớp có thể chồng lấn giữa các nhóm.
A2: Mã | B2: Nhóm hub (lệnh SEO 2026) | C2: URL hiện có | D2: URL dự kiến chưa có | E2: Số bài khớp chủ đề | F2: Quy tắc khớp (title + từ khóa) | G2: Liên kết vào từ nội dung (trang, không tính menu) | H2: Trạng thái | I2: Hành động
A3: H01 | B3: Cho thuê xe máy Hà Nội | C3: https://chatbot.thuexemaynguyentu.com/ | https://chatbot.thuexemaynguyentu.com/blog/thue-xe/ | https://chatbot.thuexemaynguyentu.com/blog/thue-xe-phuong-tien/ | D3: Không | E3: 39 | F3: cho thuê xe máy, thuê xe máy hà nội, thuê xe máy ở hà nội, thuê xe máy tại hà nội | G3: 3732 | H3: CÓ | I3: Giữ; bổ sung đoạn dẫn hub có giá trị (không chỉ danh sách thẻ) theo lô review
A4: H02 | B4: Giá thuê | C4: https://chatbot.thuexemaynguyentu.com/gia-thue/ | https://chatbot.thuexemaynguyentu.com/blog/thue-xe/gia-thue/ | D4: Không | E4: 83 | F4: giá thuê, bảng giá, chi phí thuê, giá rẻ | G4: 1549 | H4: CÓ | I4: Giữ; bổ sung đoạn dẫn hub có giá trị (không chỉ danh sách thẻ) theo lô review
A5: H03 | B5: Theo ngày / tuần / tháng | C5: https://chatbot.thuexemaynguyentu.com/blog/thue-xe/thue-tuan/ | https://chatbot.thuexemaynguyentu.com/blog/thue-xe/thue-thang/ | https://chatbot.thuexemaynguyentu.com/blog/xe-dien/thue-ngay/ | D5: Không | E5: 138 | F5: theo ngày, theo tuần, theo tháng, thuê ngày, thuê tuần, thuê tháng, dài hạn, trong ngày | G5: 97 | H5: CÓ | I5: Giữ; bổ sung đoạn dẫn hub có giá trị (không chỉ danh sách thẻ) theo lô review
A6: H04 | B6: Theo khu vực | C6: https://chatbot.thuexemaynguyentu.com/blog/dia-phuong/ | https://chatbot.thuexemaynguyentu.com/blog/dia-phuong/phuong-xa/ | D6: Không | E6: 119 | F6: long biên, hoàn kiếm, ba đình, tây hồ, gia lâm, phố cổ, cầu giấy, đống đa, hai bà trưng, thanh xuân | G6: 867 | H6: CÓ | I6: Giữ; bổ sung đoạn dẫn hub có giá trị (không chỉ danh sách thẻ) theo lô review; KHÔNG tạo trang theo từng phường/quận chỉ đổi tên (doorway) — chỉ khu vực có dịch vụ thật trong business.json
A7: H05 | B7: Các dòng xe | C7: https://chatbot.thuexemaynguyentu.com/blog/thue-xe/chon-xe/ | https://chatbot.thuexemaynguyentu.com/blog/xe-dien/chon-xe/ | D7: Không | E7: 71 | F7: xe số, xe ga, tay ga, wave, vision, air blade, lead, vario, future, sirius, dòng xe, loại xe | G7: 103 | H7: CÓ | I7: Giữ; bổ sung đoạn dẫn hub có giá trị (không chỉ danh sách thẻ) theo lô review
A8: H06 | B8: Xe 50cc | C8: Không | D8: Không | E8: 7 | F8: 50cc | G8: 0 | H8: GAP | I8: Chưa có hub riêng; chỉ tạo khi đủ bài thật sự khác nhau (quy tắc không tạo hub rỗng) — hiện gom trong /blog/thue-xe/ và /gia-thue/
A9: H07 | B9: Xe máy điện & xe đạp điện | C9: https://chatbot.thuexemaynguyentu.com/blog/xe-dien/ | https://chatbot.thuexemaynguyentu.com/blog/xe-dien/chon-xe/ | https://chatbot.thuexemaynguyentu.com/blog/xe-dien/chi-phi/ | D9: Không | E9: 321 | F9: xe máy điện, xe điện, xe đạp điện | G9: 883 | H9: CÓ | I9: Giữ; bổ sung đoạn dẫn hub có giá trị (không chỉ danh sách thẻ) theo lô review
A10: H08 | B10: Thủ tục & kinh nghiệm | C10: https://chatbot.thuexemaynguyentu.com/blog/huong-dan/ | https://chatbot.thuexemaynguyentu.com/blog/huong-dan/thu-tuc/ | https://chatbot.thuexemaynguyentu.com/blog/thue-xe/dat-coc/ | https://chatbot.thuexemaynguyentu.com/blog/thue-xe/nhan-xe/ | https://chatbot.thuexemaynguyentu.com/blog/thue-xe/tra-xe/ | D10: Không | E10: 177 | F10: thủ tục, kinh nghiệm, giấy tờ, đặt cọc, hợp đồng, nhận xe, trả xe | G10: 901 | H10: CÓ | I10: Giữ; bổ sung đoạn dẫn hub có giá trị (không chỉ danh sách thẻ) theo lô review
A11: H09 | B11: Luật giao thông & giấy phép | C11: https://chatbot.thuexemaynguyentu.com/blog/an-toan/phap-luat/ | D11: Không | E11: 76 | F11: luật, nghị định, bằng lái, giấy phép, phạt, biển báo, đăng ký xe | G11: 77 | H11: CÓ | I11: Giữ; bổ sung đoạn dẫn hub có giá trị (không chỉ danh sách thẻ) theo lô review
A12: H10 | B12: Bảo dưỡng & an toàn | C12: https://chatbot.thuexemaynguyentu.com/blog/an-toan/ | https://chatbot.thuexemaynguyentu.com/blog/an-toan/lai-xe/ | https://chatbot.thuexemaynguyentu.com/blog/an-toan/mu-bao-hiem/ | https://chatbot.thuexemaynguyentu.com/blog/an-toan/su-co/ | https://chatbot.thuexemaynguyentu.com/blog/an-toan/thoi-tiet/ | D12: Không | E12: 116 | F12: bảo dưỡng, an toàn, mũ bảo hiểm, sự cố, hỏng xe, thủng, phanh, lốp | G12: 903 | H12: CÓ | I12: Giữ; bổ sung đoạn dẫn hub có giá trị (không chỉ danh sách thẻ) theo lô review
A13: H11 | B13: Du lịch Hà Nội bằng xe máy | C13: https://chatbot.thuexemaynguyentu.com/blog/dia-phuong/ | https://chatbot.thuexemaynguyentu.com/blog/kham-pha-an-toan/ | https://chatbot.thuexemaynguyentu.com/blog/thue-xe/du-khach/ | D13: Không | E13: 144 | F13: du lịch, phượt, tham quan, cung đường, hành trình, điểm đến | G13: 1486 | H13: CÓ | I13: Giữ; bổ sung đoạn dẫn hub có giá trị (không chỉ danh sách thẻ) theo lô review
A14: H12 | B14: Giao thông xanh | C14: https://chatbot.thuexemaynguyentu.com/blog/xe-dien/ | D14: Không | E14: 1 | F14: phát thải, vành đai 1, giao thông xanh, năng lượng sạch, khí thải | G14: 803 | H14: CÓ | I14: Giữ; bổ sung đoạn dẫn hub có giá trị (không chỉ danh sách thẻ) theo lô review

Sheet SILO & CATEGORY MATRIX
A1: URL | B1: Cấp | C1: Danh mục | D1: Title | E1: Từ (nội dung chính) | F1: H2 | G1: Liên kết nội dung (thẻ) | H1: Trang liên kết vào | I1: Độ sâu click | J1: Schema | K1: QA proxy | L1: Phân loại
A2: https://chatbot.thuexemaynguyentu.com/blog/ | B2: Blog home | C2: N/A | D2: Cẩm nang thuê xe máy — ứng dụng, giá, xe điện, thủ tục | E2: 2345 | F2: 41 | G2: 36 | H2: 2169 | I2: 1 | J2: BreadcrumbList, CollectionPage, ItemList, ListItem, WebSite | K2: 98 | L2: KEEP
A3: https://chatbot.thuexemaynguyentu.com/blog/an-toan/ | B3: Hub danh mục | C3: N/A | D3: Luật giao thông và an toàn khi thuê xe máy: bằng lái, mũ, phạt | E3: 2134 | F3: 25 | G3: 80 | H3: 2169 | I3: 1 | J3: BreadcrumbList, CollectionPage, ItemList, ListItem, WebSite | K3: 96 | L3: KEEP
A4: https://chatbot.thuexemaynguyentu.com/blog/app/ | B4: Hub danh mục | C4: N/A | D4: Hướng dẫn dùng ứng dụng thuê xe máy: hỏi giá, chọn xe, đặt xe | E4: 2295 | F4: 25 | G4: 93 | H4: 2169 | I4: 1 | J4: BreadcrumbList, CollectionPage, ItemList, ListItem, WebSite | K4: 98 | L4: KEEP
A5: https://chatbot.thuexemaynguyentu.com/blog/cong-cu-huong-dan/ | B5: Hub cụm chủ đề | C5: N/A | D5: Công cụ và hướng dẫn thuê xe máy: ứng dụng, thủ tục, đặt cọc | E5: 822 | F5: 13 | G5: 13 | H5: 2169 | I5: 1 | J5: BreadcrumbList, CollectionPage, ItemList, ListItem, WebSite | K5: 93 | L5: KEEP
A6: https://chatbot.thuexemaynguyentu.com/blog/dia-phuong/ | B6: Hub danh mục | C6: N/A | D6: Đi xe máy ở Hà Nội: Phố Cổ, Hồ Tây, Ba Đình và ngoại thành | E6: 2257 | F6: 25 | G6: 88 | H6: 2169 | I6: 1 | J6: BreadcrumbList, CollectionPage, ItemList, ListItem, WebSite | K6: 96 | L6: KEEP
A7: https://chatbot.thuexemaynguyentu.com/blog/huong-dan/ | B7: Hub danh mục | C7: N/A | D7: Hướng dẫn thuê xe máy từng bước: giấy tờ, cọc, nhận và trả xe | E7: 2176 | F7: 25 | G7: 84 | H7: 2169 | I7: 1 | J7: BreadcrumbList, CollectionPage, ItemList, ListItem, WebSite | K7: 96 | L7: KEEP
A8: https://chatbot.thuexemaynguyentu.com/blog/kham-pha-an-toan/ | B8: Hub cụm chủ đề | C8: N/A | D8: Khám phá Hà Nội bằng xe máy thuê: an toàn, luật, cung đường | E8: 810 | F8: 13 | G8: 13 | H8: 2169 | I8: 1 | J8: BreadcrumbList, CollectionPage, ItemList, ListItem, WebSite | K8: 93 | L8: KEEP
A9: https://chatbot.thuexemaynguyentu.com/blog/thue-xe-phuong-tien/ | B9: Hub cụm chủ đề | C9: N/A | D9: Thuê xe máy và xe máy điện: bảng giá, chọn xe, pin và sạc | E9: 812 | F9: 13 | G9: 13 | H9: 2169 | I9: 1 | J9: BreadcrumbList, CollectionPage, ItemList, ListItem, WebSite | K9: 93 | L9: KEEP
A10: https://chatbot.thuexemaynguyentu.com/blog/thue-xe/ | B10: Hub danh mục | C10: N/A | D10: Kinh nghiệm thuê xe máy: giá theo ngày, tuần, tháng và thủ tục | E10: 2275 | F10: 25 | G10: 96 | H10: 2169 | I10: 1 | J10: BreadcrumbList, CollectionPage, ItemList, ListItem, WebSite | K10: 98 | L10: KEEP
A11: https://chatbot.thuexemaynguyentu.com/blog/xe-dien/ | B11: Hub danh mục | C11: N/A | D11: Thuê xe máy điện Hà Nội: pin, sạc, chi phí và cách chọn xe | E11: 2130 | F11: 25 | G11: 83 | H11: 2169 | I11: 1 | J11: BreadcrumbList, CollectionPage, ItemList, ListItem, WebSite | K11: 94 | L11: KEEP
A12: https://chatbot.thuexemaynguyentu.com/blog/an-toan/bang-lai/ | B12: Hub chủ đề con | C12: N/A | D12: Bằng Lái — An toàn / pháp lý — Cẩm nang thuê xe máy | E12: 766 | F12: 13 | G12: 20 | H12: 2169 | I12: 1 | J12: BreadcrumbList, CollectionPage, ItemList, ListItem, WebSite | K12: 87 | L12: KEEP
A13: https://chatbot.thuexemaynguyentu.com/blog/an-toan/du-lich/ | B13: Hub chủ đề con | C13: N/A | D13: Du Lịch — An toàn / pháp lý — Cẩm nang thuê xe máy | E13: 321 | F13: 5 | G13: 12 | H13: 2169 | I13: 1 | J13: BreadcrumbList, CollectionPage, ItemList, ListItem, WebSite | K13: 87 | L13: KEEP
... A155: https://chatbot.thuexemaynguyentu.com/blog/xe-dien/pin-xe/page/2/ | B155: Hub chủ đề con (phân trang) | C155: N/A | D155: Pin Xe — Xe điện / xe máy điện — trang 2 | E155: 1337 | F155: 23 | G155: 31 | H155: 1 | I155: 2 | J155: BreadcrumbList, CollectionPage, ItemList, ListItem, WebSite | K155: 97 | L155: KEEP

Sheet CONTENT CLUSTERS
A1: Nguồn: docs/seo/battle/05-topic-cluster-matrix.csv (W5, tools/seo-battle-matrix.mjs).
A2: Cụm | B2: Tên | C2: Ý định | D2: Từ khóa đầu | E2: Pillar | F2: Pillar tồn tại | G2: Loại pillar | H2: Vào pillar (ngữ cảnh/cụm/hub) | I2: Pillar hỗ trợ | J2: Hub | K2: Bài supporting | L2: Bài 0 inbound | M2: Nhóm từ khóa | N2: Volume nhóm | O2: SERP chụp | P2: Câu hỏi FAQ (PAA) | Q2: Tìm kiếm liên quan | R2: Trộn ý định | S2: Cạnh tranh nội bộ | T2: Việc mở | U2: Trạng thái
A3: K01 | B3: Ứng dụng & Agent thuê xe máy | C3: thông tin sản phẩm / điều hướng | D3: app thuê xe máy; ứng dụng thuê xe máy; ứng dụng cho thuê xe máy; đặt thuê xe máy online | E3: / | F3: có | G3: Trang chủ (website) | H3: 1383/0/51 | I3: /blog/app/app-thue-xe-may-la-gi/ | J3: /blog/app/ /blog/app/cai-app/ /blog/app/dat-xe/ /blog/app/huong-dan/ /blog/app/so-sanh/ /blog/app/tim-xe/ /blog/app/tinh-gia/ /blog/app/tro-ly/ /blog/app/web-app/ | K3: 379 | L3: 0 | M3: 10 | N3: 2710 | O3: 5 | P3: Ứng dụng xe ôm công nghệ nào rẻ nhất hiện nay? | Ứng dụng gọi xe BE của ai? | Giá thuê xe tự lái năm 2026 là bao nhiêu? | Có ứng dụng nào cho thuê xe tự lái không? | Q3: Thuê xe máy điện Honda | Thuê xe máy điện VinFast | Thuê xe máy điện theo tháng | Thuê xe máy điện chạy Grab | Thuê xe máy điện VinFast theo tháng | TNGo xe đạp điện | Thuê xe máy điện TPHCM | Thuê xe máy điện VinFast TPHCM | App thuê xe máy Hà Nội | App thuê xe máy TPHCM | R3: N/A | S3: thuê xe máy điện: BA-0889 | app thuê xe: BA-0001 BA-0931 BA-1117 BA-1291 | app thuê xe điện: BA-1255 | T3: N/A | U3: Ổn
A4: K02 | B4: Giá thuê xe máy | C4: thương mại - thông tin | D4: giá thuê xe máy Hà Nội; thuê xe máy giá rẻ Hà Nội; bảng giá thuê xe máy | E4: /gia-thue/ | F4: có | G4: Trang chuyển đổi (giá) | H4: 736/0/34 | I4: /blog/thue-xe/thue-xe-may-gia-re/ | J4: N/A | K4: 69 | L4: 0 | M4: 5 | N4: 42160 | O4: 3 | P4: N/A | Q4: N/A | R4: N/A | S4: thuê xe máy: BA-0074 BA-0263 BA-0268 | thuê xe máy tự lái: BA-0038 BA-0148 BA-0260 BA-0287 BA-0955 BA-1465 | giá thuê xe máy: BA-0032 BA-0350 BA-1957 | T4: N/A | U4: Ổn
A5: K03 | B5: Thuê theo ngày, tuần, tháng, dài hạn | C5: thương mại - thông tin | D5: thuê xe máy theo ngày Hà Nội; thuê xe máy theo tuần Hà Nội; thuê xe máy tháng Hà Nội; thuê xe máy dài hạn Hà Nội | E5: /blog/thue-xe/ | F5: có | G5: Hub danh mục | H5: 304/0/17 | I5: N/A | J5: N/A | K5: 58 | L5: 0 | M5: 2 | N5: 80 | O5: 3 | P5: N/A | Q5: N/A | R5: N/A | S5: N/A | T5: N/A | U5: Ổn
A6: K04 | B6: Thủ tục, giấy tờ, hợp đồng và đặt cọc | C6: thông tin - chuyển đổi | D6: thủ tục thuê xe máy; giấy tờ cần khi thuê xe máy; đặt cọc thuê xe máy | E6: /blog/huong-dan/thu-tuc-thue-xe-may/ | F6: có | G6: Bài viết | H6: 27/13/7 | I6: N/A | J6: /blog/huong-dan/ /blog/huong-dan/chuan-bi/ /blog/huong-dan/dat-xe/ /blog/huong-dan/thu-tuc/ | K6: 198 | L6: 0 | M6: 29 | N6: 1330 | O6: 4 | P6: N/A | Q6: N/A | R6: N/A | S6: xe máy đi phượt: BA-2006 | hợp đồng thuê xe máy: BA-0020 | T6: N/A | U6: Ổn
A7: K05 | B7: Nhận xe, trả xe và kiểm tra xe | C7: thông tin | D7: kiểm tra xe khi thuê; nhận xe thuê cần gì; trả xe thuê | E7: /blog/huong-dan/kiem-tra-xe-khi-nhan/ | F7: có | G7: Bài viết | H7: 134/13/3 | I7: N/A | J7: N/A | K7: 78 | L7: 0 | M7: 1 | N7: 0 | O7: 1 | P7: N/A | Q7: N/A | R7: N/A | S7: N/A | T7: N/A | U7: Ổn
A8: K06 | B8: Giao xe tận nơi, tận khách sạn | C8: thương mại | D8: cho thuê xe máy giao tận nơi; thuê xe máy giao tận khách sạn | E8: /chinh-sach/ | F8: có | G8: Trang chính sách thuê xe | H8: 4/0/16 | I8: N/A | J8: N/A | K8: 32 | L8: 0 | M8: 1 | N8: 10 | O8: 1 | P8: N/A | Q8: N/A | R8: N/A | S8: N/A | T8: N/A | U8: Ổn
A9: K07 | B9: Chọn loại xe: xe số, xe ga, 50cc | C9: thương mại - so sánh | D9: thuê xe tay ga Hà Nội; thuê xe số Hà Nội; thuê xe máy 50cc Hà Nội; thuê xe Cub 50cc Hà Nội | E9: /blog/thue-xe/ | F9: có | G9: Hub danh mục | H9: 304/0/17 | I9: N/A | J9: N/A | K9: 83 | L9: 0 | M9: 5 | N9: 60 | O9: 3 | P9: N/A | Q9: Thuê xe máy Hà Nội | Thuê xe 50cc | Hanoi Biker | App thuê xe máy Hà Nội | Thuê xe Cub Hà Nội | Thuê xe máy Nguyễn Tú | Thuê xe côn tay Hà Nội | Thuê xe máy điện Hà Nội | Thuê xe máy hà nội 24 7 | Thuê xe máy Hà Nội giá bảo nhiều | R9: N/A | S9: N/A | T9: N/A | U9: Ổn
A10: K08 | B10: Xe máy điện và xe đạp điện | C10: thương mại - thông tin | D10: thuê xe máy điện Hà Nội; thuê xe điện VinFast Hà Nội | E10: /blog/xe-dien/ | F10: có | G10: Hub danh mục | H10: 209/0/17 | I10: N/A | J10: /blog/xe-dien/ /blog/xe-dien/an-toan/ /blog/xe-dien/chi-phi/ /blog/xe-dien/chon-xe/ /blog/xe-dien/pin-xe/ /blog/xe-dien/quang-duong/ /blog/xe-dien/sac-pin/ /blog/xe-dien/so-sanh/ /blog/xe-dien/thue-ngay/ | K10: 221 | L10: 0 | M10: 3 | N10: 590 | O10: 6 | P10: N/A | Q10: Thuê xe máy điện VinFast Hà Nội | Thuê xe máy điện Hà Nội | Thuê xe máy điện theo tháng | Thuê xe máy điện TPHCM | Thuê xe máy điện VinFast TPHCM | Thuê xe máy điện 50cc TPHCM | Thuê xe điện VinFast | Thuê xe máy điện chở hàng | Thuê xe máy điện VinFast | Thuê xe đạp điện Hà Nội | R10: N/A | S10: N/A | T10: N/A | U10: Ổn
A11: K09 | B11: Bằng lái và luật giao thông | C11: thông tin - pháp lý (legal gate) | D11: bằng lái khi thuê xe máy; luật giao thông cho người thuê xe; thuê xe máy không cần bằng lái | E11: /blog/an-toan/ | F11: có | G11: Hub danh mục | H11: 167/0/14 | I11: N/A | J11: N/A | K11: 103 | L11: 0 | M11: 14 | N11: 75550 | O11: 12 | P11: N/A | Q11: N/A | R11: N/A | S11: không bằng lái xe máy phạt bao nhiêu: BA-1809 | T11: N/A | U11: Ổn
A12: K10 | B12: An toàn khi lái xe máy | C12: thông tin | D12: kinh nghiệm lái xe máy an toàn ở Hà Nội; mũ bảo hiểm chuẩn | E12: /blog/an-toan/ | F12: có | G12: Hub danh mục | H12: 167/0/14 | I12: N/A | J12: /blog/an-toan/ /blog/an-toan/lai-xe/ /blog/an-toan/mu-bao-hiem/ /blog/an-toan/phap-luat/ /blog/an-toan/su-co/ /blog/an-toan/thoi-tiet/ | K12: 123 | L12: 0 | M12: 3 | N12: 3470 | O12: 5 | P12: N/A | Q12: N/A | R12: N/A | S12: N/A | T12: N/A | U12: Ổn
A13: K11 | B13: Bảo hiểm, tai nạn, quyền lợi người thuê | C13: thông tin - pháp lý (legal gate) | D13: bảo hiểm khi thuê xe máy; trách nhiệm khi tai nạn xe thuê | E13: /blog/an-toan/ | F13: có | G13: Hub danh mục | H13: 167/0/14 | I13: N/A | J13: N/A | K13: 62 | L13: 0 | M13: 4 | N13: 690 | O13: 2 | P13: N/A | Q13: N/A | R13: N/A | S13: N/A | T13: N/A | U13: Ổn
A14: K12 | B14: Phố cổ – Hoàn Kiếm | C14: địa phương - thông tin | D14: thuê xe máy phố cổ Hà Nội; thuê xe máy Hoàn Kiếm | E14: /blog/dia-phuong/di-pho-co-bang-xe-may/ | F14: có | G14: Bài viết | H14: 49/14/3 | I14: N/A | J14: N/A | K14: 84 | L14: 0 | M14: 5 | N14: 140 | O14: 3 | P14: N/A | Q14: Xe điện đi phố cổ | Xe điện Bờ Hồ | Thuê xe máy Hà Nội | Thuê xe máy gần đây | Thuê xe máy 50cc Hà Nội | Thuê xe Hà Nội | Thuê xe máy theo tháng Hà Nội | Thuê xe phượt Hà Nội | Thuê xe máy điện Hà Nội | Thuê xe máy Tây Hồ | R14: N/A | S14: N/A | T14: N/A | U14: Ổn
... A22: K20 | B22: Bảo dưỡng, sự cố và xử lý khi đi đường | C22: thông tin | D22: xe thuê bị hỏng phải làm sao; đổ xăng xe thuê | E22: /blog/huong-dan/ | F22: có | G22: Hub danh mục | H22: 205/0/12 | I22: N/A | J22: N/A | K22: 39 | L22: 0 | M22: 5 | N22: 1020 | O22: 2 | P22: N/A | Q22: N/A | R22: N/A | S22: N/A | T22: N/A | U22: Ổn

Sheet PAGE & POST OPTIMIZATION
A1: URL | B1: Article ID | C1: Loại trang | D1: Title | E1: Title (ký tự) | F1: Meta (ký tự) | G1: H1 | H1: H2 | I1: Từ (nội dung chính) | J1: Bảng | K1: Danh sách | L1: Miền nguồn ngoài | M1: QA nhà máy | N1: Cảnh báo QA nhà máy | O1: QA proxy | P1: Phân loại | Q1: Lý do | R1: Đề xuất (seo-master-audit)
A2: https://chatbot.thuexemaynguyentu.com/ | B2: N/A | C2: Trang chủ (website) | D2: Cho thuê xe máy ở Hà Nội: xe số, xe ga, xe điện | MotoAI | E2: 56 | F2: 158 | G2: 1 | H2: 6 | I2: 1451 | J2: Không | K2: Có | L2: 0 | M2: N/A | N2: N/A | O2: 97 | P2: KEEP | Q2: QA proxy ≥ 85, không cờ mở, không cảnh báo nội dung | R2: Giữ nguyên; theo dõi Search Console (hiển thị, CTR, truy vấn)
A3: https://chatbot.thuexemaynguyentu.com/agent/ | B3: N/A | C3: Ứng dụng Agent (chat) | D3: Hỏi Agent MotoAI — Ứng dụng thuê xe máy & xe điện: hỏi giá | E3: 58 | F3: 162 | G3: 1 | H3: 0 | I3: 330 | J3: Không | K3: Có | L3: 0 | M3: N/A | N3: N/A | O3: 87 | P3: KEEP | Q3: QA proxy ≥ 85, không cờ mở, không cảnh báo nội dung | R3: Giữ nguyên; theo dõi Search Console (hiển thị, CTR, truy vấn)
A4: https://chatbot.thuexemaynguyentu.com/blog/ | B4: N/A | C4: Blog home | D4: Cẩm nang thuê xe máy — ứng dụng, giá, xe điện, thủ tục | E4: 54 | F4: 141 | G4: 1 | H4: 41 | I4: 2345 | J4: Không | K4: Có | L4: 0 | M4: N/A | N4: N/A | O4: 98 | P4: KEEP | Q4: QA proxy ≥ 85, không cờ mở, không cảnh báo nội dung | R4: Giữ nguyên; theo dõi Search Console (hiển thị, CTR, truy vấn)
A5: https://chatbot.thuexemaynguyentu.com/chinh-sach/ | B5: N/A | C5: Trang chính sách thuê xe | D5: Chính sách thuê xe máy: đặt cọc, giấy tờ, giao nhận xe | E5: 54 | F5: 160 | G5: 1 | H5: 5 | I5: 243 | J5: Không | K5: Không | L5: 0 | M5: N/A | N5: N/A | O5: 91 | P5: KEEP | Q5: QA proxy ≥ 85, không cờ mở, không cảnh báo nội dung | R5: Giữ nguyên; theo dõi Search Console (hiển thị, CTR, truy vấn)
A6: https://chatbot.thuexemaynguyentu.com/doi-tac/ | B6: N/A | C6: Trang đối tác (B2B) | D6: Thuê xe máy theo đoàn cho công ty du lịch, khách sạn — Nguyễn Tú | E6: 64 | F6: 164 | G6: 1 | H6: 5 | I6: 538 | J6: Không | K6: Có | L6: 0 | M6: N/A | N6: N/A | O6: 93 | P6: KEEP | Q6: QA proxy ≥ 85, không cờ mở, không cảnh báo nội dung | R6: Giữ nguyên; theo dõi Search Console (hiển thị, CTR, truy vấn)
A7: https://chatbot.thuexemaynguyentu.com/gia-thue/ | B7: N/A | C7: Trang chuyển đổi (giá) | D7: Giá thuê xe máy Hà Nội theo ngày, tuần, tháng | Bảng giá | E7: 56 | F7: 150 | G7: 1 | H7: 4 | I7: 877 | J7: Có | K7: Có | L7: 0 | M7: N/A | N7: N/A | O7: 97 | P7: KEEP | Q7: QA proxy ≥ 85, không cờ mở, không cảnh báo nội dung | R7: Giữ nguyên; theo dõi Search Console (hiển thị, CTR, truy vấn)
A8: https://chatbot.thuexemaynguyentu.com/gioi-thieu/ | B8: N/A | C8: Trang giới thiệu (E-E-A-T) | D8: Giới thiệu MotoAI — trợ lý thuê xe máy của Nguyễn Tú | E8: 52 | F8: 138 | G8: 1 | H8: 6 | I8: 647 | J8: Không | K8: Có | L8: 1 | M8: N/A | N8: N/A | O8: 92 | P8: KEEP | Q8: QA proxy ≥ 85, không cờ mở, không cảnh báo nội dung | R8: Giữ nguyên; theo dõi Search Console (hiển thị, CTR, truy vấn)
A9: https://chatbot.thuexemaynguyentu.com/lien-he/ | B9: N/A | C9: Trang chuyển đổi (liên hệ) | D9: Địa chỉ thuê xe máy Nguyễn Tú, Long Biên — điện thoại, bản đồ | E9: 61 | F9: 136 | G9: 1 | H9: 8 | I9: 339 | J9: Không | K9: Có | L9: 1 | M9: N/A | N9: N/A | O9: 93 | P9: KEEP | Q9: QA proxy ≥ 85, không cờ mở, không cảnh báo nội dung | R9: Giữ nguyên; theo dõi Search Console (hiển thị, CTR, truy vấn)
A10: https://chatbot.thuexemaynguyentu.com/privacy/ | B10: N/A | C10: Pháp lý | D10: Chính sách bảo mật MotoAI — dữ liệu, Agent và quyền riêng tư | E10: 60 | F10: 143 | G10: 1 | H10: 5 | I10: 377 | J10: Không | K10: Có | L10: 0 | M10: N/A | N10: N/A | O10: 96 | P10: KEEP | Q10: QA proxy ≥ 85, không cờ mở, không cảnh báo nội dung | R10: Giữ nguyên; theo dõi Search Console (hiển thị, CTR, truy vấn)
A11: https://chatbot.thuexemaynguyentu.com/terms/ | B11: N/A | C11: Pháp lý | D11: Điều khoản sử dụng MotoAI — nội dung tham khảo và trách nhiệm | E11: 61 | F11: 145 | G11: 1 | H11: 7 | I11: 373 | J11: Không | K11: Không | L11: 0 | M11: N/A | N11: N/A | O11: 93 | P11: KEEP | Q11: QA proxy ≥ 85, không cờ mở, không cảnh báo nội dung | R11: Giữ nguyên; theo dõi Search Console (hiển thị, CTR, truy vấn)
A12: https://chatbot.thuexemaynguyentu.com/blog/an-toan/ | B12: N/A | C12: Hub danh mục | D12: Luật giao thông và an toàn khi thuê xe máy: bằng lái, mũ, phạt | E12: 62 | F12: 135 | G12: 1 | H12: 25 | I12: 2134 | J12: Không | K12: Có | L12: 0 | M12: N/A | N12: N/A | O12: 96 | P12: KEEP | Q12: QA proxy ≥ 85, không cờ mở, không cảnh báo nội dung | R12: Giữ nguyên; theo dõi Search Console (hiển thị, CTR, truy vấn)
A13: https://chatbot.thuexemaynguyentu.com/blog/app/ | B13: N/A | C13: Hub danh mục | D13: Hướng dẫn dùng ứng dụng thuê xe máy: hỏi giá, chọn xe, đặt xe | E13: 61 | F13: 148 | G13: 1 | H13: 25 | I13: 2295 | J13: Không | K13: Có | L13: 0 | M13: N/A | N13: N/A | O13: 98 | P13: KEEP | Q13: QA proxy ≥ 85, không cờ mở, không cảnh báo nội dung | R13: Giữ nguyên; theo dõi Search Console (hiển thị, CTR, truy vấn)
... A20: https://chatbot.thuexemaynguyentu.com/blog/xe-dien/ | B20: N/A | C20: Hub danh mục | D20: Thuê xe máy điện Hà Nội: pin, sạc, chi phí và cách chọn xe | E20: 58 | F20: 144 | G20: 1 | H20: 25 | I20: 2130 | J20: Không | K20: Có | L20: 0 | M20: N/A | N20: N/A | O20: 94 | P20: KEEP | Q20: QA proxy ≥ 85, không cờ mở, không cảnh báo nội dung | R20: Giữ nguyên; theo dõi Search Console (hiển thị, CTR, truy vấn)
A21: https://chatbot.thuexemaynguyentu.com/blog/an-toan/ai-chiu-phat-khi-di-xe-thue-cho-du-khach/ | B21: BA-0497 | C21: Bài viết | D21: Ai chịu phạt khi đi xe thuê cho du khách: ba nhóm lỗi | E21: 53 | F21: 156 | G21: 1 | H21: 6 | I21: 1042 | J21: Không | K21: Có | L21: 1 | M21: 95 | N21: no-cross-article-duplicate | O21: 97 | P21: IMPROVE | Q21: QA nhà máy cảnh báo: no-cross-article-duplicate | R21: Giữ nguyên; theo dõi Search Console (hiển thị, CTR, truy vấn)
A22: https://chatbot.thuexemaynguyentu.com/blog/an-toan/ai-chiu-phat-khi-di-xe-thue-cho-nguoi-moi/ | B22: BA-0779 | C22: Bài viết | D22: Ai chịu phạt khi đi xe thuê cho người mới: nguyên tắc cần nhớ | E22: 61 | F22: 153 | G22: 1 | H22: 7 | I22: 1347 | J22: Không | K22: Có | L22: 1 | M22: 100 | N22: Không | O22: 92 | P22: KEEP | Q22: QA proxy ≥ 85, không cờ mở, không cảnh báo nội dung | R22: Giữ nguyên; theo dõi Search Console (hiển thị, CTR, truy vấn)
A23: https://chatbot.thuexemaynguyentu.com/blog/an-toan/ai-chiu-phat-khi-di-xe-thue-tom-tat/ | B23: BA-1061 | C23: Bài viết | D23: Tóm tắt ai chịu phạt khi đi xe thuê: phân vai và điểm bằng lái | E23: 62 | F23: 149 | G23: 1 | H23: 8 | I23: 1525 | J23: Không | K23: Có | L23: 2 | M23: 95 | N23: no-cross-article-duplicate | O23: 94 | P23: IMPROVE | Q23: QA nhà máy cảnh báo: no-cross-article-duplicate | R23: Giữ nguyên; theo dõi Search Console (hiển thị, CTR, truy vấn)
A24: https://chatbot.thuexemaynguyentu.com/blog/an-toan/ai-chiu-phat-khi-di-xe-thue-vi-du-thuc-te/ | B24: BA-1343 | C24: Bài viết | D24: Ví dụ ai chịu phạt khi đi xe thuê: các tình huống thực tế | E24: 57 | F24: 153 | G24: 1 | H24: 9 | I24: 1492 | J24: Không | K24: Có | L24: 2 | M24: 100 | N24: Không | O24: 94 | P24: KEEP | Q24: QA proxy ≥ 85, không cờ mở, không cảnh báo nội dung | R24: Giữ nguyên; theo dõi Search Console (hiển thị, CTR, truy vấn)
A25: https://chatbot.thuexemaynguyentu.com/blog/an-toan/ai-chiu-phat-khi-di-xe-thue/ | B25: BA-0215 | C25: Bài viết | D25: Ai chịu phạt khi đi xe thuê: người lái, cửa hàng hay hợp đồng | E25: 61 | F25: 154 | G25: 1 | H25: 6 | I25: 938 | J25: Không | K25: Có | L25: 1 | M25: 95 | N25: title-meta-valid | O25: 95 | P25: IMPROVE | Q25: QA nhà máy cảnh báo: title-meta-valid | R25: Giữ nguyên; theo dõi Search Console (hiển thị, CTR, truy vấn)
A26: https://chatbot.thuexemaynguyentu.com/blog/an-toan/an-toan-khi-thanh-toan-coc-cho-du-khach/ | B26: BA-0563 | C26: Bài viết | D26: Thanh toán cọc thuê xe an toàn cho du khách đến Hà Nội lần đầu | E26: 62 | F26: 157 | G26: 1 | H26: 7 | I26: 1188 | J26: Không | K26: Có | L26: 1 | M26: 100 | N26: Không | O26: 95 | P26: KEEP | Q26: QA proxy ≥ 85, không cờ mở, không cảnh báo nội dung | R26: Giữ nguyên; theo dõi Search Console (hiển thị, CTR, truy vấn)
A27: https://chatbot.thuexemaynguyentu.com/blog/an-toan/an-toan-khi-thanh-toan-coc-cho-nguoi-moi/ | B27: BA-0845 | C27: Bài viết | D27: Thanh toán cọc thuê xe an toàn cho người mới: bảy bước | E27: 54 | F27: 155 | G27: 1 | H27: 8 | I27: 1316 | J27: Không | K27: Có | L27: 2 | M27: 100 | N27: Không | O27: 97 | P27: KEEP | Q27: QA proxy ≥ 85, không cờ mở, không cảnh báo nội dung | R27: Giữ nguyên; theo dõi Search Console (hiển thị, CTR, truy vấn)
A28: https://chatbot.thuexemaynguyentu.com/blog/an-toan/an-toan-khi-thanh-toan-coc-tom-tat/ | B28: BA-1127 | C28: Bài viết | D28: Tóm tắt thanh toán cọc thuê xe an toàn: ba bước kiểm tra | E28: 56 | F28: 155 | G28: 1 | H28: 7 | I28: 1346 | J28: Không | K28: Có | L28: 1 | M28: 100 | N28: Không | O28: 94 | P28: KEEP | Q28: QA proxy ≥ 85, không cờ mở, không cảnh báo nội dung | R28: Giữ nguyên; theo dõi Search Console (hiển thị, CTR, truy vấn)
A29: https://chatbot.thuexemaynguyentu.com/blog/an-toan/an-toan-khi-thanh-toan-coc-vi-du-thuc-te/ | B29: BA-1409 | C29: Bài viết | D29: Ví dụ thanh toán cọc thuê xe an toàn: tình huống thực tế | E29: 56 | F29: 153 | G29: 1 | H29: 8 | I29: 1553 | J29: Không | K29: Có | L29: 1 | M29: 100 | N29: Không | O29: 94 | P29: KEEP | Q29: QA proxy ≥ 85, không cờ mở, không cảnh báo nội dung | R29: Giữ nguyên; theo dõi Search Console (hiển thị, CTR, truy vấn)
A30: https://chatbot.thuexemaynguyentu.com/blog/an-toan/an-toan-khi-thanh-toan-coc/ | B30: BA-0281 | C30: Bài viết | D30: Thanh toán cọc thuê xe an toàn: bằng chứng và điều khoản | E30: 56 | F30: 154 | G30: 1 | H30: 7 | I30: 1372 | J30: Không | K30: Có | L30: 1 | M30: 100 | N30: Không | O30: 97 | P30: KEEP | Q30: QA proxy ≥ 85, không cờ mở, không cảnh báo nội dung | R30: Giữ nguyên; theo dõi Search Console (hiển thị, CTR, truy vấn)
A31: https://chatbot.thuexemaynguyentu.com/blog/an-toan/bang-lai-a1-a2-khac-gi-cau-hoi-thuong-gap/ | B31: BA-1445 | C31: Bài viết | D31: Câu hỏi thường gặp bằng lái A1 A2: bằng cũ, xử phạt, thuê xe | E31: 60 | F31: 156 | G31: 1 | H31: 7 | I31: 1581 | J31: Không | K31: Có | L31: 2 | M31: 100 | N31: Không | O31: 92 | P31: KEEP | Q31: QA proxy ≥ 85, không cờ mở, không cảnh báo nội dung | R31: Giữ nguyên; theo dõi Search Console (hiển thị, CTR, truy vấn)
A32: https://chatbot.thuexemaynguyentu.com/blog/an-toan/bang-lai-a1-a2-khac-gi-cho-du-khach/ | B32: BA-0317 | C32: Bài viết | D32: Bằng lái A1 A2 khác gì cho du khách: điều kiện và rủi ro | E32: 56 | F32: 156 | G32: 1 | H32: 5 | I32: 1758 | J32: Có | K32: Có | L32: 1 | M32: 100 | N32: Không | O32: 95 | P32: KEEP | Q32: QA proxy ≥ 85, không cờ mở, không cảnh báo nội dung | R32: Giữ nguyên; theo dõi Search Console (hiển thị, CTR, truy vấn)
... A36: https://chatbot.thuexemaynguyentu.com/blog/an-toan/bang-lai-a1-a2-khac-gi/ | B36: BA-0035 | C36: Bài viết | D36: Bằng lái A1 A2 khác gì: hạng hiện hành và điều cần đối chiếu | E36: 60 | F36: 158 | G36: 1 | H36: 6 | I36: 1868 | J36: Có | K36: Có | L36: 2 | M36: 100 | N36: Không | O36: 100 | P36: KEEP | Q36: QA proxy ≥ 85, không cờ mở, không cảnh báo nội dung | R36: Giữ nguyên; theo dõi Search Console (hiển thị, CTR, truy vấn)
A37: https://chatbot.thuexemaynguyentu.com/blog/an-toan/bang-lai/ | B37: N/A | C37: Hub chủ đề con | D37: Bằng Lái — An toàn / pháp lý — Cẩm nang thuê xe máy | E37: 51 | F37: 142 | G37: 1 | H37: 13 | I37: 766 | J37: Không | K37: Không | L37: 0 | M37: N/A | N37: N/A | O37: 87 | P37: KEEP | Q37: QA proxy ≥ 85, không cờ mở, không cảnh báo nội dung | R37: Giữ nguyên; theo dõi Search Console (hiển thị, CTR, truy vấn)
A38: https://chatbot.thuexemaynguyentu.com/blog/an-toan/bao-hiem-khi-thue-xe-may-cau-hoi-thuong-gap/ | B38: BA-1463 | C38: Bài viết | D38: Câu hỏi thường gặp bảo hiểm khi thuê xe máy ở Long Biên | E38: 55 | F38: 152 | G38: 1 | H38: 6 | I38: 1486 | J38: Không | K38: Có | L38: 2 | M38: 100 | N38: Không | O38: 92 | P38: KEEP | Q38: QA proxy ≥ 85, không cờ mở, không cảnh báo nội dung | R38: Giữ nguyên; theo dõi Search Console (hiển thị, CTR, truy vấn)
A39: https://chatbot.thuexemaynguyentu.com/blog/an-toan/bao-hiem-khi-thue-xe-may-cho-du-khach/ | B39: BA-0335 | C39: Bài viết | D39: Bảo hiểm khi thuê xe máy cho du khách: hai lớp cần biết | E39: 55 | F39: 147 | G39: 1 | H39: 6 | I39: 1545 | J39: Không | K39: Có | L39: 1 | M39: 100 | N39: Không | O39: 97 | P39: KEEP | Q39: QA proxy ≥ 85, không cờ mở, không cảnh báo nội dung | R39: Giữ nguyên; theo dõi Search Console (hiển thị, CTR, truy vấn)
A40: https://chatbot.thuexemaynguyentu.com/blog/an-toan/bao-hiem-khi-thue-xe-may-cho-nguoi-moi/ | B40: BA-0617 | C40: Bài viết | D40: Bảo hiểm khi thuê xe máy cho người mới: điều cần hỏi trước | E40: 58 | F40: 155 | G40: 1 | H40: 7 | I40: 1515 | J40: Không | K40: Có | L40: 1 | M40: 100 | N40: Không | O40: 97 | P40: KEEP | Q40: QA proxy ≥ 85, không cờ mở, không cảnh báo nội dung | R40: Giữ nguyên; theo dõi Search Console (hiển thị, CTR, truy vấn)
A41: https://chatbot.thuexemaynguyentu.com/blog/an-toan/bao-hiem-khi-thue-xe-may-tom-tat/ | B41: BA-0899 | C41: Bài viết | D41: Tóm tắt bảo hiểm khi thuê xe máy: loại bắt buộc, ai chuẩn bị | E41: 60 | F41: 154 | G41: 1 | H41: 8 | I41: 1207 | J41: Không | K41: Có | L41: 2 | M41: 100 | N41: Không | O41: 94 | P41: KEEP | Q41: QA proxy ≥ 85, không cờ mở, không cảnh báo nội dung | R41: Giữ nguyên; theo dõi Search Console (hiển thị, CTR, truy vấn)
A42: https://chatbot.thuexemaynguyentu.com/blog/an-toan/bao-hiem-khi-thue-xe-may-vi-du-thuc-te/ | B42: BA-1181 | C42: Bài viết | D42: Ví dụ bảo hiểm khi thuê xe máy: va quẹt, tự ngã, nổ lốp | E42: 55 | F42: 153 | G42: 1 | H42: 10 | I42: 1900 | J42: Không | K42: Có | L42: 1 | M42: 100 | N42: Không | O42: 97 | P42: KEEP | Q42: QA proxy ≥ 85, không cờ mở, không cảnh báo nội dung | R42: Giữ nguyên; theo dõi Search Console (hiển thị, CTR, truy vấn)
A43: https://chatbot.thuexemaynguyentu.com/blog/an-toan/bao-hiem-khi-thue-xe-may/ | B43: BA-0053 | C43: Bài viết | D43: Bảo hiểm khi thuê xe máy: loại bắt buộc và bảo hiểm cá nhân | E43: 59 | F43: 151 | G43: 1 | H43: 6 | I43: 1766 | J43: Không | K43: Có | L43: 1 | M43: 100 | N43: Không | O43: 100 | P43: KEEP | Q43: QA proxy ≥ 85, không cờ mở, không cảnh báo nội dung | R43: Giữ nguyên; theo dõi Search Console (hiển thị, CTR, truy vấn)
A44: https://chatbot.thuexemaynguyentu.com/blog/an-toan/bao-va-xe-may-cho-du-khach/ | B44: BA-0467 | C44: Bài viết | D44: Đi xe máy khi có bão cho du khách: đọc bản tin, dừng hay đi | E44: 59 | F44: 157 | G44: 1 | H44: 9 | I44: 1873 | J44: Không | K44: Có | L44: 1 | M44: 100 | N44: Không | O44: 97 | P44: KEEP | Q44: QA proxy ≥ 85, không cờ mở, không cảnh báo nội dung | R44: Giữ nguyên; theo dõi Search Console (hiển thị, CTR, truy vấn)
A45: https://chatbot.thuexemaynguyentu.com/blog/an-toan/bao-va-xe-may-cho-nguoi-moi/ | B45: BA-0749 | C45: Bài viết | D45: Đi xe máy khi có bão cho người mới: hoãn, xử lý, kiểm tra xe | E45: 60 | F45: 157 | G45: 1 | H45: 5 | I45: 1469 | J45: Không | K45: Có | L45: 1 | M45: 100 | N45: Không | O45: 95 | P45: KEEP | Q45: QA proxy ≥ 85, không cờ mở, không cảnh báo nội dung | R45: Giữ nguyên; theo dõi Search Console (hiển thị, CTR, truy vấn)
A46: https://chatbot.thuexemaynguyentu.com/blog/an-toan/bao-va-xe-may-tom-tat/ | B46: BA-1031 | C46: Bài viết | D46: Tóm tắt đi xe máy khi có bão: đi hay hoãn, kiểm tra sau bão | E46: 59 | F46: 156 | G46: 1 | H46: 8 | I46: 1536 | J46: Không | K46: Có | L46: 2 | M46: 100 | N46: Không | O46: 94 | P46: KEEP | Q46: QA proxy ≥ 85, không cờ mở, không cảnh báo nội dung | R46: Giữ nguyên; theo dõi Search Console (hiển thị, CTR, truy vấn)
A47: https://chatbot.thuexemaynguyentu.com/blog/an-toan/bao-va-xe-may-vi-du-thuc-te/ | B47: BA-1313 | C47: Bài viết | D47: Ví dụ đi xe máy khi có bão: gió giật, cành cây gãy, dây điện | E47: 60 | F47: 157 | G47: 1 | H47: 8 | I47: 1582 | J47: Không | K47: Có | L47: 2 | M47: 100 | N47: Không | O47: 92 | P47: KEEP | Q47: QA proxy ≥ 85, không cờ mở, không cảnh báo nội dung | R47: Giữ nguyên; theo dõi Search Console (hiển thị, CTR, truy vấn)
A48: https://chatbot.thuexemaynguyentu.com/blog/an-toan/bao-va-xe-may/ | B48: BA-0185 | C48: Bài viết | D48: Đi xe máy khi có bão: dừng hay tiếp tục, cách đi an toàn | E48: 56 | F48: 151 | G48: 1 | H48: 7 | I48: 1097 | J48: Không | K48: Có | L48: 1 | M48: 100 | N48: Không | O48: 97 | P48: KEEP | Q48: QA proxy ≥ 85, không cờ mở, không cảnh báo nội dung | R48: Giữ nguyên; theo dõi Search Console (hiển thị, CTR, truy vấn)
A49: https://chatbot.thuexemaynguyentu.com/blog/an-toan/bao-ve-du-lieu-ca-nhan-khi-thue-xe-cho-du-khach/ | B49: BA-0557 | C49: Bài viết | D49: Dữ liệu cá nhân du khách khi thuê xe: giấy tờ và quyền | E49: 54 | F49: 150 | G49: 1 | H49: 7 | I49: 1402 | J49: Không | K49: Có | L49: 1 | M49: 95 | N49: no-cross-article-duplicate | O49: 97 | P49: IMPROVE | Q49: QA nhà máy cảnh báo: no-cross-article-duplicate | R49: Giữ nguyên; theo dõi Search Console (hiển thị, CTR, truy vấn)
... A107: https://chatbot.thuexemaynguyentu.com/blog/an-toan/dien-thoai-khi-lai-xe/ | B107: BA-0143 | C107: Bài viết | D107: Dùng điện thoại khi lái xe máy: quy định và ranh giới | E107: 53 | F107: 155 | G107: 1 | H107: 6 | I107: 1326 | J107: Không | K107: Có | L107: 2 | M107: 90 | N107: no-cross-article-duplicate, title-meta-valid | O107: 97 | P107: IMPROVE | Q107: QA nhà máy cảnh báo: no-cross-article-duplicate, title-meta-valid | R107: Giữ nguyên; theo dõi Search Console (hiển thị, CTR, truy vấn)
A108: https://chatbot.thuexemaynguyentu.com/blog/an-toan/du-lich/ | B108: N/A | C108: Hub chủ đề con | D108: Du Lịch — An toàn / pháp lý — Cẩm nang thuê xe máy | E108: 50 | F108: 140 | G108: 1 | H108: 5 | I108: 321 | J108: Không | K108: Không | L108: 0 | M108: N/A | N108: N/A | O108: 87 | P108: KEEP | Q108: QA proxy ≥ 85, không cờ mở, không cảnh báo nội dung | R108: Giữ nguyên; theo dõi Search Console (hiển thị, CTR, truy vấn)
A109: https://chatbot.thuexemaynguyentu.com/blog/an-toan/goi-canh-sat-khi-tai-nan-cau-hoi-thuong-gap/ | B109: BA-1481 | C109: Bài viết | D109: Câu hỏi thường gặp gọi cảnh sát khi tai nạn xe thuê | E109: 51 | F109: 156 | G109: 1 | H109: 7 | I109: 1572 | J109: Không | K109: Có | L109: 2 | M109: 95 | N109: no-cross-article-duplicate | O109: 90 | P109: IMPROVE | Q109: QA nhà máy cảnh báo: no-cross-article-duplicate | R109: Giữ nguyên; theo dõi Search Console (hiển thị, CTR, truy vấn)
A110: https://chatbot.thuexemaynguyentu.com/blog/an-toan/goi-canh-sat-khi-tai-nan-cho-du-khach/ | B110: BA-0353 | C110: Bài viết | D110: Gọi cảnh sát khi tai nạn cho du khách: nói gì, làm gì khi chờ | E110: 61 | F110: 158 | G110: 1 | H110: 6 | I110: 1372 | J110: Không | K110: Có | L110: 1 | M110: 100 | N110: Không | O110: 95 | P110: KEEP | Q110: QA proxy ≥ 85, không cờ mở, không cảnh báo nội dung | R110: Giữ nguyên; theo dõi Search Console (hiển thị, CTR, truy vấn)
A111: https://chatbot.thuexemaynguyentu.com/blog/an-toan/goi-canh-sat-khi-tai-nan-cho-nguoi-moi/ | B111: BA-0635 | C111: Bài viết | D111: Gọi cảnh sát khi tai nạn cho người mới: gọi 113 nói gì | E111: 54 | F111: 155 | G111: 1 | H111: 8 | I111: 1394 | J111: Không | K111: Có | L111: 1 | M111: 100 | N111: Không | O111: 97 | P111: KEEP | Q111: QA proxy ≥ 85, không cờ mở, không cảnh báo nội dung | R111: Giữ nguyên; theo dõi Search Console (hiển thị, CTR, truy vấn)
A112: https://chatbot.thuexemaynguyentu.com/blog/an-toan/goi-canh-sat-khi-tai-nan-tom-tat/ | B112: BA-0917 | C112: Bài viết | D112: Tóm tắt gọi cảnh sát khi tai nạn: tình huống và kịch bản 113 | E112: 60 | F112: 154 | G112: 1 | H112: 8 | I112: 1368 | J112: Không | K112: Có | L112: 2 | M112: 100 | N112: Không | O112: 94 | P112: KEEP | Q112: QA proxy ≥ 85, không cờ mở, không cảnh báo nội dung | R112: Giữ nguyên; theo dõi Search Console (hiển thị, CTR, truy vấn)
A113: https://chatbot.thuexemaynguyentu.com/blog/an-toan/goi-canh-sat-khi-tai-nan-vi-du-thuc-te/ | B113: BA-1199 | C113: Bài viết | D113: Ví dụ gọi cảnh sát khi tai nạn: va quẹt, ngã, xe kia bỏ chạy | E113: 60 | F113: 153 | G113: 1 | H113: 10 | I113: 1628 | J113: Không | K113: Có | L113: 2 | M113: 100 | N113: Không | O113: 92 | P113: KEEP | Q113: QA proxy ≥ 85, không cờ mở, không cảnh báo nội dung | R113: Giữ nguyên; theo dõi Search Console (hiển thị, CTR, truy vấn)
A114: https://chatbot.thuexemaynguyentu.com/blog/an-toan/goi-canh-sat-khi-tai-nan/ | B114: BA-0071 | C114: Bài viết | D114: Gọi cảnh sát khi tai nạn: khi nào bắt buộc và nói gì | E114: 52 | F114: 154 | G114: 1 | H114: 9 | I114: 1864 | J114: Không | K114: Có | L114: 2 | M114: 100 | N114: Không | O114: 97 | P114: KEEP | Q114: QA proxy ≥ 85, không cờ mở, không cảnh báo nội dung | R114: Giữ nguyên; theo dõi Search Console (hiển thị, CTR, truy vấn)
A115: https://chatbot.thuexemaynguyentu.com/blog/an-toan/guong-chieu-hau-an-toan-cho-du-khach/ | B115: BA-0377 | C115: Bài viết | D115: Gương chiếu hậu xe máy an toàn cho du khách: ba phút nhận xe | E115: 60 | F115: 157 | G115: 1 | H115: 6 | I115: 1285 | J115: Không | K115: Có | L115: 1 | M115: 95 | N115: no-cross-article-duplicate | O115: 94 | P115: IMPROVE | Q115: QA nhà máy cảnh báo: no-cross-article-duplicate | R115: Giữ nguyên; theo dõi Search Console (hiển thị, CTR, truy vấn)
A116: https://chatbot.thuexemaynguyentu.com/blog/an-toan/guong-chieu-hau-an-toan-cho-nguoi-moi/ | B116: BA-0659 | C116: Bài viết | D116: Gương chiếu hậu xe máy an toàn cho người mới: chỉnh tại quầy | E116: 60 | F116: 157 | G116: 1 | H116: 8 | I116: 1503 | J116: Không | K116: Có | L116: 1 | M116: 100 | N116: Không | O116: 97 | P116: KEEP | Q116: QA proxy ≥ 85, không cờ mở, không cảnh báo nội dung | R116: Giữ nguyên; theo dõi Search Console (hiển thị, CTR, truy vấn)
A117: https://chatbot.thuexemaynguyentu.com/blog/an-toan/guong-chieu-hau-an-toan-tom-tat/ | B117: BA-0941 | C117: Bài viết | D117: Tóm tắt gương chiếu hậu xe máy an toàn: kiểm tra nhanh | E117: 54 | F117: 156 | G117: 1 | H117: 8 | I117: 1442 | J117: Không | K117: Có | L117: 2 | M117: 100 | N117: Không | O117: 92 | P117: KEEP | Q117: QA proxy ≥ 85, không cờ mở, không cảnh báo nội dung | R117: Giữ nguyên; theo dõi Search Console (hiển thị, CTR, truy vấn)
A118: https://chatbot.thuexemaynguyentu.com/blog/an-toan/guong-chieu-hau-an-toan-vi-du-thuc-te/ | B118: BA-1223 | C118: Bài viết | D118: Ví dụ gương chiếu hậu xe máy an toàn: gương lỏng, gập gương | E118: 59 | F118: 157 | G118: 1 | H118: 8 | I118: 1321 | J118: Không | K118: Có | L118: 2 | M118: 100 | N118: Không | O118: 94 | P118: KEEP | Q118: QA proxy ≥ 85, không cờ mở, không cảnh báo nội dung | R118: Giữ nguyên; theo dõi Search Console (hiển thị, CTR, truy vấn)
A119: https://chatbot.thuexemaynguyentu.com/blog/an-toan/guong-chieu-hau-an-toan/ | B119: BA-0095 | C119: Bài viết | D119: Gương chiếu hậu xe máy an toàn: quy định và cách chỉnh | E119: 54 | F119: 157 | G119: 1 | H119: 10 | I119: 1730 | J119: Không | K119: Có | L119: 2 | M119: 100 | N119: Không | O119: 97 | P119: KEEP | Q119: QA proxy ≥ 85, không cờ mở, không cảnh báo nội dung | R119: Giữ nguyên; theo dõi Search Console (hiển thị, CTR, truy vấn)
A120: https://chatbot.thuexemaynguyentu.com/blog/an-toan/idp-va-bang-lai-quoc-te-cau-hoi-thuong-gap/ | B120: BA-1457 | C120: Bài viết | D120: Câu hỏi thường gặp IDP và bằng lái quốc tế khi thuê xe | E120: 54 | F120: 150 | G120: 1 | H120: 7 | I120: 1621 | J120: Không | K120: Có | L120: 2 | M120: 100 | N120: Không | O120: 92 | P120: KEEP | Q120: QA proxy ≥ 85, không cờ mở, không cảnh báo nội dung | R120: Giữ nguyên; theo dõi Search Console (hiển thị, CTR, truy vấn)
... A147: https://chatbot.thuexemaynguyentu.com/blog/an-toan/ky-nang-phanh-gap/ | B147: BA-0089 | C147: Bài viết | D147: Kỹ năng phanh gấp xe máy: bốn bước luyện cú phanh an toàn | E147: 57 | F147: 154 | G147: 1 | H147: 10 | I147: 1704 | J147: Không | K147: Có | L147: 2 | M147: 100 | N147: Không | O147: 97 | P147: KEEP | Q147: QA proxy ≥ 85, không cờ mở, không cảnh báo nội dung | R147: Giữ nguyên; theo dõi Search Console (hiển thị, CTR, truy vấn)
A148: https://chatbot.thuexemaynguyentu.com/blog/an-toan/lai-xe/ | B148: N/A | C148: Hub chủ đề con | D148: Lái Xe — An toàn / pháp lý — Cẩm nang thuê xe máy | E148: 49 | F148: 140 | G148: 1 | H148: 24 | I148: 1350 | J148: Không | K148: Không | L148: 0 | M148: N/A | N148: N/A | O148: 87 | P148: KEEP | Q148: QA proxy ≥ 85, không cờ mở, không cảnh báo nội dung | R148: Giữ nguyên; theo dõi Search Console (hiển thị, CTR, truy vấn)
A149: https://chatbot.thuexemaynguyentu.com/blog/an-toan/lan-duong-va-quy-tac-nhuong-cho-du-khach/ | B149: BA-0407 | C149: Bài viết | D149: Làn đường và nhường đường cho du khách: cách đọc đường Hà Nội | E149: 61 | F149: 155 | G149: 1 | H149: 8 | I149: 1994 | J149: Không | K149: Có | L149: 1 | M149: 100 | N149: Không | O149: 94 | P149: KEEP | Q149: QA proxy ≥ 85, không cờ mở, không cảnh báo nội dung | R149: Giữ nguyên; theo dõi Search Console (hiển thị, CTR, truy vấn)
A150: https://chatbot.thuexemaynguyentu.com/blog/an-toan/lan-duong-va-quy-tac-nhuong-cho-nguoi-moi/ | B150: BA-0689 | C150: Bài viết | D150: Làn đường và nhường đường cho người mới: quy tắc và mức phạt | E150: 60 | F150: 155 | G150: 1 | H150: 6 | I150: 1448 | J150: Không | K150: Có | L150: 2 | M150: 100 | N150: Không | O150: 92 | P150: KEEP | Q150: QA proxy ≥ 85, không cờ mở, không cảnh báo nội dung | R150: Giữ nguyên; theo dõi Search Console (hiển thị, CTR, truy vấn)
A151: https://chatbot.thuexemaynguyentu.com/blog/an-toan/lan-duong-va-quy-tac-nhuong-tom-tat/ | B151: BA-0971 | C151: Bài viết | D151: Tóm tắt quy tắc làn đường và nhường đường: phiếu nhắc sáu ý | E151: 59 | F151: 158 | G151: 1 | H151: 8 | I151: 1537 | J151: Không | K151: Có | L151: 2 | M151: 100 | N151: Không | O151: 94 | P151: KEEP | Q151: QA proxy ≥ 85, không cờ mở, không cảnh báo nội dung | R151: Giữ nguyên; theo dõi Search Console (hiển thị, CTR, truy vấn)
A152: https://chatbot.thuexemaynguyentu.com/blog/an-toan/lan-duong-va-quy-tac-nhuong-vi-du-thuc-te/ | B152: BA-1253 | C152: Bài viết | D152: Ví dụ quy tắc làn đường và nhường đường: bảy khoảnh khắc | E152: 56 | F152: 144 | G152: 1 | H152: 6 | I152: 1530 | J152: Không | K152: Có | L152: 2 | M152: 100 | N152: Không | O152: 88 | P152: KEEP | Q152: QA proxy ≥ 85, không cờ mở, không cảnh báo nội dung | R152: Giữ nguyên; theo dõi Search Console (hiển thị, CTR, truy vấn)
A153: https://chatbot.thuexemaynguyentu.com/blog/an-toan/lan-duong-va-quy-tac-nhuong/ | B153: BA-0125 | C153: Bài viết | D153: Quy tắc làn đường và nhường đường: Điều 13, 14 và mức xử phạt | E153: 61 | F153: 157 | G153: 1 | H153: 8 | I153: 1788 | J153: Không | K153: Có | L153: 2 | M153: 95 | N153: no-cross-article-duplicate | O153: 97 | P153: IMPROVE | Q153: QA nhà máy cảnh báo: no-cross-article-duplicate | R153: Giữ nguyên; theo dõi Search Console (hiển thị, CTR, truy vấn)
A154: https://chatbot.thuexemaynguyentu.com/blog/an-toan/loi-khong-guong-xe-may/ | B154: BA-2003 | C154: Bài viết | D154: Lỗi không gương xe máy phạt bao nhiêu? Mức phạt Nghị định 168 | E154: 61 | F154: 163 | G154: 1 | H154: 7 | I154: 1678 | J154: Có | K154: Có | L154: 2 | M154: 100 | N154: Không | O154: 97 | P154: KEEP | Q154: QA proxy ≥ 85, không cờ mở, không cảnh báo nội dung | R154: Giữ nguyên; theo dõi Search Console (hiển thị, CTR, truy vấn)
A155: https://chatbot.thuexemaynguyentu.com/blog/an-toan/luat-giao-thong-duong-bo-co-ban-cau-hoi-thuong-gap/ | B155: BA-1415 | C155: Bài viết | D155: Câu hỏi về luật giao thông khi thuê xe máy: bằng lái, đèn, cồn | E155: 62 | F155: 158 | G155: 1 | H155: 7 | I155: 1724 | J155: Không | K155: Có | L155: 2 | M155: 100 | N155: Không | O155: 92 | P155: KEEP | Q155: QA proxy ≥ 85, không cờ mở, không cảnh báo nội dung | R155: Giữ nguyên; theo dõi Search Console (hiển thị, CTR, truy vấn)
A156: https://chatbot.thuexemaynguyentu.com/blog/an-toan/luat-giao-thong-duong-bo-co-ban-cho-du-khach/ | B156: BA-0287 | C156: Bài viết | D156: Luật giao thông đường bộ cơ bản cho du khách tự lái xe máy | E156: 58 | F156: 154 | G156: 1 | H156: 7 | I156: 1305 | J156: Không | K156: Có | L156: 1 | M156: 100 | N156: Không | O156: 97 | P156: KEEP | Q156: QA proxy ≥ 85, không cờ mở, không cảnh báo nội dung | R156: Giữ nguyên; theo dõi Search Console (hiển thị, CTR, truy vấn)
A157: https://chatbot.thuexemaynguyentu.com/blog/an-toan/luat-giao-thong-duong-bo-co-ban-cho-nguoi-moi/ | B157: BA-0569 | C157: Bài viết | D157: Luật giao thông đường bộ cơ bản cho người mới thuê xe máy | E157: 57 | F157: 155 | G157: 1 | H157: 6 | I157: 1094 | J157: Không | K157: Có | L157: 1 | M157: 95 | N157: no-cross-article-duplicate | O157: 97 | P157: IMPROVE | Q157: QA nhà máy cảnh báo: no-cross-article-duplicate | R157: Giữ nguyên; theo dõi Search Console (hiển thị, CTR, truy vấn)
A158: https://chatbot.thuexemaynguyentu.com/blog/an-toan/luat-giao-thong-duong-bo-co-ban-tom-tat/ | B158: BA-0851 | C158: Bài viết | D158: Tóm tắt luật giao thông đường bộ cơ bản cho xe máy thuê | E158: 55 | F158: 157 | G158: 1 | H158: 8 | I158: 1512 | J158: Không | K158: Có | L158: 2 | M158: 100 | N158: Không | O158: 97 | P158: KEEP | Q158: QA proxy ≥ 85, không cờ mở, không cảnh báo nội dung | R158: Giữ nguyên; theo dõi Search Console (hiển thị, CTR, truy vấn)
A159: https://chatbot.thuexemaynguyentu.com/blog/an-toan/luat-giao-thong-duong-bo-co-ban-vi-du-thuc-te/ | B159: BA-1133 | C159: Bài viết | D159: Ví dụ luật giao thông đường bộ cơ bản: sáu tình huống xe máy | E159: 60 | F159: 158 | G159: 1 | H159: 8 | I159: 1625 | J159: Không | K159: Có | L159: 2 | M159: 100 | N159: Không | O159: 92 | P159: KEEP | Q159: QA proxy ≥ 85, không cờ mở, không cảnh báo nội dung | R159: Giữ nguyên; theo dõi Search Console (hiển thị, CTR, truy vấn)
A160: https://chatbot.thuexemaynguyentu.com/blog/an-toan/luat-giao-thong-duong-bo-co-ban/ | B160: BA-0005 | C160: Bài viết | D160: Luật giao thông đường bộ cơ bản: điều người thuê xe cần nắm | E160: 59 | F160: 158 | G160: 1 | H160: 8 | I160: 1964 | J160: Không | K160: Có | L160: 1 | M160: 100 | N160: Không | O160: 100 | P160: KEEP | Q160: QA proxy ≥ 85, không cờ mở, không cảnh báo nội dung | R160: Giữ nguyên; theo dõi Search Console (hiển thị, CTR, truy vấn)
... A171: https://chatbot.thuexemaynguyentu.com/blog/an-toan/mu-bao-hiem-chuan/ | B171: BA-0017 | C171: Bài viết | D171: Mũ bảo hiểm đạt chuẩn: cách nhận biết dấu CR và cài quai đúng | E171: 61 | F171: 150 | G171: 1 | H171: 8 | I171: 1985 | J171: Không | K171: Có | L171: 2 | M171: 100 | N171: Không | O171: 100 | P171: KEEP | Q171: QA proxy ≥ 85, không cờ mở, không cảnh báo nội dung | R171: Giữ nguyên; theo dõi Search Console (hiển thị, CTR, truy vấn)
A172: https://chatbot.thuexemaynguyentu.com/blog/an-toan/mu-bao-hiem/ | B172: N/A | C172: Hub chủ đề con | D172: Mũ Bảo Hiểm — An toàn / pháp lý — Cẩm nang thuê xe máy | E172: 54 | F172: 145 | G172: 1 | H172: 16 | I172: 930 | J172: Không | K172: Không | L172: 0 | M172: N/A | N172: N/A | O172: 87 | P172: KEEP | Q172: QA proxy ≥ 85, không cờ mở, không cảnh báo nội dung | R172: Giữ nguyên; theo dõi Search Console (hiển thị, CTR, truy vấn)
A173: https://chatbot.thuexemaynguyentu.com/blog/an-toan/mua-ban-xe-may-giay-to-cho-du-khach/ | B173: BA-0509 | C173: Bài viết | D173: Du khách mua xe máy cần giấy tờ gì: kiểm tra trước khi mua | E173: 58 | F173: 156 | G173: 1 | H173: 7 | I173: 1079 | J173: Không | K173: Có | L173: 1 | M173: 95 | N173: no-cross-article-duplicate | O173: 94 | P173: IMPROVE | Q173: QA nhà máy cảnh báo: no-cross-article-duplicate | R173: Giữ nguyên; theo dõi Search Console (hiển thị, CTR, truy vấn)
A174: https://chatbot.thuexemaynguyentu.com/blog/an-toan/mua-ban-xe-may-giay-to-cho-nguoi-moi/ | B174: BA-0791 | C174: Bài viết | D174: Mua xe máy cũ lần đầu cần giấy tờ gì: năm bước xem xe | E174: 53 | F174: 152 | G174: 1 | H174: 8 | I174: 1622 | J174: Không | K174: Có | L174: 2 | M174: 100 | N174: Không | O174: 94 | P174: KEEP | Q174: QA proxy ≥ 85, không cờ mở, không cảnh báo nội dung | R174: Giữ nguyên; theo dõi Search Console (hiển thị, CTR, truy vấn)
A175: https://chatbot.thuexemaynguyentu.com/blog/an-toan/mua-ban-xe-may-giay-to-tom-tat/ | B175: BA-1073 | C175: Bài viết | D175: Tóm tắt giấy tờ mua bán xe máy: bốn nhóm giấy tờ phải có | E175: 56 | F175: 151 | G175: 1 | H175: 7 | I175: 1356 | J175: Không | K175: Có | L175: 1 | M175: 100 | N175: Không | O175: 94 | P175: KEEP | Q175: QA proxy ≥ 85, không cờ mở, không cảnh báo nội dung | R175: Giữ nguyên; theo dõi Search Console (hiển thị, CTR, truy vấn)
A176: https://chatbot.thuexemaynguyentu.com/blog/an-toan/mua-ban-xe-may-giay-to-vi-du-thuc-te/ | B176: BA-1355 | C176: Bài viết | D176: Ví dụ giấy tờ mua bán xe máy: sáu tình huống dễ vướng | E176: 53 | F176: 150 | G176: 1 | H176: 9 | I176: 1559 | J176: Không | K176: Có | L176: 2 | M176: 100 | N176: Không | O176: 92 | P176: KEEP | Q176: QA proxy ≥ 85, không cờ mở, không cảnh báo nội dung | R176: Giữ nguyên; theo dõi Search Console (hiển thị, CTR, truy vấn)
A177: https://chatbot.thuexemaynguyentu.com/blog/an-toan/mua-ban-xe-may-giay-to/ | B177: BA-0227 | C177: Bài viết | D177: Mua bán xe máy giấy tờ: cần những gì và sang tên thế nào | E177: 56 | F177: 154 | G177: 1 | H177: 7 | I177: 1136 | J177: Không | K177: Có | L177: 1 | M177: 95 | N177: no-cross-article-duplicate | O177: 97 | P177: IMPROVE | Q177: QA nhà máy cảnh báo: no-cross-article-duplicate | R177: Giữ nguyên; theo dõi Search Console (hiển thị, CTR, truy vấn)
A178: https://chatbot.thuexemaynguyentu.com/blog/an-toan/mua-lon-va-lai-xe-cho-du-khach/ | B178: BA-0383 | C178: Bài viết | D178: Du khách đi xe máy gặp mưa lớn: dừng hay chạy tiếp | E178: 50 | F178: 147 | G178: 1 | H178: 6 | I178: 1172 | J178: Không | K178: Có | L178: 1 | M178: 100 | N178: Không | O178: 92 | P178: KEEP | Q178: QA proxy ≥ 85, không cờ mở, không cảnh báo nội dung | R178: Giữ nguyên; theo dõi Search Console (hiển thị, CTR, truy vấn)
A179: https://chatbot.thuexemaynguyentu.com/blog/an-toan/mua-lon-va-lai-xe-cho-nguoi-moi/ | B179: BA-0665 | C179: Bài viết | D179: Người mới lái xe máy khi mưa lớn: trang bị và bốn thao tác | E179: 58 | F179: 148 | G179: 1 | H179: 9 | I179: 1659 | J179: Không | K179: Có | L179: 1 | M179: 95 | N179: no-cross-article-duplicate | O179: 97 | P179: IMPROVE | Q179: QA nhà máy cảnh báo: no-cross-article-duplicate | R179: Giữ nguyên; theo dõi Search Console (hiển thị, CTR, truy vấn)
A180: https://chatbot.thuexemaynguyentu.com/blog/an-toan/mua-lon-va-lai-xe-tom-tat/ | B180: BA-0947 | C180: Bài viết | D180: Tóm tắt lái xe máy khi mưa lớn: năm ý chính cần nhớ | E180: 51 | F180: 155 | G180: 1 | H180: 7 | I180: 1217 | J180: Không | K180: Có | L180: 2 | M180: 100 | N180: Không | O180: 94 | P180: KEEP | Q180: QA proxy ≥ 85, không cờ mở, không cảnh báo nội dung | R180: Giữ nguyên; theo dõi Search Console (hiển thị, CTR, truy vấn)
A181: https://chatbot.thuexemaynguyentu.com/blog/an-toan/mua-lon-va-lai-xe-vi-du-thuc-te/ | B181: BA-1229 | C181: Bài viết | D181: Ví dụ lái xe máy khi mưa lớn: năm tình huống dễ mắc lỗi | E181: 55 | F181: 156 | G181: 1 | H181: 8 | I181: 1562 | J181: Không | K181: Có | L181: 2 | M181: 100 | N181: Không | O181: 92 | P181: KEEP | Q181: QA proxy ≥ 85, không cờ mở, không cảnh báo nội dung | R181: Giữ nguyên; theo dõi Search Console (hiển thị, CTR, truy vấn)
A182: https://chatbot.thuexemaynguyentu.com/blog/an-toan/mua-lon-va-lai-xe/ | B182: BA-0101 | C182: Bài viết | D182: Lái xe máy khi mưa lớn: quy định, chuẩn bị và đường ướt | E182: 55 | F182: 154 | G182: 1 | H182: 10 | I182: 1537 | J182: Không | K182: Có | L182: 2 | M182: 95 | N182: no-cross-article-duplicate | O182: 97 | P182: IMPROVE | Q182: QA nhà máy cảnh báo: no-cross-article-duplicate | R182: Giữ nguyên; theo dõi Search Console (hiển thị, CTR, truy vấn)
A183: https://chatbot.thuexemaynguyentu.com/blog/an-toan/ngap-nuoc-va-xe-may-cho-du-khach/ | B183: BA-0473 | C183: Bài viết | D183: Du khách đi xe máy gặp đường ngập: bốn bước xử lý giữa phố | E183: 58 | F183: 157 | G183: 1 | H183: 8 | I183: 1698 | J183: Không | K183: Có | L183: 1 | M183: 100 | N183: Không | O183: 94 | P183: KEEP | Q183: QA proxy ≥ 85, không cờ mở, không cảnh báo nội dung | R183: Giữ nguyên; theo dõi Search Console (hiển thị, CTR, truy vấn)
A184: https://chatbot.thuexemaynguyentu.com/blog/an-toan/ngap-nuoc-va-xe-may-cho-nguoi-moi/ | B184: BA-0755 | C184: Bài viết | D184: Người mới đi xe máy qua đường ngập: ba bước xử lý, trang bị | E184: 59 | F184: 142 | G184: 1 | H184: 7 | I184: 1305 | J184: Không | K184: Có | L184: 1 | M184: 100 | N184: Không | O184: 97 | P184: KEEP | Q184: QA proxy ≥ 85, không cờ mở, không cảnh báo nội dung | R184: Giữ nguyên; theo dõi Search Console (hiển thị, CTR, truy vấn)
... A209: https://chatbot.thuexemaynguyentu.com/blog/an-toan/nong-do-con-khi-lai-xe/ | B209: BA-0011 | C209: Bài viết | D209: Mức phạt nồng độ cồn xe máy: ba mức, trừ điểm, tước bằng | E209: 56 | F209: 158 | G209: 1 | H209: 9 | I209: 1970 | J209: Có | K209: Có | L209: 1 | M209: 100 | N209: Không | O209: 100 | P209: KEEP | Q209: QA proxy ≥ 85, không cờ mở, không cảnh báo nội dung | R209: Giữ nguyên; theo dõi Search Console (hiển thị, CTR, truy vấn)
A210: https://chatbot.thuexemaynguyentu.com/blog/an-toan/phap-luat/ | B210: N/A | C210: Hub chủ đề con | D210: Pháp Luật — An toàn / pháp lý — Cẩm nang thuê xe máy | E210: 52 | F210: 143 | G210: 1 | H210: 24 | I210: 1355 | J210: Không | K210: Không | L210: 0 | M210: N/A | N210: N/A | O210: 90 | P210: KEEP | Q210: QA proxy ≥ 85, không cờ mở, không cảnh báo nội dung | R210: Giữ nguyên; theo dõi Search Console (hiển thị, CTR, truy vấn)
A211: https://chatbot.thuexemaynguyentu.com/blog/an-toan/phat-nguoi-va-xe-thue-cho-du-khach/ | B211: BA-0491 | C211: Bài viết | D211: Phạt nguội xe thuê cho du khách: thông báo đến sau khi trả xe | E211: 61 | F211: 146 | G211: 1 | H211: 6 | I211: 1114 | J211: Không | K211: Có | L211: 1 | M211: 95 | N211: no-cross-article-duplicate | O211: 97 | P211: IMPROVE | Q211: QA nhà máy cảnh báo: no-cross-article-duplicate | R211: Giữ nguyên; theo dõi Search Console (hiển thị, CTR, truy vấn)
A212: https://chatbot.thuexemaynguyentu.com/blog/an-toan/phat-nguoi-va-xe-thue-cho-nguoi-moi/ | B212: BA-0773 | C212: Bài viết | D212: Phạt nguội xe thuê cho người mới: dòng thời gian một vé phạt | E212: 60 | F212: 141 | G212: 1 | H212: 7 | I212: 1864 | J212: Không | K212: Có | L212: 3 | M212: 95 | N212: no-cross-article-duplicate | O212: 97 | P212: IMPROVE | Q212: QA nhà máy cảnh báo: no-cross-article-duplicate | R212: Giữ nguyên; theo dõi Search Console (hiển thị, CTR, truy vấn)
A213: https://chatbot.thuexemaynguyentu.com/blog/an-toan/phat-nguoi-va-xe-thue-tom-tat/ | B213: BA-1055 | C213: Bài viết | D213: Tóm tắt phạt nguội xe thuê: ai bị phạt và năm việc nên làm | E213: 58 | F213: 145 | G213: 1 | H213: 7 | I213: 1236 | J213: Không | K213: Có | L213: 2 | M213: 95 | N213: no-cross-article-duplicate | O213: 92 | P213: IMPROVE | Q213: QA nhà máy cảnh báo: no-cross-article-duplicate | R213: Giữ nguyên; theo dõi Search Console (hiển thị, CTR, truy vấn)
A214: https://chatbot.thuexemaynguyentu.com/blog/an-toan/phat-nguoi-va-xe-thue-vi-du-thuc-te/ | B214: BA-1337 | C214: Bài viết | D214: Ví dụ phạt nguội xe thuê: năm tình huống và bộ hồ sơ nên giữ | E214: 60 | F214: 158 | G214: 1 | H214: 6 | I214: 1510 | J214: Không | K214: Có | L214: 2 | M214: 100 | N214: Không | O214: 97 | P214: KEEP | Q214: QA proxy ≥ 85, không cờ mở, không cảnh báo nội dung | R214: Giữ nguyên; theo dõi Search Console (hiển thị, CTR, truy vấn)
A215: https://chatbot.thuexemaynguyentu.com/blog/an-toan/phat-nguoi-va-xe-thue/ | B215: BA-0209 | C215: Bài viết | D215: Phạt nguội xe thuê: ai bị liên hệ trước và việc nên làm | E215: 55 | F215: 150 | G215: 1 | H215: 6 | I215: 1189 | J215: Không | K215: Có | L215: 1 | M215: 100 | N215: Không | O215: 97 | P215: KEEP | Q215: QA proxy ≥ 85, không cờ mở, không cảnh báo nội dung | R215: Giữ nguyên; theo dõi Search Console (hiển thị, CTR, truy vấn)
A216: https://chatbot.thuexemaynguyentu.com/blog/an-toan/quy-dinh-mu-bao-hiem-tre-em-cho-du-khach/ | B216: BA-0437 | C216: Bài viết | D216: Quy định mũ bảo hiểm trẻ em cho du khách: mũ đạt chuẩn cho bé | E216: 61 | F216: 154 | G216: 1 | H216: 6 | I216: 1442 | J216: Không | K216: Có | L216: 1 | M216: 100 | N216: Không | O216: 94 | P216: KEEP | Q216: QA proxy ≥ 85, không cờ mở, không cảnh báo nội dung | R216: Giữ nguyên; theo dõi Search Console (hiển thị, CTR, truy vấn)
A217: https://chatbot.thuexemaynguyentu.com/blog/an-toan/quy-dinh-mu-bao-hiem-tre-em-cho-nguoi-moi/ | B217: BA-0719 | C217: Bài viết | D217: Mũ bảo hiểm trẻ em cho người mới chở con: bốn bước kiểm mũ | E217: 58 | F217: 149 | G217: 1 | H217: 6 | I217: 1439 | J217: Không | K217: Có | L217: 1 | M217: 95 | N217: no-cross-article-duplicate | O217: 94 | P217: IMPROVE | Q217: QA nhà máy cảnh báo: no-cross-article-duplicate | R217: Giữ nguyên; theo dõi Search Console (hiển thị, CTR, truy vấn)
A218: https://chatbot.thuexemaynguyentu.com/blog/an-toan/quy-dinh-mu-bao-hiem-tre-em-tom-tat/ | B218: BA-1001 | C218: Bài viết | D218: Tóm tắt quy định mũ bảo hiểm trẻ em: ai đội, ai chịu phạt | E218: 57 | F218: 148 | G218: 1 | H218: 7 | I218: 1475 | J218: Không | K218: Có | L218: 2 | M218: 100 | N218: Không | O218: 94 | P218: KEEP | Q218: QA proxy ≥ 85, không cờ mở, không cảnh báo nội dung | R218: Giữ nguyên; theo dõi Search Console (hiển thị, CTR, truy vấn)
A219: https://chatbot.thuexemaynguyentu.com/blog/an-toan/quy-dinh-mu-bao-hiem-tre-em-vi-du-thuc-te/ | B219: BA-1283 | C219: Bài viết | D219: Ví dụ quy định mũ bảo hiểm trẻ em: năm tình huống khi chở bé | E219: 60 | F219: 154 | G219: 1 | H219: 9 | I219: 1500 | J219: Không | K219: Có | L219: 2 | M219: 100 | N219: Không | O219: 92 | P219: KEEP | Q219: QA proxy ≥ 85, không cờ mở, không cảnh báo nội dung | R219: Giữ nguyên; theo dõi Search Console (hiển thị, CTR, truy vấn)
A220: https://chatbot.thuexemaynguyentu.com/blog/an-toan/quy-dinh-mu-bao-hiem-tre-em/ | B220: BA-0155 | C220: Bài viết | D220: Quy định mũ bảo hiểm trẻ em: tiêu chuẩn, mức phạt, cách chọn | E220: 60 | F220: 156 | G220: 1 | H220: 6 | I220: 1096 | J220: Không | K220: Có | L220: 1 | M220: 100 | N220: Không | O220: 97 | P220: KEEP | Q220: QA proxy ≥ 85, không cờ mở, không cảnh báo nội dung | R220: Giữ nguyên; theo dõi Search Console (hiển thị, CTR, truy vấn)
A221: https://chatbot.thuexemaynguyentu.com/blog/an-toan/quyen-cua-nguoi-thue-xe-cho-du-khach/ | B221: BA-0539 | C221: Bài viết | D221: Quyền của du khách khi thuê xe máy: bốn quyền cốt lõi | E221: 53 | F221: 158 | G221: 1 | H221: 6 | I221: 1347 | J221: Không | K221: Có | L221: 1 | M221: 100 | N221: Không | O221: 97 | P221: KEEP | Q221: QA proxy ≥ 85, không cờ mở, không cảnh báo nội dung | R221: Giữ nguyên; theo dõi Search Console (hiển thị, CTR, truy vấn)
A222: https://chatbot.thuexemaynguyentu.com/blog/an-toan/quyen-cua-nguoi-thue-xe-cho-nguoi-moi/ | B222: BA-0821 | C222: Bài viết | D222: Quyền của người mới thuê xe máy: từ lúc đặt xe đến khi trả cọc | E222: 62 | F222: 155 | G222: 1 | H222: 8 | I222: 1585 | J222: Không | K222: Có | L222: 2 | M222: 100 | N222: Không | O222: 94 | P222: KEEP | Q222: QA proxy ≥ 85, không cờ mở, không cảnh báo nội dung | R222: Giữ nguyên; theo dõi Search Console (hiển thị, CTR, truy vấn)
... A225: https://chatbot.thuexemaynguyentu.com/blog/an-toan/quyen-cua-nguoi-thue-xe/ | B225: BA-0257 | C225: Bài viết | D225: Quyền của người thuê xe máy: dùng ổn định, sửa chữa, nhận cọc | E225: 61 | F225: 150 | G225: 1 | H225: 7 | I225: 1491 | J225: Không | K225: Không | L225: 1 | M225: 90 | N225: body-structure, title-meta-valid | O225: 94 | P225: IMPROVE | Q225: QA nhà máy cảnh báo: body-structure, title-meta-valid | R225: Giữ nguyên; theo dõi Search Console (hiển thị, CTR, truy vấn)
A226: https://chatbot.thuexemaynguyentu.com/blog/an-toan/su-co/ | B226: N/A | C226: Hub chủ đề con | D226: Sự Cố — An toàn / pháp lý — Cẩm nang thuê xe máy | E226: 48 | F226: 139 | G226: 1 | H226: 12 | I226: 710 | J226: Không | K226: Không | L226: 0 | M226: N/A | N226: N/A | O226: 87 | P226: KEEP | Q226: QA proxy ≥ 85, không cờ mở, không cảnh báo nội dung | R226: Giữ nguyên; theo dõi Search Console (hiển thị, CTR, truy vấn)
A227: https://chatbot.thuexemaynguyentu.com/blog/an-toan/suong-mu-mua-dong-cho-du-khach/ | B227: BA-0389 | C227: Bài viết | D227: Du khách đi xe máy trong sương mù mùa đông: đèn, đi hay chờ | E227: 59 | F227: 158 | G227: 1 | H227: 6 | I227: 1359 | J227: Không | K227: Có | L227: 1 | M227: 100 | N227: Không | O227: 97 | P227: KEEP | Q227: QA proxy ≥ 85, không cờ mở, không cảnh báo nội dung | R227: Giữ nguyên; theo dõi Search Console (hiển thị, CTR, truy vấn)
A228: https://chatbot.thuexemaynguyentu.com/blog/an-toan/suong-mu-mua-dong-cho-nguoi-moi/ | B228: BA-0671 | C228: Bài viết | D228: Người mới lái xe máy trong sương mù: quy định và bốn kỹ thuật | E228: 61 | F228: 154 | G228: 1 | H228: 7 | I228: 1510 | J228: Không | K228: Có | L228: 1 | M228: 95 | N228: no-cross-article-duplicate | O228: 97 | P228: IMPROVE | Q228: QA nhà máy cảnh báo: no-cross-article-duplicate | R228: Giữ nguyên; theo dõi Search Console (hiển thị, CTR, truy vấn)
...

Sheet TECHNICAL SEO AUDIT
A1: Mã | B1: Nhóm | C1: Kiểm tra | D1: Phạm vi | E1: Số lỗi | F1: Giá trị đo | G1: Ngưỡng | H1: Trạng thái | I1: Chuẩn tham chiếu | J1: Hành động | K1: Ưu tiên
A2: T01 | B2: Crawl | C2: robots.txt cho phép crawl + khai báo sitemap | D2: site | E2: 0 | F2: N/A | G2: N/A | H2: PASS | I2: Search Essentials | J2: Giữ | K2: P0
A3: T02 | B3: Index | C3: Trang có meta robots noindex | D3: 2169 trang | E3: 0 | F3: N/A | G3: N/A | H3: PASS | I3: Search Essentials | J3: Không noindex trang có giá trị | K3: P0
A4: T03 | B4: Index | C4: Canonical tự tham chiếu đúng URL sạch | D4: 2169 trang | E4: 0 | F4: N/A | G4: N/A | H4: PASS | I4: Canonicalization | J4: Giữ | K4: P0
A5: T04 | B5: Index | C5: URL trong sitemap không có file build | D5: 2169 URL | E5: 0 | F5: N/A | G5: N/A | H5: PASS | I5: Sitemaps | J5: Giữ đồng bộ | K5: P0
A6: T05 | B6: Index | C6: Trang build không có trong sitemap | D6: 2169 trang | E6: 0 | F6: N/A | G6: N/A | H6: PASS | I6: Sitemaps | J6: Giữ đồng bộ | K6: P1
A7: T06 | B7: Links | C7: Liên kết nội bộ hỏng | D7: 2169 trang | E7: 0 | F7: N/A | G7: N/A | H7: PASS | I7: SEO Starter Guide | J7: Sửa link | K7: P0
A8: T07 | B8: Links | C8: Trang mồ côi (0 liên kết vào từ nội dung, chỉ có menu/chân trang hoặc không có) | D8: 2169 trang | E8: 0 | F8: N/A | G8: N/A | H8: PASS | I8: SEO Starter Guide | J8: Thêm liên kết ngữ cảnh | K8: P1
A9: T08 | B9: Links | C9: Độ sâu click > 4 từ trang chủ | D9: 2169 trang | E9: 0 | F9: 3 | G9: ≤ 4 | H9: PASS | I9: SEO Starter Guide | J9: Giữ ≤ 3–4 | K9: P1
A10: T09 | B10: On-page | C10: Không đúng 1 H1 | D10: 2169 trang | E10: 0 | F10: N/A | G10: N/A | H10: PASS | I10: SEO Starter Guide | J10: Giữ 1 H1 | K10: P1
A11: T10 | B11: On-page | C11: Title ngoài 30–70 ký tự | D11: 2169 trang | E11: 0 | F11: N/A | G11: N/A | H11: PASS | I11: Title links | J11: Sửa qua data/seo/article-meta.json | K11: P2
A12: T11 | B12: On-page | C12: Meta description ngoài 100–180 ký tự | D12: 2169 trang | E12: 0 | F12: N/A | G12: N/A | H12: PASS | I12: Snippets | J12: Sửa qua article-meta.json | K12: P2
A13: T12 | B13: On-page | C13: Title trùng nhau | D13: 2169 trang | E13: 0 | F13: N/A | G13: N/A | H13: PASS | I13: Title links | J13: Title duy nhất | K13: P1
A14: T13 | B14: On-page | C14: Meta description trùng nhau | D14: 2169 trang | E14: 0 | F14: N/A | G14: N/A | H14: PASS | I14: Snippets | J14: Mô tả duy nhất | K14: P2
A15: T14 | B15: International | C15: Thuộc tính lang khác "vi" | D15: 2169 trang | E15: 0 | F15: N/A | G15: N/A | H15: PASS | I15: Localized versions | J15: Giữ lang="vi" | K15: P2
A16: T15 | B16: Structured data | C16: Khối JSON-LD lỗi cú pháp | D16: 2169 trang | E16: 0 | F16: N/A | G16: N/A | H16: PASS | I16: Structured data guidelines | J16: Sửa builder | K16: P0
A17: T16 | B17: Structured data | C17: Thiếu thuộc tính khuyến nghị/bắt buộc (Article, Breadcrumb, LocalBusiness, Organization) | D17: 2169 trang | E17: 0 | F17: N/A | G17: N/A | H17: PASS | I17: Structured data docs | J17: Bổ sung từ dữ liệu thật | K17: P2
A18: T17 | B18: Images | C18: Ảnh trong nội dung thiếu alt | D18: 60 ảnh | E18: 0 | F18: N/A | G18: N/A | H18: PASS | I18: Image SEO | J18: Thêm alt mô tả | K18: P1
A19: T18 | B19: Images/CLS | C19: Ảnh thiếu width/height | D19: 60 ảnh | E19: 0 | F19: N/A | G19: N/A | H19: PASS | I19: Web Vitals (CLS) | J19: Khai báo kích thước | K19: P1
A20: T19 | B20: Security | C20: Tài nguyên http:// (mixed content) | D20: 2169 trang | E20: 0 | F20: N/A | G20: N/A | H20: PASS | I20: HTTPS | J20: Dùng https | K20: P1
A21: T20 | B21: Performance | C21: HTML > 100 KB (hub chủ đề con liệt kê toàn bộ bài trên một trang, không phân trang) | D21: 2169 trang | E21: 0 | F21: 69.6 | G21: ≤ 100 KB | H21: PASS | I21: web.dev (DOM lớn → INP) | J21: Giữ | K21: P2
A22: T21 | B22: Performance | C22: CSS tải trên một trang (stylesheet liên kết, chưa nén) | D22: 2169 trang | E22: 0 | F22: 85.6 | G22: < 64 KB (khuyến nghị nội bộ) | H22: WARN | I22: tools/seo-score.mjs cảnh báo ≥ 64 KB | J22: Theo dõi; chỉ tách CSS nếu LCP lab/field xấu đi | K22: P3
A23: T22 | B23: Search Console | C23: Thẻ google-site-verification trên trang chủ / | D23: / | E23: 0 | F23: N/A | G23: N/A | H23: PASS | I23: Search Console verification (kiểm tra định kỳ) | J23: Đã khôi phục ở lô C07b (build-blog đọc từ data/site/agent.html.tpl) | K23: P0
A24: T23 | B24: Index | C24: URL dạng /index.html xuất hiện trong SERP chụp 2026-10-14: /blog/thue-xe/cho-thue-xe-may-thu-tuc-don-gian/index.html, /blog/thue-xe/hong-xe-giua-duong-khi-thue/index.html | D24: 2 URL | E24: 2 | F24: N/A | G24: N/A | H24: WARN | I24: Canonicalization | J24: Trang có canonical về URL sạch; 0 link nội bộ dùng index.html; sitemap không chứa index.html. Kiểm tra canonical Google chọn bằng URL Inspection khi có GSC | K24: P3
A25: T24 | B25: Search Console | C25: Dữ liệu Search Console (Coverage, Performance, CWV field) | D25: site | E25: 1 | F25: N/A | G25: N/A | H25: N/A | I25: Search Console | J25: Owner kết nối GSC (tài sản Domain) và xuất dữ liệu vào data/seo/performance/ | K25: P0
A26: CWV01-LCP | B26: Core Web Vitals (LAB) | C26: LCP lab (ms) — Trang chủ | D26: / | E26: 0 | F26: 752 | G26: ≤ 2500 | H26: PASS | I26: web.dev/articles/vitals (ngưỡng p75 field) | J26: LAB — không thay dữ liệu field (CrUX/GSC: N/A) | K26: P2
A27: CWV01-CLS | B27: Core Web Vitals (LAB) | C27: CLS lab — Trang chủ | D27: / | E27: 0 | F27: 0.016 | G27: ≤ 0.1 | H27: PASS | I27: web.dev/articles/vitals (ngưỡng p75 field) | J27: LAB — không thay dữ liệu field (CrUX/GSC: N/A) | K27: P2
A28: CWV01-INTERACTION | B28: Core Web Vitals (LAB) | C28: Tương tác chạm menu lab (ms, proxy INP) — Trang chủ | D28: / | E28: 0 | F28: 160 | G28: ≤ 200 | H28: PASS | I28: web.dev/articles/vitals (ngưỡng p75 field) | J28: LAB — không thay dữ liệu field (CrUX/GSC: N/A) | K28: P2
A29: CWV01-TBT | B29: Core Web Vitals (LAB) | C29: TBT lab (ms) — Trang chủ | D29: / | E29: 0 | F29: 47 | G29: ≤ 200 | H29: PASS | I29: web.dev/articles/vitals (ngưỡng p75 field) | J29: LAB — không thay dữ liệu field (CrUX/GSC: N/A) | K29: P2
A30: CWV02-LCP | B30: Core Web Vitals (LAB) | C30: LCP lab (ms) — Trang giá (chuyển đổi) | D30: /gia-thue/ | E30: 0 | F30: 756 | G30: ≤ 2500 | H30: PASS | I30: web.dev/articles/vitals (ngưỡng p75 field) | J30: LAB — không thay dữ liệu field (CrUX/GSC: N/A) | K30: P2
A31: CWV02-CLS | B31: Core Web Vitals (LAB) | C31: CLS lab — Trang giá (chuyển đổi) | D31: /gia-thue/ | E31: 0 | F31: 0 | G31: ≤ 0.1 | H31: PASS | I31: web.dev/articles/vitals (ngưỡng p75 field) | J31: LAB — không thay dữ liệu field (CrUX/GSC: N/A) | K31: P2
A32: CWV02-INTERACTION | B32: Core Web Vitals (LAB) | C32: Tương tác chạm menu lab (ms, proxy INP) — Trang giá (chuyển đổi) | D32: /gia-thue/ | E32: 0 | F32: 96 | G32: ≤ 200 | H32: PASS | I32: web.dev/articles/vitals (ngưỡng p75 field) | J32: LAB — không thay dữ liệu field (CrUX/GSC: N/A) | K32: P2
A33: CWV02-TBT | B33: Core Web Vitals (LAB) | C33: TBT lab (ms) — Trang giá (chuyển đổi) | D33: /gia-thue/ | E33: 0 | F33: 29 | G33: ≤ 200 | H33: PASS | I33: web.dev/articles/vitals (ngưỡng p75 field) | J33: LAB — không thay dữ liệu field (CrUX/GSC: N/A) | K33: P2
A34: CWV03-LCP | B34: Core Web Vitals (LAB) | C34: LCP lab (ms) — Trang liên hệ (chuyển đổi) | D34: /lien-he/ | E34: 0 | F34: 668 | G34: ≤ 2500 | H34: PASS | I34: web.dev/articles/vitals (ngưỡng p75 field) | J34: LAB — không thay dữ liệu field (CrUX/GSC: N/A) | K34: P2
A35: CWV03-CLS | B35: Core Web Vitals (LAB) | C35: CLS lab — Trang liên hệ (chuyển đổi) | D35: /lien-he/ | E35: 0 | F35: 0 | G35: ≤ 0.1 | H35: PASS | I35: web.dev/articles/vitals (ngưỡng p75 field) | J35: LAB — không thay dữ liệu field (CrUX/GSC: N/A) | K35: P2
A36: CWV03-INTERACTION | B36: Core Web Vitals (LAB) | C36: Tương tác chạm menu lab (ms, proxy INP) — Trang liên hệ (chuyển đổi) | D36: /lien-he/ | E36: 0 | F36: 96 | G36: ≤ 200 | H36: PASS | I36: web.dev/articles/vitals (ngưỡng p75 field) | J36: LAB — không thay dữ liệu field (CrUX/GSC: N/A) | K36: P2
A37: CWV03-TBT | B37: Core Web Vitals (LAB) | C37: TBT lab (ms) — Trang liên hệ (chuyển đổi) | D37: /lien-he/ | E37: 0 | F37: 24 | G37: ≤ 200 | H37: PASS | I37: web.dev/articles/vitals (ngưỡng p75 field) | J37: LAB — không thay dữ liệu field (CrUX/GSC: N/A) | K37: P2
... A61: CWV09-TBT | B61: Core Web Vitals (LAB) | C61: TBT lab (ms) — Bài viết (có ảnh đại diện) | D61: /blog/app/app-thue-xe-may-la-gi/ | E61: 0 | F61: 21 | G61: ≤ 200 | H61: PASS | I61: web.dev/articles/vitals (ngưỡng p75 field) | J61: LAB — không thay dữ liệu field (CrUX/GSC: N/A) | K61: P2

Sheet INDEX & SITEMAP
A1: robots.txt: User-agent: * | Allow: / | Sitemap: https://chatbot.thuexemaynguyentu.com/sitemap.xml — IndexNow: tools/indexnow.mjs + .github/workflows/indexnow.yml.
A2: URL | B2: Loại trang | C2: Trong sitemap | D2: lastmod | E2: Ảnh trong image sitemap | F2: Indexability | G2: Canonical | H2: robots.txt | I2: HTTP live (ngày) | J2: Trạng thái index GSC | K2: Nguồn thiếu
A3: https://chatbot.thuexemaynguyentu.com/ | B3: Trang chủ (website) | C3: Có | D3: N/A | E3: 0 | F3: indexable | G3: self | H3: allowed | I3: 200 (2026-10-29) | J3: N/A | K3: N/A — thiếu nguồn: Google Search Console chưa kết nối (OpenSEO 0 tài khoản Google; data/seo/performance/ trống)
A4: https://chatbot.thuexemaynguyentu.com/agent/ | B4: Ứng dụng Agent (chat) | C4: Có | D4: N/A | E4: 0 | F4: indexable | G4: self | H4: allowed | I4: 200 (2026-10-29) | J4: N/A | K4: N/A — thiếu nguồn: Google Search Console chưa kết nối (OpenSEO 0 tài khoản Google; data/seo/performance/ trống)
A5: https://chatbot.thuexemaynguyentu.com/blog/ | B5: Blog home | C5: Có | D5: 2026-11-01 | E5: 0 | F5: indexable | G5: self | H5: allowed | I5: 200 (2026-10-28) | J5: N/A | K5: N/A — thiếu nguồn: Google Search Console chưa kết nối (OpenSEO 0 tài khoản Google; data/seo/performance/ trống)
A6: https://chatbot.thuexemaynguyentu.com/chinh-sach/ | B6: Trang chính sách thuê xe | C6: Có | D6: N/A | E6: 0 | F6: indexable | G6: self | H6: allowed | I6: 200 (2026-10-28) | J6: N/A | K6: N/A — thiếu nguồn: Google Search Console chưa kết nối (OpenSEO 0 tài khoản Google; data/seo/performance/ trống)
A7: https://chatbot.thuexemaynguyentu.com/doi-tac/ | B7: Trang đối tác (B2B) | C7: Có | D7: N/A | E7: 0 | F7: indexable | G7: self | H7: allowed | I7: Chưa kiểm tra live trong lô này | J7: N/A | K7: N/A — thiếu nguồn: Google Search Console chưa kết nối (OpenSEO 0 tài khoản Google; data/seo/performance/ trống)
A8: https://chatbot.thuexemaynguyentu.com/gia-thue/ | B8: Trang chuyển đổi (giá) | C8: Có | D8: N/A | E8: 0 | F8: indexable | G8: self | H8: allowed | I8: 200 (2026-10-28) | J8: N/A | K8: N/A — thiếu nguồn: Google Search Console chưa kết nối (OpenSEO 0 tài khoản Google; data/seo/performance/ trống)
A9: https://chatbot.thuexemaynguyentu.com/gioi-thieu/ | B9: Trang giới thiệu (E-E-A-T) | C9: Có | D9: N/A | E9: 0 | F9: indexable | G9: self | H9: allowed | I9: 200 (2026-10-28) | J9: N/A | K9: N/A — thiếu nguồn: Google Search Console chưa kết nối (OpenSEO 0 tài khoản Google; data/seo/performance/ trống)
A10: https://chatbot.thuexemaynguyentu.com/lien-he/ | B10: Trang chuyển đổi (liên hệ) | C10: Có | D10: N/A | E10: 0 | F10: indexable | G10: self | H10: allowed | I10: 200 (2026-10-28) | J10: N/A | K10: N/A — thiếu nguồn: Google Search Console chưa kết nối (OpenSEO 0 tài khoản Google; data/seo/performance/ trống)
A11: https://chatbot.thuexemaynguyentu.com/privacy/ | B11: Pháp lý | C11: Có | D11: N/A | E11: 0 | F11: indexable | G11: self | H11: allowed | I11: Chưa kiểm tra live trong lô này | J11: N/A | K11: N/A — thiếu nguồn: Google Search Console chưa kết nối (OpenSEO 0 tài khoản Google; data/seo/performance/ trống)
A12: https://chatbot.thuexemaynguyentu.com/terms/ | B12: Pháp lý | C12: Có | D12: N/A | E12: 0 | F12: indexable | G12: self | H12: allowed | I12: Chưa kiểm tra live trong lô này | J12: N/A | K12: N/A — thiếu nguồn: Google Search Console chưa kết nối (OpenSEO 0 tài khoản Google; data/seo/performance/ trống)
A13: https://chatbot.thuexemaynguyentu.com/blog/an-toan/ | B13: Hub danh mục | C13: Có | D13: 2026-11-01 | E13: 0 | F13: indexable | G13: self | H13: allowed | I13: Chưa kiểm tra live trong lô này | J13: N/A | K13: N/A — thiếu nguồn: Google Search Console chưa kết nối (OpenSEO 0 tài khoản Google; data/seo/performance/ trống)
A14: https://chatbot.thuexemaynguyentu.com/blog/app/ | B14: Hub danh mục | C14: Có | D14: 2026-11-01 | E14: 0 | F14: indexable | G14: self | H14: allowed | I14: Chưa kiểm tra live trong lô này | J14: N/A | K14: N/A — thiếu nguồn: Google Search Console chưa kết nối (OpenSEO 0 tài khoản Google; data/seo/performance/ trống)
